[
{
    "0_key": "клиентский запрос",
    "1_textForm": "клиентские запросы",
    "2_modelName": "Прил + С",
    "3_docNum": 691996,
    "4_sentNum": 3,
    "5_start_ind": 7,
    "6_end_ind": 8,
    "7_lemmas": [
        "0_запрос",
        "1_клиентский"
    ]
},
{
    "0_key": "beeline чат-бот",
    "1_textForm": "Beeline чат-бота",
    "2_modelName": "Прил + С",
    "3_docNum": 691996,
    "4_sentNum": 3,
    "5_start_ind": 13,
    "6_end_ind": 14,
    "7_lemmas": [
        "0_чат-бот",
        "1_beeline"
    ]
},
{
    "0_key": "понимание клиент",
    "1_textForm": "понимание клиента",
    "2_modelName": "С + Срд",
    "3_docNum": 691996,
    "4_sentNum": 4,
    "5_start_ind": 2,
    "6_end_ind": 3,
    "7_lemmas": [
        "0_понимание",
        "1_клиент"
    ]
},
{
    "0_key": "текстовый запрос",
    "1_textForm": "текстовый запрос",
    "2_modelName": "Прил + С",
    "3_docNum": 691996,
    "4_sentNum": 4,
    "5_start_ind": 12,
    "6_end_ind": 13,
    "7_lemmas": [
        "0_запрос",
        "1_текстовый"
    ]
},
{
    "0_key": "текстовый запрос с описание",
    "1_textForm": "текстовый запрос с описанием",
    "2_modelName": "(Прил + С) + Предл + С",
    "3_docNum": 691996,
    "4_sentNum": 4,
    "5_start_ind": 12,
    "6_end_ind": 15,
    "7_lemmas": [
        "0_запрос",
        "1_текстовый",
        "2_с",
        "3_описание"
    ]
},
{
    "0_key": "намерение клиент",
    "1_textForm": "Намерение клиента",
    "2_modelName": "С + Срд",
    "3_docNum": 691996,
    "4_sentNum": 5,
    "5_start_ind": 0,
    "6_end_ind": 1,
    "7_lemmas": [
        "0_намерение",
        "1_клиент"
    ]
},
{
    "0_key": "текстовый запрос",
    "1_textForm": "текстовом запросе",
    "2_modelName": "Прил + С",
    "3_docNum": 691996,
    "4_sentNum": 5,
    "5_start_ind": 3,
    "6_end_ind": 4,
    "7_lemmas": [
        "0_запрос",
        "1_текстовый"
    ]
},
{
    "0_key": "намерение клиент в текстовый запрос",
    "1_textForm": "Намерение клиента в текстовом запросе",
    "2_modelName": "(С + Срд) + Предл + (Прил + С)",
    "3_docNum": 691996,
    "4_sentNum": 5,
    "5_start_ind": 0,
    "6_end_ind": 4,
    "7_lemmas": [
        "0_намерение",
        "1_клиент",
        "2_в",
        "3_текстовый",
        "4_запрос"
    ]
},
{
    "0_key": "клиент в текстовый запрос",
    "1_textForm": "клиента в текстовом запросе",
    "2_modelName": "С + Предл + (Прил + С)",
    "3_docNum": 691996,
    "4_sentNum": 5,
    "5_start_ind": 1,
    "6_end_ind": 4,
    "7_lemmas": [
        "0_запрос",
        "1_текстовый",
        "2_в",
        "3_клиент"
    ]
},
{
    "0_key": "дополненный инсайт",
    "1_textForm": "дополненными инсайтами",
    "2_modelName": "Прич + С",
    "3_docNum": 691996,
    "4_sentNum": 7,
    "5_start_ind": 2,
    "6_end_ind": 3,
    "7_lemmas": [
        "0_инсайт",
        "1_дополненный"
    ]
},
{
    "0_key": "дополненный инсайт и лайфхак",
    "1_textForm": "дополненными инсайтами и лайфхаками",
    "2_modelName": "(Прич + С) + СоюзИ + С",
    "3_docNum": 691996,
    "4_sentNum": 7,
    "5_start_ind": 2,
    "6_end_ind": 5,
    "7_lemmas": [
        "0_инсайт",
        "1_дополненный",
        "2_и",
        "3_лайфхак"
    ]
},
{
    "0_key": "первоначальный чат-бот",
    "1_textForm": "Первоначальный чат-бот",
    "2_modelName": "Прил + С",
    "3_docNum": 691996,
    "4_sentNum": 8,
    "5_start_ind": 0,
    "6_end_ind": 1,
    "7_lemmas": [
        "0_чат-бот",
        "1_первоначальный"
    ]
},
{
    "0_key": "вводный данный",
    "1_textForm": "вводные данные",
    "2_modelName": "Прил + С",
    "3_docNum": 691996,
    "4_sentNum": 8,
    "5_start_ind": 3,
    "6_end_ind": 4,
    "7_lemmas": [
        "0_данный",
        "1_вводный"
    ]
},
{
    "0_key": "постановка задача",
    "1_textForm": "постановки задачи",
    "2_modelName": "С + Срд",
    "3_docNum": 691996,
    "4_sentNum": 9,
    "5_start_ind": 10,
    "6_end_ind": 11,
    "7_lemmas": [
        "0_постановка",
        "1_задача"
    ]
},
{
    "0_key": "итоговый модель",
    "1_textForm": "итоговой модели",
    "2_modelName": "Прил + С",
    "3_docNum": 691996,
    "4_sentNum": 9,
    "5_start_ind": 13,
    "6_end_ind": 14,
    "7_lemmas": [
        "0_модель",
        "1_итоговый"
    ]
},
{
    "0_key": "постановка задача до итоговый модель",
    "1_textForm": "постановки задачи до итоговой модели",
    "2_modelName": "(С + Срд) + Предл + (Прил + С)",
    "3_docNum": 691996,
    "4_sentNum": 9,
    "5_start_ind": 10,
    "6_end_ind": 14,
    "7_lemmas": [
        "0_постановка",
        "1_задача",
        "2_до",
        "3_итоговый",
        "4_модель"
    ]
},
{
    "0_key": "задача до итоговый модель",
    "1_textForm": "задачи до итоговой модели",
    "2_modelName": "С + Предл + (Прил + С)",
    "3_docNum": 691996,
    "4_sentNum": 9,
    "5_start_ind": 11,
    "6_end_ind": 14,
    "7_lemmas": [
        "0_модель",
        "1_итоговый",
        "2_до",
        "3_задача"
    ]
},
{
    "0_key": "условный итерация",
    "1_textForm": "условных итераций",
    "2_modelName": "Прил + С",
    "3_docNum": 691996,
    "4_sentNum": 10,
    "5_start_ind": 4,
    "6_end_ind": 5,
    "7_lemmas": [
        "0_итерация",
        "1_условный"
    ]
},
{
    "0_key": "полноценный модель",
    "1_textForm": "полноценную модель",
    "2_modelName": "Прил + С",
    "3_docNum": 691996,
    "4_sentNum": 10,
    "5_start_ind": 14,
    "6_end_ind": 15,
    "7_lemmas": [
        "0_модель",
        "1_полноценный"
    ]
},
{
    "0_key": "продуктив полноценный модель",
    "1_textForm": "продуктив полноценную модель",
    "2_modelName": "C + (Прил + С)рд",
    "3_docNum": 691996,
    "4_sentNum": 10,
    "5_start_ind": 13,
    "6_end_ind": 15,
    "7_lemmas": [
        "0_модель",
        "1_полноценный",
        "2_продуктив"
    ]
},
{
    "0_key": "постановка задача",
    "1_textForm": "постановке задачи",
    "2_modelName": "С + Срд",
    "3_docNum": 691996,
    "4_sentNum": 12,
    "5_start_ind": 5,
    "6_end_ind": 6,
    "7_lemmas": [
        "0_постановка",
        "1_задача"
    ]
},
{
    "0_key": "сценарный чат-бот",
    "1_textForm": "сценарный чат-бот",
    "2_modelName": "Прил + С",
    "3_docNum": 691996,
    "4_sentNum": 13,
    "5_start_ind": 18,
    "6_end_ind": 19,
    "7_lemmas": [
        "0_чат-бот",
        "1_сценарный"
    ]
},
{
    "0_key": "кнопочный и сценарный чат-бот",
    "1_textForm": "кнопочный и сценарный чат-бот",
    "2_modelName": "Прил и (Прил + С)",
    "3_docNum": 691996,
    "4_sentNum": 13,
    "5_start_ind": 16,
    "6_end_ind": 19,
    "7_lemmas": [
        "0_чат-бот",
        "1_сценарный",
        "2_и",
        "3_кнопочный"
    ]
},
{
    "0_key": "статичный сценарий",
    "1_textForm": "статичные сценарии",
    "2_modelName": "Прил + С",
    "3_docNum": 691996,
    "4_sentNum": 14,
    "5_start_ind": 2,
    "6_end_ind": 3,
    "7_lemmas": [
        "0_сценарий",
        "1_статичный"
    ]
},
{
    "0_key": "содержадый статичный сценарий",
    "1_textForm": "содержада статичные сценарии",
    "2_modelName": "Прил + С",
    "3_docNum": 691996,
    "4_sentNum": 14,
    "5_start_ind": 1,
    "6_end_ind": 3,
    "7_lemmas": [
        "0_сценарий",
        "1_статичный",
        "2_содержадый"
    ]
},
{
    "0_key": "история обращение",
    "1_textForm": "историю обращений",
    "2_modelName": "С + Срд",
    "3_docNum": 691996,
    "4_sentNum": 14,
    "5_start_ind": 5,
    "6_end_ind": 6,
    "7_lemmas": [
        "0_история",
        "1_обращение"
    ]
},
{
    "0_key": "история обращение клиент",
    "1_textForm": "историю обращений клиента",
    "2_modelName": "С + Срд",
    "3_docNum": 691996,
    "4_sentNum": 14,
    "5_start_ind": 5,
    "6_end_ind": 7,
    "7_lemmas": [
        "0_история",
        "1_обращение",
        "2_клиент"
    ]
},
{
    "0_key": "обращение клиент",
    "1_textForm": "обращений клиента",
    "2_modelName": "С + Срд",
    "3_docNum": 691996,
    "4_sentNum": 14,
    "5_start_ind": 6,
    "6_end_ind": 7,
    "7_lemmas": [
        "0_обращение",
        "1_клиент"
    ]
},
{
    "0_key": "текстовый запросо",
    "1_textForm": "текстового запроса",
    "2_modelName": "Прил + С",
    "3_docNum": 691996,
    "4_sentNum": 14,
    "5_start_ind": 14,
    "6_end_ind": 15,
    "7_lemmas": [
        "0_запросо",
        "1_текстовый"
    ]
},
{
    "0_key": "ключевой слов",
    "1_textForm": "ключевых слов",
    "2_modelName": "Прил + С",
    "3_docNum": 691996,
    "4_sentNum": 14,
    "5_start_ind": 18,
    "6_end_ind": 19,
    "7_lemmas": [
        "0_слов",
        "1_ключевой"
    ]
},
{
    "0_key": "статичный сценарий и история",
    "1_textForm": "статичные сценарии и историю",
    "2_modelName": "(Прил + С) + СоюзИ + С",
    "3_docNum": 691996,
    "4_sentNum": 14,
    "5_start_ind": 2,
    "6_end_ind": 5,
    "7_lemmas": [
        "0_сценарий",
        "1_статичный",
        "2_и",
        "3_история"
    ]
},
{
    "0_key": "содержадый статичный сценарий и история",
    "1_textForm": "содержада статичные сценарии и историю",
    "2_modelName": "(Прил + С) + СоюзИ + С",
    "3_docNum": 691996,
    "4_sentNum": 14,
    "5_start_ind": 1,
    "6_end_ind": 5,
    "7_lemmas": [
        "0_сценарий",
        "1_статичный",
        "2_содержадый",
        "3_и",
        "4_история"
    ]
},
{
    "0_key": "сценарий и история обращение клиент",
    "1_textForm": "сценарии и историю обращений клиента",
    "2_modelName": "С + СоюзИ + (С + Срд)",
    "3_docNum": 691996,
    "4_sentNum": 14,
    "5_start_ind": 3,
    "6_end_ind": 7,
    "7_lemmas": [
        "0_история",
        "1_обращение",
        "2_клиент",
        "3_и",
        "4_сценарий"
    ]
},
{
    "0_key": "история обращение клиент к бот",
    "1_textForm": "историю обращений клиента к боту",
    "2_modelName": "(С + Срд) + Предл + С",
    "3_docNum": 691996,
    "4_sentNum": 14,
    "5_start_ind": 5,
    "6_end_ind": 9,
    "7_lemmas": [
        "0_история",
        "1_обращение",
        "2_клиент",
        "3_к",
        "4_бот"
    ]
},
{
    "0_key": "обращение клиент к бот",
    "1_textForm": "обращений клиента к боту",
    "2_modelName": "(С + Срд) + Предл + С",
    "3_docNum": 691996,
    "4_sentNum": 14,
    "5_start_ind": 6,
    "6_end_ind": 9,
    "7_lemmas": [
        "0_обращение",
        "1_клиент",
        "2_к",
        "3_бот"
    ]
},
{
    "0_key": "тематика текстовый запросо",
    "1_textForm": "тематику текстового запроса",
    "2_modelName": "C + (Прил + С)рд",
    "3_docNum": 691996,
    "4_sentNum": 14,
    "5_start_ind": 13,
    "6_end_ind": 15,
    "7_lemmas": [
        "0_запросо",
        "1_текстовый",
        "2_тематика"
    ]
},
{
    "0_key": "сценарий чат-бот",
    "1_textForm": "сценариям чат-бота",
    "2_modelName": "С + Срд",
    "3_docNum": 691996,
    "4_sentNum": 15,
    "5_start_ind": 19,
    "6_end_ind": 20,
    "7_lemmas": [
        "0_сценарий",
        "1_чат-бот"
    ]
},
{
    "0_key": "улучшение чат-бот",
    "1_textForm": "улучшение чат-бот",
    "2_modelName": "С + Срд",
    "3_docNum": 691996,
    "4_sentNum": 16,
    "5_start_ind": 3,
    "6_end_ind": 4,
    "7_lemmas": [
        "0_улучшение",
        "1_чат-бот"
    ]
},
{
    "0_key": "компонента распознавание",
    "1_textForm": "компоненты распознавания",
    "2_modelName": "С + Срд",
    "3_docNum": 691996,
    "4_sentNum": 16,
    "5_start_ind": 6,
    "6_end_ind": 7,
    "7_lemmas": [
        "0_компонента",
        "1_распознавание"
    ]
},
{
    "0_key": "компонента распознавание тематика",
    "1_textForm": "компоненты распознавания тематики",
    "2_modelName": "С + Срд",
    "3_docNum": 691996,
    "4_sentNum": 16,
    "5_start_ind": 6,
    "6_end_ind": 8,
    "7_lemmas": [
        "0_компонента",
        "1_распознавание",
        "2_тематика"
    ]
},
{
    "0_key": "компонента распознавание тематика обращение",
    "1_textForm": "компоненты распознавания тематики обращения",
    "2_modelName": "С + Срд",
    "3_docNum": 691996,
    "4_sentNum": 16,
    "5_start_ind": 6,
    "6_end_ind": 9,
    "7_lemmas": [
        "0_компонента",
        "1_распознавание",
        "2_тематика",
        "3_обращение"
    ]
},
{
    "0_key": "распознавание тематика",
    "1_textForm": "распознавания тематики",
    "2_modelName": "С + Срд",
    "3_docNum": 691996,
    "4_sentNum": 16,
    "5_start_ind": 7,
    "6_end_ind": 8,
    "7_lemmas": [
        "0_распознавание",
        "1_тематика"
    ]
},
{
    "0_key": "распознавание тематика обращение",
    "1_textForm": "распознавания тематики обращения",
    "2_modelName": "С + Срд",
    "3_docNum": 691996,
    "4_sentNum": 16,
    "5_start_ind": 7,
    "6_end_ind": 9,
    "7_lemmas": [
        "0_распознавание",
        "1_тематика",
        "2_обращение"
    ]
},
{
    "0_key": "тематика обращение",
    "1_textForm": "тематики обращения",
    "2_modelName": "С + Срд",
    "3_docNum": 691996,
    "4_sentNum": 16,
    "5_start_ind": 8,
    "6_end_ind": 9,
    "7_lemmas": [
        "0_тематика",
        "1_обращение"
    ]
},
{
    "0_key": "улучшение чат-бот с компонента распознавание",
    "1_textForm": "улучшение чат-бот с компоненты распознавания",
    "2_modelName": "(С + Срд) + Предл + (С + Срд)",
    "3_docNum": 691996,
    "4_sentNum": 16,
    "5_start_ind": 3,
    "6_end_ind": 7,
    "7_lemmas": [
        "0_улучшение",
        "1_чат-бот",
        "2_с",
        "3_компонента",
        "4_распознавание"
    ]
},
{
    "0_key": "чат-бот с компонента распознавание тематика обращение",
    "1_textForm": "чат-бот с компоненты распознавания тематики обращения",
    "2_modelName": "С + Предл + (С + Срд)",
    "3_docNum": 691996,
    "4_sentNum": 16,
    "5_start_ind": 4,
    "6_end_ind": 9,
    "7_lemmas": [
        "0_компонента",
        "1_распознавание",
        "2_тематика",
        "3_обращение",
        "4_с",
        "5_чат-бот"
    ]
},
{
    "0_key": "модель классификация",
    "1_textForm": "модель классификации",
    "2_modelName": "С + Срд",
    "3_docNum": 691996,
    "4_sentNum": 17,
    "5_start_ind": 5,
    "6_end_ind": 6,
    "7_lemmas": [
        "0_модель",
        "1_классификация"
    ]
},
{
    "0_key": "список интент",
    "1_textForm": "список интентов",
    "2_modelName": "С + Срд",
    "3_docNum": 691996,
    "4_sentNum": 18,
    "5_start_ind": 4,
    "6_end_ind": 5,
    "7_lemmas": [
        "0_список",
        "1_интент"
    ]
},
{
    "0_key": "текстовой запрос",
    "1_textForm": "текстовые запросы",
    "2_modelName": "Прил + С",
    "3_docNum": 691996,
    "4_sentNum": 18,
    "5_start_ind": 8,
    "6_end_ind": 9,
    "7_lemmas": [
        "0_запрос",
        "1_текстовой"
    ]
},
{
    "0_key": "запрос клиент",
    "1_textForm": "запросы клиентов",
    "2_modelName": "С + Срд",
    "3_docNum": 691996,
    "4_sentNum": 18,
    "5_start_ind": 9,
    "6_end_ind": 10,
    "7_lemmas": [
        "0_запрос",
        "1_клиент"
    ]
},
{
    "0_key": "текстовой запрос клиент",
    "1_textForm": "текстовые запросы клиентов",
    "2_modelName": "(Прил + С) + Срд",
    "3_docNum": 691996,
    "4_sentNum": 18,
    "5_start_ind": 8,
    "6_end_ind": 10,
    "7_lemmas": [
        "0_запрос",
        "1_текстовой",
        "2_клиент"
    ]
},
{
    "0_key": "запрос клиент с разметка",
    "1_textForm": "запросы клиентов с разметкой",
    "2_modelName": "(С + Срд) + Предл + С",
    "3_docNum": 691996,
    "4_sentNum": 18,
    "5_start_ind": 9,
    "6_end_ind": 12,
    "7_lemmas": [
        "0_запрос",
        "1_клиент",
        "2_с",
        "3_разметка"
    ]
},
{
    "0_key": "встречаемость сценарий",
    "1_textForm": "встречаемости сценариев",
    "2_modelName": "С + Срд",
    "3_docNum": 691996,
    "4_sentNum": 20,
    "5_start_ind": 5,
    "6_end_ind": 6,
    "7_lemmas": [
        "0_встречаемость",
        "1_сценарий"
    ]
},
{
    "0_key": "диалог чат-бот",
    "1_textForm": "диалогах чат-бота",
    "2_modelName": "С + Срд",
    "3_docNum": 691996,
    "4_sentNum": 20,
    "5_start_ind": 8,
    "6_end_ind": 9,
    "7_lemmas": [
        "0_диалог",
        "1_чат-бот"
    ]
},
{
    "0_key": "текстовый запрос",
    "1_textForm": "текстовые запросы",
    "2_modelName": "Прил + С",
    "3_docNum": 691996,
    "4_sentNum": 20,
    "5_start_ind": 13,
    "6_end_ind": 14,
    "7_lemmas": [
        "0_запрос",
        "1_текстовый"
    ]
},
{
    "0_key": "статистика по встречаемость сценарий",
    "1_textForm": "статистику по встречаемости сценариев",
    "2_modelName": "С + Предл + (С + Срд)",
    "3_docNum": 691996,
    "4_sentNum": 20,
    "5_start_ind": 3,
    "6_end_ind": 6,
    "7_lemmas": [
        "0_встречаемость",
        "1_сценарий",
        "2_по",
        "3_статистика"
    ]
},
{
    "0_key": "встречаемость сценарий в диалог чат-бот",
    "1_textForm": "встречаемости сценариев в диалогах чат-бота",
    "2_modelName": "(С + Срд) + Предл + (С + Срд)",
    "3_docNum": 691996,
    "4_sentNum": 20,
    "5_start_ind": 5,
    "6_end_ind": 9,
    "7_lemmas": [
        "0_встречаемость",
        "1_сценарий",
        "2_в",
        "3_диалог",
        "4_чат-бот"
    ]
},
{
    "0_key": "сценарий в диалог чат-бот",
    "1_textForm": "сценариев в диалогах чат-бота",
    "2_modelName": "С + Предл + (С + Срд)",
    "3_docNum": 691996,
    "4_sentNum": 20,
    "5_start_ind": 6,
    "6_end_ind": 9,
    "7_lemmas": [
        "0_диалог",
        "1_чат-бот",
        "2_в",
        "3_сценарий"
    ]
},
{
    "0_key": "доменно-интентной схема",
    "1_textForm": "доменно-интентную схему",
    "2_modelName": "Прил + С",
    "3_docNum": 691996,
    "4_sentNum": 21,
    "5_start_ind": 3,
    "6_end_ind": 4,
    "7_lemmas": [
        "0_схема",
        "1_доменно-интентной"
    ]
},
{
    "0_key": "источник данный",
    "1_textForm": "Источником данных",
    "2_modelName": "С + Срд",
    "3_docNum": 691996,
    "4_sentNum": 25,
    "5_start_ind": 0,
    "6_end_ind": 1,
    "7_lemmas": [
        "0_источник",
        "1_данный"
    ]
},
{
    "0_key": "запрос клиент",
    "1_textForm": "запросы клиентов",
    "2_modelName": "С + Срд",
    "3_docNum": 691996,
    "4_sentNum": 25,
    "5_start_ind": 3,
    "6_end_ind": 4,
    "7_lemmas": [
        "0_запрос",
        "1_клиент"
    ]
},
{
    "0_key": "русский язык",
    "1_textForm": "русском языке",
    "2_modelName": "Прил + С",
    "3_docNum": 691996,
    "4_sentNum": 25,
    "5_start_ind": 6,
    "6_end_ind": 7,
    "7_lemmas": [
        "0_язык",
        "1_русский"
    ]
},
{
    "0_key": "запрос клиент на русский язык",
    "1_textForm": "запросы клиентов на русском языке",
    "2_modelName": "(С + Срд) + Предл + (Прил + С)",
    "3_docNum": 691996,
    "4_sentNum": 25,
    "5_start_ind": 3,
    "6_end_ind": 7,
    "7_lemmas": [
        "0_запрос",
        "1_клиент",
        "2_на",
        "3_русский",
        "4_язык"
    ]
},
{
    "0_key": "клиент на русский язык",
    "1_textForm": "клиентов на русском языке",
    "2_modelName": "С + Предл + (Прил + С)",
    "3_docNum": 691996,
    "4_sentNum": 25,
    "5_start_ind": 4,
    "6_end_ind": 7,
    "7_lemmas": [
        "0_язык",
        "1_русский",
        "2_на",
        "3_клиент"
    ]
},
{
    "0_key": "средний количество",
    "1_textForm": "Среднее количество",
    "2_modelName": "Прил + С",
    "3_docNum": 691996,
    "4_sentNum": 26,
    "5_start_ind": 0,
    "6_end_ind": 1,
    "7_lemmas": [
        "0_количество",
        "1_средний"
    ]
},
{
    "0_key": "количество слово",
    "1_textForm": "количество слов",
    "2_modelName": "С + Срд",
    "3_docNum": 691996,
    "4_sentNum": 26,
    "5_start_ind": 1,
    "6_end_ind": 2,
    "7_lemmas": [
        "0_количество",
        "1_слово"
    ]
},
{
    "0_key": "тематический моделирование",
    "1_textForm": "тематического моделирования",
    "2_modelName": "Прил + С",
    "3_docNum": 691996,
    "4_sentNum": 26,
    "5_start_ind": 25,
    "6_end_ind": 26,
    "7_lemmas": [
        "0_моделирование",
        "1_тематический"
    ]
},
{
    "0_key": "средний количество слово",
    "1_textForm": "Среднее количество слов",
    "2_modelName": "(Прил + С) + Срд",
    "3_docNum": 691996,
    "4_sentNum": 26,
    "5_start_ind": 0,
    "6_end_ind": 2,
    "7_lemmas": [
        "0_количество",
        "1_средний",
        "2_слово"
    ]
},
{
    "0_key": "количество слово в запрос",
    "1_textForm": "количество слов в запросе",
    "2_modelName": "(С + Срд) + Предл + С",
    "3_docNum": 691996,
    "4_sentNum": 26,
    "5_start_ind": 1,
    "6_end_ind": 4,
    "7_lemmas": [
        "0_количество",
        "1_слово",
        "2_в",
        "3_запрос"
    ]
},
{
    "0_key": "агломеративной кластеризация",
    "1_textForm": "Агломеративная кластеризация",
    "2_modelName": "Прил + С",
    "3_docNum": 691996,
    "4_sentNum": 27,
    "5_start_ind": 0,
    "6_end_ind": 1,
    "7_lemmas": [
        "0_кластеризация",
        "1_агломеративной"
    ]
},
{
    "0_key": "необходимый трешхолд",
    "1_textForm": "необходимый трешхолд",
    "2_modelName": "Прил + С",
    "3_docNum": 691996,
    "4_sentNum": 27,
    "5_start_ind": 12,
    "6_end_ind": 13,
    "7_lemmas": [
        "0_трешхолд",
        "1_необходимый"
    ]
},
{
    "0_key": "трешхолд для расстояние",
    "1_textForm": "трешхолд для расстояния",
    "2_modelName": "С + Предл(Для) + С",
    "3_docNum": 691996,
    "4_sentNum": 27,
    "5_start_ind": 13,
    "6_end_ind": 15,
    "7_lemmas": [
        "0_трешхолд",
        "1_для",
        "2_расстояние"
    ]
},
{
    "0_key": "мера расстояние",
    "1_textForm": "меру расстояния",
    "2_modelName": "С + Срд",
    "3_docNum": 691996,
    "4_sentNum": 27,
    "5_start_ind": 20,
    "6_end_ind": 21,
    "7_lemmas": [
        "0_мера",
        "1_расстояние"
    ]
},
{
    "0_key": "необходимый трешхолд для расстояние",
    "1_textForm": "необходимый трешхолд для расстояния",
    "2_modelName": "(Прил + С) + Предл + С",
    "3_docNum": 691996,
    "4_sentNum": 27,
    "5_start_ind": 12,
    "6_end_ind": 15,
    "7_lemmas": [
        "0_трешхолд",
        "1_необходимый",
        "2_для",
        "3_расстояние"
    ]
},
{
    "0_key": "трешхолд расстояние",
    "1_textForm": "трешхолда расстояния",
    "2_modelName": "Прил + С",
    "3_docNum": 691996,
    "4_sentNum": 29,
    "5_start_ind": 3,
    "6_end_ind": 4,
    "7_lemmas": [
        "0_расстояние",
        "1_трешхолд"
    ]
},
{
    "0_key": "выставление трешхолд расстояние",
    "1_textForm": "выставлении трешхолда расстояния",
    "2_modelName": "C + (Прил + С)рд",
    "3_docNum": 691996,
    "4_sentNum": 29,
    "5_start_ind": 2,
    "6_end_ind": 4,
    "7_lemmas": [
        "0_расстояние",
        "1_трешхолд",
        "2_выставление"
    ]
},
{
    "0_key": "география кластер",
    "1_textForm": "география кластеров",
    "2_modelName": "С + Срд",
    "3_docNum": 691996,
    "4_sentNum": 30,
    "5_start_ind": 12,
    "6_end_ind": 13,
    "7_lemmas": [
        "0_география",
        "1_кластер"
    ]
},
{
    "0_key": "получившийся кластер",
    "1_textForm": "получившиеся кластеры",
    "2_modelName": "Прич + С",
    "3_docNum": 691996,
    "4_sentNum": 31,
    "5_start_ind": 11,
    "6_end_ind": 12,
    "7_lemmas": [
        "0_кластер",
        "1_получившийся"
    ]
},
{
    "0_key": "группа кластер",
    "1_textForm": "группы кластеров",
    "2_modelName": "С + Срд",
    "3_docNum": 691996,
    "4_sentNum": 32,
    "5_start_ind": 2,
    "6_end_ind": 3,
    "7_lemmas": [
        "0_группа",
        "1_кластер"
    ]
},
{
    "0_key": "размерность вектор",
    "1_textForm": "размерность векторов",
    "2_modelName": "С + Срд",
    "3_docNum": 691996,
    "4_sentNum": 33,
    "5_start_ind": 4,
    "6_end_ind": 5,
    "7_lemmas": [
        "0_размерность",
        "1_вектор"
    ]
},
{
    "0_key": "получившийся кластер",
    "1_textForm": "получившейся кластер",
    "2_modelName": "Прич + С",
    "3_docNum": 691996,
    "4_sentNum": 33,
    "5_start_ind": 11,
    "6_end_ind": 12,
    "7_lemmas": [
        "0_кластер",
        "1_получившийся"
    ]
},
{
    "0_key": "карта кластер",
    "1_textForm": "карте кластеров",
    "2_modelName": "С + Срд",
    "3_docNum": 691996,
    "4_sentNum": 33,
    "5_start_ind": 17,
    "6_end_ind": 18,
    "7_lemmas": [
        "0_карта",
        "1_кластер"
    ]
},
{
    "0_key": "заметный разделение",
    "1_textForm": "заметное разделение",
    "2_modelName": "Прил + С",
    "3_docNum": 691996,
    "4_sentNum": 35,
    "5_start_ind": 8,
    "6_end_ind": 9,
    "7_lemmas": [
        "0_разделение",
        "1_заметный"
    ]
},
{
    "0_key": "личный кабинет",
    "1_textForm": "личному кабинету",
    "2_modelName": "Прил + С",
    "3_docNum": 691996,
    "4_sentNum": 35,
    "5_start_ind": 14,
    "6_end_ind": 15,
    "7_lemmas": [
        "0_кабинет",
        "1_личный"
    ]
},
{
    "0_key": "интернет дом",
    "1_textForm": "интернету дома",
    "2_modelName": "С + Срд",
    "3_docNum": 691996,
    "4_sentNum": 35,
    "5_start_ind": 17,
    "6_end_ind": 18,
    "7_lemmas": [
        "0_интернет",
        "1_дом"
    ]
},
{
    "0_key": "смена тариф",
    "1_textForm": "смене тарифа",
    "2_modelName": "С + Срд",
    "3_docNum": 691996,
    "4_sentNum": 35,
    "5_start_ind": 20,
    "6_end_ind": 21,
    "7_lemmas": [
        "0_смена",
        "1_тариф"
    ]
},
{
    "0_key": "запрос по личный кабинет",
    "1_textForm": "запросы по личному кабинету",
    "2_modelName": "С + Предл + (Прил + С)",
    "3_docNum": 691996,
    "4_sentNum": 35,
    "5_start_ind": 12,
    "6_end_ind": 15,
    "7_lemmas": [
        "0_кабинет",
        "1_личный",
        "2_по",
        "3_запрос"
    ]
},
{
    "0_key": "малый усилие",
    "1_textForm": "малым усилием",
    "2_modelName": "Прил + С",
    "3_docNum": 691996,
    "4_sentNum": 37,
    "5_start_ind": 9,
    "6_end_ind": 10,
    "7_lemmas": [
        "0_усилие",
        "1_малый"
    ]
},
{
    "0_key": "интент с малый усилие",
    "1_textForm": "интентам с малым усилием",
    "2_modelName": "С + Предл + (Прил + С)",
    "3_docNum": 691996,
    "4_sentNum": 37,
    "5_start_ind": 7,
    "6_end_ind": 10,
    "7_lemmas": [
        "0_усилие",
        "1_малый",
        "2_с",
        "3_интент"
    ]
},
{
    "0_key": "область точка",
    "1_textForm": "области точек",
    "2_modelName": "С + Срд",
    "3_docNum": 691996,
    "4_sentNum": 38,
    "5_start_ind": 2,
    "6_end_ind": 3,
    "7_lemmas": [
        "0_область",
        "1_точка"
    ]
},
{
    "0_key": "доменный интент",
    "1_textForm": "доменные интенты",
    "2_modelName": "Прил + С",
    "3_docNum": 691996,
    "4_sentNum": 38,
    "5_start_ind": 20,
    "6_end_ind": 21,
    "7_lemmas": [
        "0_интент",
        "1_доменный"
    ]
},
{
    "0_key": "метрика классификатор",
    "1_textForm": "Метрики классификатора",
    "2_modelName": "С + Срд",
    "3_docNum": 691996,
    "4_sentNum": 39,
    "5_start_ind": 0,
    "6_end_ind": 1,
    "7_lemmas": [
        "0_метрика",
        "1_классификатор"
    ]
},
{
    "0_key": "метрика классификатор и чат-бот",
    "1_textForm": "Метрики классификатора и чат-бота",
    "2_modelName": "(С + Срд) + СоюзИ + С",
    "3_docNum": 691996,
    "4_sentNum": 39,
    "5_start_ind": 0,
    "6_end_ind": 3,
    "7_lemmas": [
        "0_метрика",
        "1_классификатор",
        "2_и",
        "3_чат-бот"
    ]
},
{
    "0_key": "модель классификация",
    "1_textForm": "модель классификации",
    "2_modelName": "С + Срд",
    "3_docNum": 691996,
    "4_sentNum": 40,
    "5_start_ind": 2,
    "6_end_ind": 3,
    "7_lemmas": [
        "0_модель",
        "1_классификация"
    ]
},
{
    "0_key": "качество модель",
    "1_textForm": "качество модели",
    "2_modelName": "С + Срд",
    "3_docNum": 691996,
    "4_sentNum": 40,
    "5_start_ind": 12,
    "6_end_ind": 13,
    "7_lemmas": [
        "0_качество",
        "1_модель"
    ]
},
{
    "0_key": "количество наблюдение",
    "1_textForm": "количества наблюдений",
    "2_modelName": "С + Срд",
    "3_docNum": 691996,
    "4_sentNum": 73,
    "5_start_ind": 7,
    "6_end_ind": 8,
    "7_lemmas": [
        "0_количество",
        "1_наблюдение"
    ]
},
{
    "0_key": "метрика классификатор",
    "1_textForm": "метриками классификатора",
    "2_modelName": "С + Срд",
    "3_docNum": 691996,
    "4_sentNum": 74,
    "5_start_ind": 3,
    "6_end_ind": 4,
    "7_lemmas": [
        "0_метрика",
        "1_классификатор"
    ]
},
{
    "0_key": "эффективность работа",
    "1_textForm": "эффективность работы",
    "2_modelName": "С + Срд",
    "3_docNum": 691996,
    "4_sentNum": 74,
    "5_start_ind": 7,
    "6_end_ind": 8,
    "7_lemmas": [
        "0_эффективность",
        "1_работа"
    ]
},
{
    "0_key": "эффективность работа чат-бот",
    "1_textForm": "эффективность работы чат-бота",
    "2_modelName": "С + Срд",
    "3_docNum": 691996,
    "4_sentNum": 74,
    "5_start_ind": 7,
    "6_end_ind": 9,
    "7_lemmas": [
        "0_эффективность",
        "1_работа",
        "2_чат-бот"
    ]
},
{
    "0_key": "работа чат-бот",
    "1_textForm": "работы чат-бота",
    "2_modelName": "С + Срд",
    "3_docNum": 691996,
    "4_sentNum": 74,
    "5_start_ind": 8,
    "6_end_ind": 9,
    "7_lemmas": [
        "0_работа",
        "1_чат-бот"
    ]
},
{
    "0_key": "основный метрика",
    "1_textForm": "основные метрики",
    "2_modelName": "Прил + С",
    "3_docNum": 691996,
    "4_sentNum": 74,
    "5_start_ind": 16,
    "6_end_ind": 17,
    "7_lemmas": [
        "0_метрика",
        "1_основный"
    ]
},
{
    "0_key": "процент диалог",
    "1_textForm": "процент диалогов",
    "2_modelName": "С + Срд",
    "3_docNum": 691996,
    "4_sentNum": 75,
    "5_start_ind": 7,
    "6_end_ind": 8,
    "7_lemmas": [
        "0_процент",
        "1_диалог"
    ]
},
{
    "0_key": "проблема абонент",
    "1_textForm": "проблему абонента",
    "2_modelName": "С + Срд",
    "3_docNum": 691996,
    "4_sentNum": 75,
    "5_start_ind": 16,
    "6_end_ind": 17,
    "7_lemmas": [
        "0_проблема",
        "1_абонент"
    ]
},
{
    "0_key": "ручной разметка",
    "1_textForm": "ручная разметка",
    "2_modelName": "Прил + С",
    "3_docNum": 691996,
    "4_sentNum": 76,
    "5_start_ind": 1,
    "6_end_ind": 2,
    "7_lemmas": [
        "0_разметка",
        "1_ручной"
    ]
},
{
    "0_key": "разметка выборка",
    "1_textForm": "разметка выборки",
    "2_modelName": "С + Срд",
    "3_docNum": 691996,
    "4_sentNum": 76,
    "5_start_ind": 2,
    "6_end_ind": 3,
    "7_lemmas": [
        "0_разметка",
        "1_выборка"
    ]
},
{
    "0_key": "разметка выборка диалог",
    "1_textForm": "разметка выборки диалогов",
    "2_modelName": "С + Срд",
    "3_docNum": 691996,
    "4_sentNum": 76,
    "5_start_ind": 2,
    "6_end_ind": 4,
    "7_lemmas": [
        "0_разметка",
        "1_выборка",
        "2_диалог"
    ]
},
{
    "0_key": "выборка диалог",
    "1_textForm": "выборки диалогов",
    "2_modelName": "С + Срд",
    "3_docNum": 691996,
    "4_sentNum": 76,
    "5_start_ind": 3,
    "6_end_ind": 4,
    "7_lemmas": [
        "0_выборка",
        "1_диалог"
    ]
},
{
    "0_key": "ручной разметка выборка диалог",
    "1_textForm": "ручная разметка выборки диалогов",
    "2_modelName": "(Прил + С) + Срд",
    "3_docNum": 691996,
    "4_sentNum": 76,
    "5_start_ind": 1,
    "6_end_ind": 4,
    "7_lemmas": [
        "0_разметка",
        "1_ручной",
        "2_выборка",
        "3_диалог"
    ]
},
{
    "0_key": "зеленый цвет",
    "1_textForm": "зеленый цвет",
    "2_modelName": "Прил + С",
    "3_docNum": 691996,
    "4_sentNum": 78,
    "5_start_ind": 0,
    "6_end_ind": 1,
    "7_lemmas": [
        "0_цвет",
        "1_зеленый"
    ]
},
{
    "0_key": "правильный ответ",
    "1_textForm": "правильный ответ",
    "2_modelName": "Прил + С",
    "3_docNum": 691996,
    "4_sentNum": 78,
    "5_start_ind": 9,
    "6_end_ind": 10,
    "7_lemmas": [
        "0_ответ",
        "1_правильный"
    ]
},
{
    "0_key": "желтый цвет",
    "1_textForm": "желтый цвет",
    "2_modelName": "Прил + С",
    "3_docNum": 691996,
    "4_sentNum": 79,
    "5_start_ind": 0,
    "6_end_ind": 1,
    "7_lemmas": [
        "0_цвет",
        "1_желтый"
    ]
},
{
    "0_key": "неполный ответ",
    "1_textForm": "неполный ответ",
    "2_modelName": "Прил + С",
    "3_docNum": 691996,
    "4_sentNum": 79,
    "5_start_ind": 11,
    "6_end_ind": 12,
    "7_lemmas": [
        "0_ответ",
        "1_неполный"
    ]
},
{
    "0_key": "красный цвет",
    "1_textForm": "красный цвет",
    "2_modelName": "Прил + С",
    "3_docNum": 691996,
    "4_sentNum": 80,
    "5_start_ind": 0,
    "6_end_ind": 1,
    "7_lemmas": [
        "0_цвет",
        "1_красный"
    ]
},
{
    "0_key": "информативный метрика",
    "1_textForm": "информативная метрика",
    "2_modelName": "Прил + С",
    "3_docNum": 691996,
    "4_sentNum": 81,
    "5_start_ind": 1,
    "6_end_ind": 2,
    "7_lemmas": [
        "0_метрика",
        "1_информативный"
    ]
},
{
    "0_key": "процесс разметка",
    "1_textForm": "процесс разметки",
    "2_modelName": "С + Срд",
    "3_docNum": 691996,
    "4_sentNum": 81,
    "5_start_ind": 8,
    "6_end_ind": 9,
    "7_lemmas": [
        "0_процесс",
        "1_разметка"
    ]
},
{
    "0_key": "средний оценка",
    "1_textForm": "средняя оценка",
    "2_modelName": "Прил + С",
    "3_docNum": 691996,
    "4_sentNum": 82,
    "5_start_ind": 7,
    "6_end_ind": 8,
    "7_lemmas": [
        "0_оценка",
        "1_средний"
    ]
},
{
    "0_key": "основный момент",
    "1_textForm": "Основные моменты",
    "2_modelName": "Прил + С",
    "3_docNum": 691996,
    "4_sentNum": 83,
    "5_start_ind": 0,
    "6_end_ind": 1,
    "7_lemmas": [
        "0_момент",
        "1_основный"
    ]
},
{
    "0_key": "уровень удовлетворенность",
    "1_textForm": "уровень удовлетворенности",
    "2_modelName": "С + Срд",
    "3_docNum": 691996,
    "4_sentNum": 84,
    "5_start_ind": 5,
    "6_end_ind": 6,
    "7_lemmas": [
        "0_уровень",
        "1_удовлетворенность"
    ]
},
{
    "0_key": "уровень удовлетворенность клиент",
    "1_textForm": "уровень удовлетворенности клиента",
    "2_modelName": "С + Срд",
    "3_docNum": 691996,
    "4_sentNum": 84,
    "5_start_ind": 5,
    "6_end_ind": 7,
    "7_lemmas": [
        "0_уровень",
        "1_удовлетворенность",
        "2_клиент"
    ]
},
{
    "0_key": "удовлетворенность клиент",
    "1_textForm": "удовлетворенности клиента",
    "2_modelName": "С + Срд",
    "3_docNum": 691996,
    "4_sentNum": 84,
    "5_start_ind": 6,
    "6_end_ind": 7,
    "7_lemmas": [
        "0_удовлетворенность",
        "1_клиент"
    ]
},
{
    "0_key": "реальный время",
    "1_textForm": "реальном времени",
    "2_modelName": "Прил + С",
    "3_docNum": 691996,
    "4_sentNum": 84,
    "5_start_ind": 9,
    "6_end_ind": 10,
    "7_lemmas": [
        "0_время",
        "1_реальный"
    ]
},
{
    "0_key": "уровень удовлетворенность клиент в реальный время",
    "1_textForm": "уровень удовлетворенности клиента в реальном времени",
    "2_modelName": "(С + Срд) + Предл + (Прил + С)",
    "3_docNum": 691996,
    "4_sentNum": 84,
    "5_start_ind": 5,
    "6_end_ind": 10,
    "7_lemmas": [
        "0_уровень",
        "1_удовлетворенность",
        "2_клиент",
        "3_в",
        "4_реальный",
        "5_время"
    ]
},
{
    "0_key": "удовлетворенность клиент в реальный время",
    "1_textForm": "удовлетворенности клиента в реальном времени",
    "2_modelName": "(С + Срд) + Предл + (Прил + С)",
    "3_docNum": 691996,
    "4_sentNum": 84,
    "5_start_ind": 6,
    "6_end_ind": 10,
    "7_lemmas": [
        "0_удовлетворенность",
        "1_клиент",
        "2_в",
        "3_реальный",
        "4_время"
    ]
},
{
    "0_key": "клиент в реальный время",
    "1_textForm": "клиента в реальном времени",
    "2_modelName": "С + Предл + (Прил + С)",
    "3_docNum": 691996,
    "4_sentNum": 84,
    "5_start_ind": 7,
    "6_end_ind": 10,
    "7_lemmas": [
        "0_время",
        "1_реальный",
        "2_в",
        "3_клиент"
    ]
},
{
    "0_key": "репрезентативность выборка",
    "1_textForm": "репрезентативностью выборки",
    "2_modelName": "С + Срд",
    "3_docNum": 691996,
    "4_sentNum": 85,
    "5_start_ind": 4,
    "6_end_ind": 5,
    "7_lemmas": [
        "0_репрезентативность",
        "1_выборка"
    ]
},
{
    "0_key": "репрезентативность выборка респондент",
    "1_textForm": "репрезентативностью выборки респондентов",
    "2_modelName": "С + Срд",
    "3_docNum": 691996,
    "4_sentNum": 85,
    "5_start_ind": 4,
    "6_end_ind": 6,
    "7_lemmas": [
        "0_репрезентативность",
        "1_выборка",
        "2_респондент"
    ]
},
{
    "0_key": "выборка респондент",
    "1_textForm": "выборки респондентов",
    "2_modelName": "С + Срд",
    "3_docNum": 691996,
    "4_sentNum": 85,
    "5_start_ind": 5,
    "6_end_ind": 6,
    "7_lemmas": [
        "0_выборка",
        "1_респондент"
    ]
},
{
    "0_key": "доступ клиент",
    "1_textForm": "доступ клиентов",
    "2_modelName": "С + Срд",
    "3_docNum": 691996,
    "4_sentNum": 86,
    "5_start_ind": 5,
    "6_end_ind": 6,
    "7_lemmas": [
        "0_доступ",
        "1_клиент"
    ]
},
{
    "0_key": "доступ клиент к анкета",
    "1_textForm": "доступ клиентов к анкете",
    "2_modelName": "(С + Срд) + Предл + С",
    "3_docNum": 691996,
    "4_sentNum": 86,
    "5_start_ind": 5,
    "6_end_ind": 8,
    "7_lemmas": [
        "0_доступ",
        "1_клиент",
        "2_к",
        "3_анкета"
    ]
},
{
    "0_key": "процент диалог",
    "1_textForm": "процент диалогов",
    "2_modelName": "С + Срд",
    "3_docNum": 691996,
    "4_sentNum": 87,
    "5_start_ind": 6,
    "6_end_ind": 7,
    "7_lemmas": [
        "0_процент",
        "1_диалог"
    ]
},
{
    "0_key": "принятие решение",
    "1_textForm": "принятии решения",
    "2_modelName": "С + Срд",
    "3_docNum": 691996,
    "4_sentNum": 90,
    "5_start_ind": 12,
    "6_end_ind": 13,
    "7_lemmas": [
        "0_принятие",
        "1_решение"
    ]
},
{
    "0_key": "вес в принятие решение",
    "1_textForm": "веса в принятии решения",
    "2_modelName": "С + Предл + (С + Срд)",
    "3_docNum": 691996,
    "4_sentNum": 90,
    "5_start_ind": 10,
    "6_end_ind": 13,
    "7_lemmas": [
        "0_принятие",
        "1_решение",
        "2_в",
        "3_вес"
    ]
},
{
    "0_key": "бесплатный разметка",
    "1_textForm": "бесплатную разметку",
    "2_modelName": "Прил + С",
    "3_docNum": 691996,
    "4_sentNum": 93,
    "5_start_ind": 4,
    "6_end_ind": 5,
    "7_lemmas": [
        "0_разметка",
        "1_бесплатный"
    ]
},
{
    "0_key": "черновой бесплатный разметка",
    "1_textForm": "черновую бесплатную разметку",
    "2_modelName": "Прил + С",
    "3_docNum": 691996,
    "4_sentNum": 93,
    "5_start_ind": 3,
    "6_end_ind": 5,
    "7_lemmas": [
        "0_разметка",
        "1_бесплатный",
        "2_черновой"
    ]
},
{
    "0_key": "бесплатный разметка путем кластеризация",
    "1_textForm": "бесплатную разметку путем кластеризации",
    "2_modelName": "(Прил + С) + Предл + С",
    "3_docNum": 691996,
    "4_sentNum": 93,
    "5_start_ind": 4,
    "6_end_ind": 7,
    "7_lemmas": [
        "0_разметка",
        "1_бесплатный",
        "2_путем",
        "3_кластеризация"
    ]
},
{
    "0_key": "черновой бесплатный разметка путем кластеризация",
    "1_textForm": "черновую бесплатную разметку путем кластеризации",
    "2_modelName": "(Прил + С) + Предл + С",
    "3_docNum": 691996,
    "4_sentNum": 93,
    "5_start_ind": 3,
    "6_end_ind": 7,
    "7_lemmas": [
        "0_разметка",
        "1_бесплатный",
        "2_черновой",
        "3_путем",
        "4_кластеризация"
    ]
},
{
    "0_key": "обучение модель",
    "1_textForm": "обучением модели",
    "2_modelName": "С + Срд",
    "3_docNum": 691996,
    "4_sentNum": 95,
    "5_start_ind": 10,
    "6_end_ind": 11,
    "7_lemmas": [
        "0_обучение",
        "1_модель"
    ]
},
{
    "0_key": "частотный метод",
    "1_textForm": "частотных методов",
    "2_modelName": "Прил + С",
    "3_docNum": 691996,
    "4_sentNum": 96,
    "5_start_ind": 3,
    "6_end_ind": 4,
    "7_lemmas": [
        "0_метод",
        "1_частотный"
    ]
},
{
    "0_key": "метод векторизация",
    "1_textForm": "методов векторизации",
    "2_modelName": "С + Срд",
    "3_docNum": 691996,
    "4_sentNum": 96,
    "5_start_ind": 4,
    "6_end_ind": 5,
    "7_lemmas": [
        "0_метод",
        "1_векторизация"
    ]
},
{
    "0_key": "метод векторизация текст",
    "1_textForm": "методов векторизации текста",
    "2_modelName": "С + Срд",
    "3_docNum": 691996,
    "4_sentNum": 96,
    "5_start_ind": 4,
    "6_end_ind": 6,
    "7_lemmas": [
        "0_метод",
        "1_векторизация",
        "2_текст"
    ]
},
{
    "0_key": "векторизация текст",
    "1_textForm": "векторизации текста",
    "2_modelName": "С + Срд",
    "3_docNum": 691996,
    "4_sentNum": 96,
    "5_start_ind": 5,
    "6_end_ind": 6,
    "7_lemmas": [
        "0_векторизация",
        "1_текст"
    ]
},
{
    "0_key": "частотный метод векторизация текст",
    "1_textForm": "частотных методов векторизации текста",
    "2_modelName": "(Прил + С) + Срд",
    "3_docNum": 691996,
    "4_sentNum": 96,
    "5_start_ind": 3,
    "6_end_ind": 6,
    "7_lemmas": [
        "0_метод",
        "1_частотный",
        "2_векторизация",
        "3_текст"
    ]
},
{
    "0_key": "русский язык",
    "1_textForm": "русского языка",
    "2_modelName": "Прил + С",
    "3_docNum": 691996,
    "4_sentNum": 100,
    "5_start_ind": 8,
    "6_end_ind": 9,
    "7_lemmas": [
        "0_язык",
        "1_русский"
    ]
},
{
    "0_key": "предобученный модель",
    "1_textForm": "предобученные модели",
    "2_modelName": "Прил + С",
    "3_docNum": 691996,
    "4_sentNum": 101,
    "5_start_ind": 3,
    "6_end_ind": 4,
    "7_lemmas": [
        "0_модель",
        "1_предобученный"
    ]
},
{
    "0_key": "предобученный модель с ресурс",
    "1_textForm": "предобученные модели с ресурса",
    "2_modelName": "(Прил + С) + Предл + С",
    "3_docNum": 691996,
    "4_sentNum": 101,
    "5_start_ind": 3,
    "6_end_ind": 6,
    "7_lemmas": [
        "0_модель",
        "1_предобученный",
        "2_с",
        "3_ресурс"
    ]
},
{
    "0_key": "инструмент визуализация",
    "1_textForm": "инструмент визуализации",
    "2_modelName": "С + Срд",
    "3_docNum": 691996,
    "4_sentNum": 103,
    "5_start_ind": 9,
    "6_end_ind": 10,
    "7_lemmas": [
        "0_инструмент",
        "1_визуализация"
    ]
},
{
    "0_key": "обучение модель",
    "1_textForm": "обучением модели",
    "2_modelName": "С + Срд",
    "3_docNum": 691996,
    "4_sentNum": 104,
    "5_start_ind": 3,
    "6_end_ind": 4,
    "7_lemmas": [
        "0_обучение",
        "1_модель"
    ]
},
{
    "0_key": "текстовый классификатор",
    "1_textForm": "текстовый классификатор",
    "2_modelName": "Прил + С",
    "3_docNum": 691996,
    "4_sentNum": 104,
    "5_start_ind": 18,
    "6_end_ind": 19,
    "7_lemmas": [
        "0_классификатор",
        "1_текстовый"
    ]
},
{
    "0_key": "эксперимент с обучение модель",
    "1_textForm": "экспериментов с обучением модели",
    "2_modelName": "С + Предл + (С + Срд)",
    "3_docNum": 691996,
    "4_sentNum": 104,
    "5_start_ind": 1,
    "6_end_ind": 4,
    "7_lemmas": [
        "0_обучение",
        "1_модель",
        "2_с",
        "3_эксперимент"
    ]
},
{
    "0_key": "ожидаемый качество",
    "1_textForm": "ожидаемого качества",
    "2_modelName": "Прич + С",
    "3_docNum": 691996,
    "4_sentNum": 106,
    "5_start_ind": 14,
    "6_end_ind": 15,
    "7_lemmas": [
        "0_качество",
        "1_ожидаемый"
    ]
},
{
    "0_key": "модель ожидаемый качество",
    "1_textForm": "модель ожидаемого качества",
    "2_modelName": "C + (Прич + С)рд",
    "3_docNum": 691996,
    "4_sentNum": 106,
    "5_start_ind": 13,
    "6_end_ind": 15,
    "7_lemmas": [
        "0_качество",
        "1_ожидаемый",
        "2_модель"
    ]
},
{
    "0_key": "основный метод",
    "1_textForm": "основными методами",
    "2_modelName": "Прил + С",
    "3_docNum": 691996,
    "4_sentNum": 109,
    "5_start_ind": 15,
    "6_end_ind": 16,
    "7_lemmas": [
        "0_метод",
        "1_основный"
    ]
},
{
    "0_key": "контекстный вставка",
    "1_textForm": "Контекстная вставка",
    "2_modelName": "Прил + С",
    "3_docNum": 691996,
    "4_sentNum": 113,
    "5_start_ind": 0,
    "6_end_ind": 1,
    "7_lemmas": [
        "0_вставка",
        "1_контекстный"
    ]
},
{
    "0_key": "вставка слово",
    "1_textForm": "вставка слова",
    "2_modelName": "С + Срд",
    "3_docNum": 691996,
    "4_sentNum": 113,
    "5_start_ind": 1,
    "6_end_ind": 2,
    "7_lemmas": [
        "0_вставка",
        "1_слово"
    ]
},
{
    "0_key": "контекстный вставка слово",
    "1_textForm": "Контекстная вставка слова",
    "2_modelName": "(Прил + С) + Срд",
    "3_docNum": 691996,
    "4_sentNum": 113,
    "5_start_ind": 0,
    "6_end_ind": 2,
    "7_lemmas": [
        "0_вставка",
        "1_контекстный",
        "2_слово"
    ]
},
{
    "0_key": "результативный способ",
    "1_textForm": "результативный способ",
    "2_modelName": "Прил + С",
    "3_docNum": 691996,
    "4_sentNum": 115,
    "5_start_ind": 4,
    "6_end_ind": 5,
    "7_lemmas": [
        "0_способ",
        "1_результативный"
    ]
},
{
    "0_key": "прочий шум",
    "1_textForm": "прочий шум",
    "2_modelName": "Прил + С",
    "3_docNum": 691996,
    "4_sentNum": 116,
    "5_start_ind": 4,
    "6_end_ind": 5,
    "7_lemmas": [
        "0_шум",
        "1_прочий"
    ]
},
{
    "0_key": "опечатка и прочий шум",
    "1_textForm": "опечатки и прочий шум",
    "2_modelName": "С + СоюзИ + (Прил + С)",
    "3_docNum": 691996,
    "4_sentNum": 116,
    "5_start_ind": 2,
    "6_end_ind": 5,
    "7_lemmas": [
        "0_шум",
        "1_прочий",
        "2_и",
        "3_опечатка"
    ]
},
{
    "0_key": "синтаксический дерево",
    "1_textForm": "синтаксическое дерево",
    "2_modelName": "Прил + С",
    "3_docNum": 691996,
    "4_sentNum": 118,
    "5_start_ind": 1,
    "6_end_ind": 2,
    "7_lemmas": [
        "0_дерево",
        "1_синтаксический"
    ]
},
{
    "0_key": "дистрибутивный семантика",
    "1_textForm": "дистрибутивной семантики",
    "2_modelName": "Прил + С",
    "3_docNum": 691996,
    "4_sentNum": 118,
    "5_start_ind": 23,
    "6_end_ind": 24,
    "7_lemmas": [
        "0_семантика",
        "1_дистрибутивный"
    ]
},
{
    "0_key": "модель дистрибутивный семантика",
    "1_textForm": "моделей дистрибутивной семантики",
    "2_modelName": "C + (Прил + С)рд",
    "3_docNum": 691996,
    "4_sentNum": 118,
    "5_start_ind": 22,
    "6_end_ind": 24,
    "7_lemmas": [
        "0_семантика",
        "1_дистрибутивный",
        "2_модель"
    ]
},
{
    "0_key": "связность текст",
    "1_textForm": "связность текста",
    "2_modelName": "С + Срд",
    "3_docNum": 691996,
    "4_sentNum": 119,
    "5_start_ind": 6,
    "6_end_ind": 7,
    "7_lemmas": [
        "0_связность",
        "1_текст"
    ]
},
{
    "0_key": "обратный перевод",
    "1_textForm": "обратным переводом",
    "2_modelName": "Прил + С",
    "3_docNum": 691996,
    "4_sentNum": 122,
    "5_start_ind": 9,
    "6_end_ind": 10,
    "7_lemmas": [
        "0_перевод",
        "1_обратный"
    ]
},
{
    "0_key": "популярный способ",
    "1_textForm": "Популярный способ",
    "2_modelName": "Прил + С",
    "3_docNum": 691996,
    "4_sentNum": 125,
    "5_start_ind": 0,
    "6_end_ind": 1,
    "7_lemmas": [
        "0_способ",
        "1_популярный"
    ]
},
{
    "0_key": "способ аугментация",
    "1_textForm": "способ аугментации",
    "2_modelName": "С + Срд",
    "3_docNum": 691996,
    "4_sentNum": 125,
    "5_start_ind": 1,
    "6_end_ind": 2,
    "7_lemmas": [
        "0_способ",
        "1_аугментация"
    ]
},
{
    "0_key": "популярный способ аугментация",
    "1_textForm": "Популярный способ аугментации",
    "2_modelName": "(Прил + С) + Срд",
    "3_docNum": 691996,
    "4_sentNum": 125,
    "5_start_ind": 0,
    "6_end_ind": 2,
    "7_lemmas": [
        "0_способ",
        "1_популярный",
        "2_аугментация"
    ]
},
{
    "0_key": "иностранный язык",
    "1_textForm": "иностранный язык",
    "2_modelName": "Прил + С",
    "3_docNum": 691996,
    "4_sentNum": 126,
    "5_start_ind": 3,
    "6_end_ind": 4,
    "7_lemmas": [
        "0_язык",
        "1_иностранный"
    ]
},
{
    "0_key": "способ аугментация",
    "1_textForm": "способ аугментации",
    "2_modelName": "С + Срд",
    "3_docNum": 691996,
    "4_sentNum": 127,
    "5_start_ind": 3,
    "6_end_ind": 4,
    "7_lemmas": [
        "0_способ",
        "1_аугментация"
    ]
},
{
    "0_key": "ключевой слово",
    "1_textForm": "ключевые слова",
    "2_modelName": "Прил + С",
    "3_docNum": 691996,
    "4_sentNum": 127,
    "5_start_ind": 11,
    "6_end_ind": 12,
    "7_lemmas": [
        "0_слово",
        "1_ключевой"
    ]
},
{
    "0_key": "платный разметка",
    "1_textForm": "платная разметка",
    "2_modelName": "Прил + С",
    "3_docNum": 691996,
    "4_sentNum": 128,
    "5_start_ind": 22,
    "6_end_ind": 23,
    "7_lemmas": [
        "0_разметка",
        "1_платный"
    ]
},
{
    "0_key": "процесс аннотатор",
    "1_textForm": "процессу аннотаторов",
    "2_modelName": "С + Срд",
    "3_docNum": 691996,
    "4_sentNum": 129,
    "5_start_ind": 3,
    "6_end_ind": 4,
    "7_lemmas": [
        "0_процесс",
        "1_аннотатор"
    ]
},
{
    "0_key": "качественный разметка",
    "1_textForm": "качественной разметкой",
    "2_modelName": "Прил + С",
    "3_docNum": 691996,
    "4_sentNum": 130,
    "5_start_ind": 11,
    "6_end_ind": 12,
    "7_lemmas": [
        "0_разметка",
        "1_качественный"
    ]
},
{
    "0_key": "текст с качественный разметка",
    "1_textForm": "текстах с качественной разметкой",
    "2_modelName": "С + Предл + (Прил + С)",
    "3_docNum": 691996,
    "4_sentNum": 130,
    "5_start_ind": 9,
    "6_end_ind": 12,
    "7_lemmas": [
        "0_разметка",
        "1_качественный",
        "2_с",
        "3_текст"
    ]
},
{
    "0_key": "предсказание модель",
    "1_textForm": "предсказания модели",
    "2_modelName": "С + Срд",
    "3_docNum": 691996,
    "4_sentNum": 131,
    "5_start_ind": 20,
    "6_end_ind": 21,
    "7_lemmas": [
        "0_предсказание",
        "1_модель"
    ]
},
{
    "0_key": "механизм внимание",
    "1_textForm": "механизм внимания",
    "2_modelName": "С + Срд",
    "3_docNum": 691996,
    "4_sentNum": 133,
    "5_start_ind": 6,
    "6_end_ind": 7,
    "7_lemmas": [
        "0_механизм",
        "1_внимание"
    ]
},
{
    "0_key": "механизм внимание модель",
    "1_textForm": "механизм внимания модели",
    "2_modelName": "С + Срд",
    "3_docNum": 691996,
    "4_sentNum": 133,
    "5_start_ind": 6,
    "6_end_ind": 8,
    "7_lemmas": [
        "0_механизм",
        "1_внимание",
        "2_модель"
    ]
},
{
    "0_key": "внимание модель",
    "1_textForm": "внимания модели",
    "2_modelName": "С + Срд",
    "3_docNum": 691996,
    "4_sentNum": 133,
    "5_start_ind": 7,
    "6_end_ind": 8,
    "7_lemmas": [
        "0_внимание",
        "1_модель"
    ]
},
{
    "0_key": "конкретный слой",
    "1_textForm": "конкретных слоев",
    "2_modelName": "Прил + С",
    "3_docNum": 691996,
    "4_sentNum": 133,
    "5_start_ind": 30,
    "6_end_ind": 31,
    "7_lemmas": [
        "0_слой",
        "1_конкретный"
    ]
},
{
    "0_key": "ключевой слово",
    "1_textForm": "ключевые слова",
    "2_modelName": "Прил + С",
    "3_docNum": 691996,
    "4_sentNum": 135,
    "5_start_ind": 10,
    "6_end_ind": 11,
    "7_lemmas": [
        "0_слово",
        "1_ключевой"
    ]
},
{
    "0_key": "обучающий датасет",
    "1_textForm": "обучающий датасет",
    "2_modelName": "Прич + С",
    "3_docNum": 691996,
    "4_sentNum": 136,
    "5_start_ind": 5,
    "6_end_ind": 6,
    "7_lemmas": [
        "0_датасет",
        "1_обучающий"
    ]
},
{
    "0_key": "анализ разметка",
    "1_textForm": "анализ разметки",
    "2_modelName": "С + Срд",
    "3_docNum": 691996,
    "4_sentNum": 137,
    "5_start_ind": 3,
    "6_end_ind": 4,
    "7_lemmas": [
        "0_анализ",
        "1_разметка"
    ]
},
{
    "0_key": "полноценный текст",
    "1_textForm": "полноценным текстам",
    "2_modelName": "Прил + С",
    "3_docNum": 691996,
    "4_sentNum": 137,
    "5_start_ind": 10,
    "6_end_ind": 11,
    "7_lemmas": [
        "0_текст",
        "1_полноценный"
    ]
},
{
    "0_key": "инсайт по полноценный текст",
    "1_textForm": "инсайт по полноценным текстам",
    "2_modelName": "С + Предл + (Прил + С)",
    "3_docNum": 691996,
    "4_sentNum": 137,
    "5_start_ind": 8,
    "6_end_ind": 11,
    "7_lemmas": [
        "0_текст",
        "1_полноценный",
        "2_по",
        "3_инсайт"
    ]
},
{
    "0_key": "полноценный текст",
    "1_textForm": "полноценных текстах",
    "2_modelName": "Прил + С",
    "3_docNum": 691996,
    "4_sentNum": 138,
    "5_start_ind": 4,
    "6_end_ind": 5,
    "7_lemmas": [
        "0_текст",
        "1_полноценный"
    ]
},
{
    "0_key": "естественный язык",
    "1_textForm": "естественном языке",
    "2_modelName": "Прил + С",
    "3_docNum": 691996,
    "4_sentNum": 138,
    "5_start_ind": 7,
    "6_end_ind": 8,
    "7_lemmas": [
        "0_язык",
        "1_естественный"
    ]
},
{
    "0_key": "полноценный текст на естественный язык",
    "1_textForm": "полноценных текстах на естественном языке",
    "2_modelName": "(Прил + С) + Предл + (Прил + С)",
    "3_docNum": 691996,
    "4_sentNum": 138,
    "5_start_ind": 4,
    "6_end_ind": 8,
    "7_lemmas": [
        "0_текст",
        "1_полноценный",
        "2_на",
        "3_естественный",
        "4_язык"
    ]
},
{
    "0_key": "текст на естественный язык",
    "1_textForm": "текстах на естественном языке",
    "2_modelName": "С + Предл + (Прил + С)",
    "3_docNum": 691996,
    "4_sentNum": 138,
    "5_start_ind": 5,
    "6_end_ind": 8,
    "7_lemmas": [
        "0_язык",
        "1_естественный",
        "2_на",
        "3_текст"
    ]
},
{
    "0_key": "конкретный интент",
    "1_textForm": "конкретных интентах",
    "2_modelName": "Прил + С",
    "3_docNum": 691996,
    "4_sentNum": 139,
    "5_start_ind": 14,
    "6_end_ind": 15,
    "7_lemmas": [
        "0_интент",
        "1_конкретный"
    ]
},
{
    "0_key": "имеющийся разметка",
    "1_textForm": "имеющийся разметок",
    "2_modelName": "Прич + С",
    "3_docNum": 691996,
    "4_sentNum": 139,
    "5_start_ind": 25,
    "6_end_ind": 26,
    "7_lemmas": [
        "0_разметка",
        "1_имеющийся"
    ]
},
{
    "0_key": "анализ имеющийся разметка",
    "1_textForm": "анализ имеющийся разметок",
    "2_modelName": "C + (Прич + С)рд",
    "3_docNum": 691996,
    "4_sentNum": 139,
    "5_start_ind": 24,
    "6_end_ind": 26,
    "7_lemmas": [
        "0_разметка",
        "1_имеющийся",
        "2_анализ"
    ]
},
{
    "0_key": "время разметка",
    "1_textForm": "времен разметки",
    "2_modelName": "С + Срд",
    "3_docNum": 691996,
    "4_sentNum": 140,
    "5_start_ind": 16,
    "6_end_ind": 17,
    "7_lemmas": [
        "0_время",
        "1_разметка"
    ]
},
{
    "0_key": "время разметка от аннотатор",
    "1_textForm": "времен разметки от аннотаторов",
    "2_modelName": "(С + Срд) + Предл + С",
    "3_docNum": 691996,
    "4_sentNum": 140,
    "5_start_ind": 16,
    "6_end_ind": 19,
    "7_lemmas": [
        "0_время",
        "1_разметка",
        "2_от",
        "3_аннотатор"
    ]
},
{
    "0_key": "интент запрос",
    "1_textForm": "интент запроса",
    "2_modelName": "С + Срд",
    "3_docNum": 691996,
    "4_sentNum": 142,
    "5_start_ind": 14,
    "6_end_ind": 15,
    "7_lemmas": [
        "0_интент",
        "1_запрос"
    ]
},
{
    "0_key": "бинарный классификация",
    "1_textForm": "бинарная классификация",
    "2_modelName": "Прил + С",
    "3_docNum": 691996,
    "4_sentNum": 142,
    "5_start_ind": 28,
    "6_end_ind": 29,
    "7_lemmas": [
        "0_классификация",
        "1_бинарный"
    ]
},
{
    "0_key": "домен и интент запрос",
    "1_textForm": "домен и интент запроса",
    "2_modelName": "С + СоюзИ + (С + Срд)",
    "3_docNum": 691996,
    "4_sentNum": 142,
    "5_start_ind": 12,
    "6_end_ind": 15,
    "7_lemmas": [
        "0_интент",
        "1_запрос",
        "2_и",
        "3_домен"
    ]
},
{
    "0_key": "результат переразметка",
    "1_textForm": "результате переразметки",
    "2_modelName": "С + Срд",
    "3_docNum": 691996,
    "4_sentNum": 143,
    "5_start_ind": 1,
    "6_end_ind": 2,
    "7_lemmas": [
        "0_результат",
        "1_переразметка"
    ]
},
{
    "0_key": "разделение модель",
    "1_textForm": "разделение моделей",
    "2_modelName": "С + Срд",
    "3_docNum": 691996,
    "4_sentNum": 143,
    "5_start_ind": 4,
    "6_end_ind": 5,
    "7_lemmas": [
        "0_разделение",
        "1_модель"
    ]
},
{
    "0_key": "результат переразметка и разделение модель",
    "1_textForm": "результате переразметки и разделение моделей",
    "2_modelName": "(С + Срд) + СоюзИ + (С + Срд)",
    "3_docNum": 691996,
    "4_sentNum": 143,
    "5_start_ind": 1,
    "6_end_ind": 5,
    "7_lemmas": [
        "0_результат",
        "1_переразметка",
        "2_и",
        "3_разделение",
        "4_модель"
    ]
},
{
    "0_key": "переразметка и разделение модель",
    "1_textForm": "переразметки и разделение моделей",
    "2_modelName": "С + СоюзИ + (С + Срд)",
    "3_docNum": 691996,
    "4_sentNum": 143,
    "5_start_ind": 2,
    "6_end_ind": 5,
    "7_lemmas": [
        "0_разделение",
        "1_модель",
        "2_и",
        "3_переразметка"
    ]
},
{
    "0_key": "имеющийся список",
    "1_textForm": "имеющийся список",
    "2_modelName": "Прич + С",
    "3_docNum": 691996,
    "4_sentNum": 145,
    "5_start_ind": 21,
    "6_end_ind": 22,
    "7_lemmas": [
        "0_список",
        "1_имеющийся"
    ]
},
{
    "0_key": "список интент",
    "1_textForm": "список интентов",
    "2_modelName": "С + Срд",
    "3_docNum": 691996,
    "4_sentNum": 145,
    "5_start_ind": 22,
    "6_end_ind": 23,
    "7_lemmas": [
        "0_список",
        "1_интент"
    ]
},
{
    "0_key": "остальной лексика",
    "1_textForm": "остальную лексику",
    "2_modelName": "Прил + С",
    "3_docNum": 691996,
    "4_sentNum": 145,
    "5_start_ind": 27,
    "6_end_ind": 28,
    "7_lemmas": [
        "0_лексика",
        "1_остальной"
    ]
},
{
    "0_key": "остальной интент",
    "1_textForm": "остальные интенты",
    "2_modelName": "Прил + С",
    "3_docNum": 691996,
    "4_sentNum": 145,
    "5_start_ind": 35,
    "6_end_ind": 36,
    "7_lemmas": [
        "0_интент",
        "1_остальной"
    ]
},
{
    "0_key": "имеющийся список интент",
    "1_textForm": "имеющийся список интентов",
    "2_modelName": "(Прич + С) + Срд",
    "3_docNum": 691996,
    "4_sentNum": 145,
    "5_start_ind": 21,
    "6_end_ind": 23,
    "7_lemmas": [
        "0_список",
        "1_имеющийся",
        "2_интент"
    ]
},
{
    "0_key": "список интент в чат-бот",
    "1_textForm": "список интентов в чат-боте",
    "2_modelName": "(С + Срд) + Предл + С",
    "3_docNum": 691996,
    "4_sentNum": 145,
    "5_start_ind": 22,
    "6_end_ind": 25,
    "7_lemmas": [
        "0_список",
        "1_интент",
        "2_в",
        "3_чат-бот"
    ]
},
{
    "0_key": "чат-бот и остальной лексика",
    "1_textForm": "чат-боте и остальную лексику",
    "2_modelName": "С + СоюзИ + (Прил + С)",
    "3_docNum": 691996,
    "4_sentNum": 145,
    "5_start_ind": 25,
    "6_end_ind": 28,
    "7_lemmas": [
        "0_лексика",
        "1_остальной",
        "2_и",
        "3_чат-бот"
    ]
},
{
    "0_key": "ряд эксперимент",
    "1_textForm": "ряд экспериментов",
    "2_modelName": "С + Срд",
    "3_docNum": 691996,
    "4_sentNum": 146,
    "5_start_ind": 3,
    "6_end_ind": 4,
    "7_lemmas": [
        "0_ряд",
        "1_эксперимент"
    ]
},
{
    "0_key": "определение наличие",
    "1_textForm": "определение наличия",
    "2_modelName": "С + Срд",
    "3_docNum": 691996,
    "4_sentNum": 146,
    "5_start_ind": 16,
    "6_end_ind": 17,
    "7_lemmas": [
        "0_определение",
        "1_наличие"
    ]
},
{
    "0_key": "пайплайн предсказание",
    "1_textForm": "пайплайн предсказания",
    "2_modelName": "С + Срд",
    "3_docNum": 691996,
    "4_sentNum": 147,
    "5_start_ind": 5,
    "6_end_ind": 6,
    "7_lemmas": [
        "0_пайплайн",
        "1_предсказание"
    ]
},
{
    "0_key": "неосмысленный текст",
    "1_textForm": "неосмысленный текст",
    "2_modelName": "Прил + С",
    "3_docNum": 691996,
    "4_sentNum": 148,
    "5_start_ind": 15,
    "6_end_ind": 16,
    "7_lemmas": [
        "0_текст",
        "1_неосмысленный"
    ]
},
{
    "0_key": "запрос бот",
    "1_textForm": "запрос бота",
    "2_modelName": "С + Срд",
    "3_docNum": 691996,
    "4_sentNum": 149,
    "5_start_ind": 6,
    "6_end_ind": 7,
    "7_lemmas": [
        "0_запрос",
        "1_бот"
    ]
},
{
    "0_key": "определение интент",
    "1_textForm": "определение интента",
    "2_modelName": "С + Срд",
    "3_docNum": 691996,
    "4_sentNum": 150,
    "5_start_ind": 7,
    "6_end_ind": 8,
    "7_lemmas": [
        "0_определение",
        "1_интент"
    ]
},
{
    "0_key": "бинарный модель",
    "1_textForm": "бинарная модель",
    "2_modelName": "Прил + С",
    "3_docNum": 691996,
    "4_sentNum": 150,
    "5_start_ind": 10,
    "6_end_ind": 11,
    "7_lemmas": [
        "0_модель",
        "1_бинарный"
    ]
},
{
    "0_key": "финальный предикт",
    "1_textForm": "финальный предикт",
    "2_modelName": "Прил + С",
    "3_docNum": 691996,
    "4_sentNum": 151,
    "5_start_ind": 21,
    "6_end_ind": 22,
    "7_lemmas": [
        "0_предикт",
        "1_финальный"
    ]
},
{
    "0_key": "ответ бот",
    "1_textForm": "ответ бота",
    "2_modelName": "С + Срд",
    "3_docNum": 691996,
    "4_sentNum": 152,
    "5_start_ind": 14,
    "6_end_ind": 15,
    "7_lemmas": [
        "0_ответ",
        "1_бот"
    ]
},
{
    "0_key": "косвенный метрика",
    "1_textForm": "косвенными метриками",
    "2_modelName": "Прил + С",
    "3_docNum": 691996,
    "4_sentNum": 154,
    "5_start_ind": 7,
    "6_end_ind": 8,
    "7_lemmas": [
        "0_метрика",
        "1_косвенный"
    ]
},
{
    "0_key": "чат-бот косвенный метрика",
    "1_textForm": "чат-бот косвенными метриками",
    "2_modelName": "C + (Прил + С)рд",
    "3_docNum": 691996,
    "4_sentNum": 154,
    "5_start_ind": 6,
    "6_end_ind": 8,
    "7_lemmas": [
        "0_метрика",
        "1_косвенный",
        "2_чат-бот"
    ]
},
{
    "0_key": "распознавание пул",
    "1_textForm": "распознавании пула",
    "2_modelName": "С + Срд",
    "3_docNum": 691996,
    "4_sentNum": 155,
    "5_start_ind": 3,
    "6_end_ind": 4,
    "7_lemmas": [
        "0_распознавание",
        "1_пул"
    ]
},
{
    "0_key": "распознавание пул запрос",
    "1_textForm": "распознавании пула запросов",
    "2_modelName": "С + Срд",
    "3_docNum": 691996,
    "4_sentNum": 155,
    "5_start_ind": 3,
    "6_end_ind": 5,
    "7_lemmas": [
        "0_распознавание",
        "1_пул",
        "2_запрос"
    ]
},
{
    "0_key": "пул запрос",
    "1_textForm": "пула запросов",
    "2_modelName": "С + Срд",
    "3_docNum": 691996,
    "4_sentNum": 155,
    "5_start_ind": 4,
    "6_end_ind": 5,
    "7_lemmas": [
        "0_пул",
        "1_запрос"
    ]
},
{
    "0_key": "инструмент распознавание",
    "1_textForm": "инструмент распознавания",
    "2_modelName": "С + Срд",
    "3_docNum": 691996,
    "4_sentNum": 155,
    "5_start_ind": 21,
    "6_end_ind": 22,
    "7_lemmas": [
        "0_инструмент",
        "1_распознавание"
    ]
},
{
    "0_key": "инструмент распознавание тематика",
    "1_textForm": "инструмент распознавания тематики",
    "2_modelName": "С + Срд",
    "3_docNum": 691996,
    "4_sentNum": 155,
    "5_start_ind": 21,
    "6_end_ind": 23,
    "7_lemmas": [
        "0_инструмент",
        "1_распознавание",
        "2_тематика"
    ]
},
{
    "0_key": "инструмент распознавание тематика запрос",
    "1_textForm": "инструмент распознавания тематики запроса",
    "2_modelName": "С + Срд",
    "3_docNum": 691996,
    "4_sentNum": 155,
    "5_start_ind": 21,
    "6_end_ind": 24,
    "7_lemmas": [
        "0_инструмент",
        "1_распознавание",
        "2_тематика",
        "3_запрос"
    ]
},
{
    "0_key": "распознавание тематика",
    "1_textForm": "распознавания тематики",
    "2_modelName": "С + Срд",
    "3_docNum": 691996,
    "4_sentNum": 155,
    "5_start_ind": 22,
    "6_end_ind": 23,
    "7_lemmas": [
        "0_распознавание",
        "1_тематика"
    ]
},
{
    "0_key": "распознавание тематика запрос",
    "1_textForm": "распознавания тематики запроса",
    "2_modelName": "С + Срд",
    "3_docNum": 691996,
    "4_sentNum": 155,
    "5_start_ind": 22,
    "6_end_ind": 24,
    "7_lemmas": [
        "0_распознавание",
        "1_тематика",
        "2_запрос"
    ]
},
{
    "0_key": "тематика запрос",
    "1_textForm": "тематики запроса",
    "2_modelName": "С + Срд",
    "3_docNum": 691996,
    "4_sentNum": 155,
    "5_start_ind": 23,
    "6_end_ind": 24,
    "7_lemmas": [
        "0_тематика",
        "1_запрос"
    ]
},
{
    "0_key": "ключевой слово",
    "1_textForm": "ключевых слов",
    "2_modelName": "Прил + С",
    "3_docNum": 691996,
    "4_sentNum": 155,
    "5_start_ind": 29,
    "6_end_ind": 30,
    "7_lemmas": [
        "0_слово",
        "1_ключевой"
    ]
},
{
    "0_key": "доля в распознавание пул запрос",
    "1_textForm": "доля в распознавании пула запросов",
    "2_modelName": "С + Предл + (С + Срд)",
    "3_docNum": 691996,
    "4_sentNum": 155,
    "5_start_ind": 1,
    "6_end_ind": 5,
    "7_lemmas": [
        "0_распознавание",
        "1_пул",
        "2_запрос",
        "3_в",
        "4_доля"
    ]
},
{
    "0_key": "основа ключевой слово",
    "1_textForm": "основе ключевых слов",
    "2_modelName": "C + (Прил + С)рд",
    "3_docNum": 691996,
    "4_sentNum": 155,
    "5_start_ind": 28,
    "6_end_ind": 30,
    "7_lemmas": [
        "0_слово",
        "1_ключевой",
        "2_основа"
    ]
},
{
    "0_key": "процент перевод",
    "1_textForm": "процент перевода",
    "2_modelName": "С + Срд",
    "3_docNum": 691996,
    "4_sentNum": 156,
    "5_start_ind": 1,
    "6_end_ind": 2,
    "7_lemmas": [
        "0_процент",
        "1_перевод"
    ]
},
{
    "0_key": "процент перевод на оператор",
    "1_textForm": "процент перевода на оператора",
    "2_modelName": "(С + Срд) + Предл + С",
    "3_docNum": 691996,
    "4_sentNum": 156,
    "5_start_ind": 1,
    "6_end_ind": 4,
    "7_lemmas": [
        "0_процент",
        "1_перевод",
        "2_на",
        "3_оператор"
    ]
},
{
    "0_key": "улучшение чат-бот",
    "1_textForm": "улучшение чат-бота",
    "2_modelName": "С + Срд",
    "3_docNum": 691996,
    "4_sentNum": 158,
    "5_start_ind": 6,
    "6_end_ind": 7,
    "7_lemmas": [
        "0_улучшение",
        "1_чат-бот"
    ]
},
{
    "0_key": "увеличение количество",
    "1_textForm": "увеличение количества",
    "2_modelName": "С + Срд",
    "3_docNum": 691996,
    "4_sentNum": 158,
    "5_start_ind": 10,
    "6_end_ind": 11,
    "7_lemmas": [
        "0_увеличение",
        "1_количество"
    ]
},
{
    "0_key": "охват запрос",
    "1_textForm": "охват запросов",
    "2_modelName": "С + Срд",
    "3_docNum": 691996,
    "4_sentNum": 158,
    "5_start_ind": 21,
    "6_end_ind": 22,
    "7_lemmas": [
        "0_охват",
        "1_запрос"
    ]
},
{
    "0_key": "увеличение порог",
    "1_textForm": "увеличение порога",
    "2_modelName": "С + Срд",
    "3_docNum": 691996,
    "4_sentNum": 159,
    "5_start_ind": 1,
    "6_end_ind": 2,
    "7_lemmas": [
        "0_увеличение",
        "1_порог"
    ]
},
{
    "0_key": "увеличение порог распознавание",
    "1_textForm": "увеличение порога распознавания",
    "2_modelName": "С + Срд",
    "3_docNum": 691996,
    "4_sentNum": 159,
    "5_start_ind": 1,
    "6_end_ind": 3,
    "7_lemmas": [
        "0_увеличение",
        "1_порог",
        "2_распознавание"
    ]
},
{
    "0_key": "порог распознавание",
    "1_textForm": "порога распознавания",
    "2_modelName": "С + Срд",
    "3_docNum": 691996,
    "4_sentNum": 159,
    "5_start_ind": 2,
    "6_end_ind": 3,
    "7_lemmas": [
        "0_порог",
        "1_распознавание"
    ]
},
{
    "0_key": "повышение точность",
    "1_textForm": "повышения точности",
    "2_modelName": "С + Срд",
    "3_docNum": 691996,
    "4_sentNum": 159,
    "5_start_ind": 8,
    "6_end_ind": 9,
    "7_lemmas": [
        "0_повышение",
        "1_точность"
    ]
},
{
    "0_key": "модель распознавание",
    "1_textForm": "моделью распознавания",
    "2_modelName": "С + Срд",
    "3_docNum": 691996,
    "4_sentNum": 159,
    "5_start_ind": 17,
    "6_end_ind": 18,
    "7_lemmas": [
        "0_модель",
        "1_распознавание"
    ]
},
{
    "0_key": "модель распознавание интент",
    "1_textForm": "моделью распознавания интента",
    "2_modelName": "С + Срд",
    "3_docNum": 691996,
    "4_sentNum": 159,
    "5_start_ind": 17,
    "6_end_ind": 19,
    "7_lemmas": [
        "0_модель",
        "1_распознавание",
        "2_интент"
    ]
},
{
    "0_key": "распознавание интент",
    "1_textForm": "распознавания интента",
    "2_modelName": "С + Срд",
    "3_docNum": 691996,
    "4_sentNum": 159,
    "5_start_ind": 18,
    "6_end_ind": 19,
    "7_lemmas": [
        "0_распознавание",
        "1_интент"
    ]
},
{
    "0_key": "внедрение классификатор",
    "1_textForm": "внедрение классификатора",
    "2_modelName": "С + Срд",
    "3_docNum": 691996,
    "4_sentNum": 160,
    "5_start_ind": 1,
    "6_end_ind": 2,
    "7_lemmas": [
        "0_внедрение",
        "1_классификатор"
    ]
},
{
    "0_key": "казахский язык",
    "1_textForm": "казахском языке",
    "2_modelName": "Прил + С",
    "3_docNum": 691996,
    "4_sentNum": 160,
    "5_start_ind": 4,
    "6_end_ind": 5,
    "7_lemmas": [
        "0_язык",
        "1_казахский"
    ]
},
{
    "0_key": "охват запрос",
    "1_textForm": "охвата запросов",
    "2_modelName": "С + Срд",
    "3_docNum": 691996,
    "4_sentNum": 160,
    "5_start_ind": 10,
    "6_end_ind": 11,
    "7_lemmas": [
        "0_охват",
        "1_запрос"
    ]
},
{
    "0_key": "внедрение классификатор на казахский язык",
    "1_textForm": "внедрение классификатора на казахском языке",
    "2_modelName": "(С + Срд) + Предл + (Прил + С)",
    "3_docNum": 691996,
    "4_sentNum": 160,
    "5_start_ind": 1,
    "6_end_ind": 5,
    "7_lemmas": [
        "0_внедрение",
        "1_классификатор",
        "2_на",
        "3_казахский",
        "4_язык"
    ]
},
{
    "0_key": "классификатор на казахский язык",
    "1_textForm": "классификатора на казахском языке",
    "2_modelName": "С + Предл + (Прил + С)",
    "3_docNum": 691996,
    "4_sentNum": 160,
    "5_start_ind": 2,
    "6_end_ind": 5,
    "7_lemmas": [
        "0_язык",
        "1_казахский",
        "2_на",
        "3_классификатор"
    ]
},
{
    "0_key": "улучшение качество",
    "1_textForm": "улучшение качества",
    "2_modelName": "С + Срд",
    "3_docNum": 691996,
    "4_sentNum": 161,
    "5_start_ind": 1,
    "6_end_ind": 2,
    "7_lemmas": [
        "0_улучшение",
        "1_качество"
    ]
},
{
    "0_key": "улучшение качество распознавание",
    "1_textForm": "улучшение качества распознавания",
    "2_modelName": "С + Срд",
    "3_docNum": 691996,
    "4_sentNum": 161,
    "5_start_ind": 1,
    "6_end_ind": 3,
    "7_lemmas": [
        "0_улучшение",
        "1_качество",
        "2_распознавание"
    ]
},
{
    "0_key": "качество распознавание",
    "1_textForm": "качества распознавания",
    "2_modelName": "С + Срд",
    "3_docNum": 691996,
    "4_sentNum": 161,
    "5_start_ind": 2,
    "6_end_ind": 3,
    "7_lemmas": [
        "0_качество",
        "1_распознавание"
    ]
},
{
    "0_key": "налаживание процесс",
    "1_textForm": "налаживания процесса",
    "2_modelName": "С + Срд",
    "3_docNum": 691996,
    "4_sentNum": 161,
    "5_start_ind": 5,
    "6_end_ind": 6,
    "7_lemmas": [
        "0_налаживание",
        "1_процесс"
    ]
},
{
    "0_key": "налаживание процесс разметка",
    "1_textForm": "налаживания процесса разметки",
    "2_modelName": "С + Срд",
    "3_docNum": 691996,
    "4_sentNum": 161,
    "5_start_ind": 5,
    "6_end_ind": 7,
    "7_lemmas": [
        "0_налаживание",
        "1_процесс",
        "2_разметка"
    ]
},
{
    "0_key": "налаживание процесс разметка запрос",
    "1_textForm": "налаживания процесса разметки запросов",
    "2_modelName": "С + Срд",
    "3_docNum": 691996,
    "4_sentNum": 161,
    "5_start_ind": 5,
    "6_end_ind": 8,
    "7_lemmas": [
        "0_налаживание",
        "1_процесс",
        "2_разметка",
        "3_запрос"
    ]
},
{
    "0_key": "процесс разметка",
    "1_textForm": "процесса разметки",
    "2_modelName": "С + Срд",
    "3_docNum": 691996,
    "4_sentNum": 161,
    "5_start_ind": 6,
    "6_end_ind": 7,
    "7_lemmas": [
        "0_процесс",
        "1_разметка"
    ]
},
{
    "0_key": "процесс разметка запрос",
    "1_textForm": "процесса разметки запросов",
    "2_modelName": "С + Срд",
    "3_docNum": 691996,
    "4_sentNum": 161,
    "5_start_ind": 6,
    "6_end_ind": 8,
    "7_lemmas": [
        "0_процесс",
        "1_разметка",
        "2_запрос"
    ]
},
{
    "0_key": "разметка запрос",
    "1_textForm": "разметки запросов",
    "2_modelName": "С + Срд",
    "3_docNum": 691996,
    "4_sentNum": 161,
    "5_start_ind": 7,
    "6_end_ind": 8,
    "7_lemmas": [
        "0_разметка",
        "1_запрос"
    ]
},
{
    "0_key": "автоматический процесс",
    "1_textForm": "автоматического процесса",
    "2_modelName": "Прил + С",
    "3_docNum": 691996,
    "4_sentNum": 161,
    "5_start_ind": 11,
    "6_end_ind": 12,
    "7_lemmas": [
        "0_процесс",
        "1_автоматический"
    ]
},
{
    "0_key": "процесс разметка",
    "1_textForm": "процесса разметки",
    "2_modelName": "С + Срд",
    "3_docNum": 691996,
    "4_sentNum": 161,
    "5_start_ind": 12,
    "6_end_ind": 13,
    "7_lemmas": [
        "0_процесс",
        "1_разметка"
    ]
},
{
    "0_key": "процесс разметка данный",
    "1_textForm": "процесса разметки данных",
    "2_modelName": "С + Срд",
    "3_docNum": 691996,
    "4_sentNum": 161,
    "5_start_ind": 12,
    "6_end_ind": 14,
    "7_lemmas": [
        "0_процесс",
        "1_разметка",
        "2_данный"
    ]
},
{
    "0_key": "разметка данный",
    "1_textForm": "разметки данных",
    "2_modelName": "С + Срд",
    "3_docNum": 691996,
    "4_sentNum": 161,
    "5_start_ind": 13,
    "6_end_ind": 14,
    "7_lemmas": [
        "0_разметка",
        "1_данный"
    ]
},
{
    "0_key": "участие аннотатор",
    "1_textForm": "участием аннотаторов",
    "2_modelName": "С + Срд",
    "3_docNum": 691996,
    "4_sentNum": 161,
    "5_start_ind": 16,
    "6_end_ind": 17,
    "7_lemmas": [
        "0_участие",
        "1_аннотатор"
    ]
},
{
    "0_key": "улучшение качество распознавание путем налаживание процесс",
    "1_textForm": "улучшение качества распознавания путем налаживания процесса",
    "2_modelName": "(С + Срд) + Предл + (С + Срд)",
    "3_docNum": 691996,
    "4_sentNum": 161,
    "5_start_ind": 1,
    "6_end_ind": 6,
    "7_lemmas": [
        "0_улучшение",
        "1_качество",
        "2_распознавание",
        "3_путем",
        "4_налаживание",
        "5_процесс"
    ]
},
{
    "0_key": "качество распознавание путем налаживание процесс",
    "1_textForm": "качества распознавания путем налаживания процесса",
    "2_modelName": "(С + Срд) + Предл + (С + Срд)",
    "3_docNum": 691996,
    "4_sentNum": 161,
    "5_start_ind": 2,
    "6_end_ind": 6,
    "7_lemmas": [
        "0_качество",
        "1_распознавание",
        "2_путем",
        "3_налаживание",
        "4_процесс"
    ]
},
{
    "0_key": "налаживание процесс разметка запрос и построение",
    "1_textForm": "налаживания процесса разметки запросов и построение",
    "2_modelName": "(С + Срд) + СоюзИ + С",
    "3_docNum": 691996,
    "4_sentNum": 161,
    "5_start_ind": 5,
    "6_end_ind": 10,
    "7_lemmas": [
        "0_налаживание",
        "1_процесс",
        "2_разметка",
        "3_запрос",
        "4_и",
        "5_построение"
    ]
},
{
    "0_key": "распознавание путем налаживание процесс разметка запрос",
    "1_textForm": "распознавания путем налаживания процесса разметки запросов",
    "2_modelName": "С + Предл + (С + Срд)",
    "3_docNum": 691996,
    "4_sentNum": 161,
    "5_start_ind": 3,
    "6_end_ind": 8,
    "7_lemmas": [
        "0_налаживание",
        "1_процесс",
        "2_разметка",
        "3_запрос",
        "4_путем",
        "5_распознавание"
    ]
},
{
    "0_key": "процесс разметка запрос и построение",
    "1_textForm": "процесса разметки запросов и построение",
    "2_modelName": "(С + Срд) + СоюзИ + С",
    "3_docNum": 691996,
    "4_sentNum": 161,
    "5_start_ind": 6,
    "6_end_ind": 10,
    "7_lemmas": [
        "0_процесс",
        "1_разметка",
        "2_запрос",
        "3_и",
        "4_построение"
    ]
},
{
    "0_key": "разметка запрос и построение",
    "1_textForm": "разметки запросов и построение",
    "2_modelName": "(С + Срд) + СоюзИ + С",
    "3_docNum": 691996,
    "4_sentNum": 161,
    "5_start_ind": 7,
    "6_end_ind": 10,
    "7_lemmas": [
        "0_разметка",
        "1_запрос",
        "2_и",
        "3_построение"
    ]
},
{
    "0_key": "построение автоматический процесс",
    "1_textForm": "построение автоматического процесса",
    "2_modelName": "C + (Прил + С)рд",
    "3_docNum": 691996,
    "4_sentNum": 161,
    "5_start_ind": 10,
    "6_end_ind": 12,
    "7_lemmas": [
        "0_процесс",
        "1_автоматический",
        "2_построение"
    ]
},
{
    "0_key": "автоматический процесс разметка данный",
    "1_textForm": "автоматического процесса разметки данных",
    "2_modelName": "(Прил + С) + Срд",
    "3_docNum": 691996,
    "4_sentNum": 161,
    "5_start_ind": 11,
    "6_end_ind": 14,
    "7_lemmas": [
        "0_процесс",
        "1_автоматический",
        "2_разметка",
        "3_данный"
    ]
},
{
    "0_key": "процесс разметка данный с участие аннотатор",
    "1_textForm": "процесса разметки данных с участием аннотаторов",
    "2_modelName": "(С + Срд) + Предл + (С + Срд)",
    "3_docNum": 691996,
    "4_sentNum": 161,
    "5_start_ind": 12,
    "6_end_ind": 17,
    "7_lemmas": [
        "0_процесс",
        "1_разметка",
        "2_данный",
        "3_с",
        "4_участие",
        "5_аннотатор"
    ]
},
{
    "0_key": "разметка данный с участие аннотатор",
    "1_textForm": "разметки данных с участием аннотаторов",
    "2_modelName": "(С + Срд) + Предл + (С + Срд)",
    "3_docNum": 691996,
    "4_sentNum": 161,
    "5_start_ind": 13,
    "6_end_ind": 17,
    "7_lemmas": [
        "0_разметка",
        "1_данный",
        "2_с",
        "3_участие",
        "4_аннотатор"
    ]
},
{
    "0_key": "участие аннотатор и валидатор",
    "1_textForm": "участием аннотаторов и валидаторов",
    "2_modelName": "(С + Срд) + СоюзИ + С",
    "3_docNum": 691996,
    "4_sentNum": 161,
    "5_start_ind": 16,
    "6_end_ind": 19,
    "7_lemmas": [
        "0_участие",
        "1_аннотатор",
        "2_и",
        "3_валидатор"
    ]
},
{
    "0_key": "данный с участие аннотатор",
    "1_textForm": "данных с участием аннотаторов",
    "2_modelName": "С + Предл + (С + Срд)",
    "3_docNum": 691996,
    "4_sentNum": 161,
    "5_start_ind": 14,
    "6_end_ind": 17,
    "7_lemmas": [
        "0_участие",
        "1_аннотатор",
        "2_с",
        "3_данный"
    ]
},
{
    "0_key": "бинарный классификация",
    "1_textForm": "бинарной классификации",
    "2_modelName": "Прил + С",
    "3_docNum": 691996,
    "4_sentNum": 162,
    "5_start_ind": 12,
    "6_end_ind": 13,
    "7_lemmas": [
        "0_классификация",
        "1_бинарный"
    ]
},
{
    "0_key": "потеря качество",
    "1_textForm": "потери качества",
    "2_modelName": "С + Срд",
    "3_docNum": 691996,
    "4_sentNum": 162,
    "5_start_ind": 20,
    "6_end_ind": 21,
    "7_lemmas": [
        "0_потеря",
        "1_качество"
    ]
},
{
    "0_key": "модель без потеря качество",
    "1_textForm": "модели без потери качества",
    "2_modelName": "С + Предл + (С + Срд)",
    "3_docNum": 691996,
    "4_sentNum": 162,
    "5_start_ind": 18,
    "6_end_ind": 21,
    "7_lemmas": [
        "0_потеря",
        "1_качество",
        "2_без",
        "3_модель"
    ]
},
{
    "0_key": "ускорение работа",
    "1_textForm": "ускорение работы",
    "2_modelName": "С + Срд",
    "3_docNum": 691996,
    "4_sentNum": 163,
    "5_start_ind": 3,
    "6_end_ind": 4,
    "7_lemmas": [
        "0_ускорение",
        "1_работа"
    ]
},
{
    "0_key": "ускорение работа сервис",
    "1_textForm": "ускорение работы сервиса",
    "2_modelName": "С + Срд",
    "3_docNum": 691996,
    "4_sentNum": 163,
    "5_start_ind": 3,
    "6_end_ind": 5,
    "7_lemmas": [
        "0_ускорение",
        "1_работа",
        "2_сервис"
    ]
},
{
    "0_key": "работа сервис",
    "1_textForm": "работы сервиса",
    "2_modelName": "С + Срд",
    "3_docNum": 691996,
    "4_sentNum": 163,
    "5_start_ind": 4,
    "6_end_ind": 5,
    "7_lemmas": [
        "0_работа",
        "1_сервис"
    ]
},
{
    "0_key": "внедрение инструмент",
    "1_textForm": "внедрением инструментов",
    "2_modelName": "С + Срд",
    "3_docNum": 691996,
    "4_sentNum": 164,
    "5_start_ind": 5,
    "6_end_ind": 6,
    "7_lemmas": [
        "0_внедрение",
        "1_инструмент"
    ]
},
{
    "0_key": "внедрение инструмент распознавание",
    "1_textForm": "внедрением инструментов распознавания",
    "2_modelName": "С + Срд",
    "3_docNum": 691996,
    "4_sentNum": 164,
    "5_start_ind": 5,
    "6_end_ind": 7,
    "7_lemmas": [
        "0_внедрение",
        "1_инструмент",
        "2_распознавание"
    ]
},
{
    "0_key": "инструмент распознавание",
    "1_textForm": "инструментов распознавания",
    "2_modelName": "С + Срд",
    "3_docNum": 691996,
    "4_sentNum": 164,
    "5_start_ind": 6,
    "6_end_ind": 7,
    "7_lemmas": [
        "0_инструмент",
        "1_распознавание"
    ]
},
{
    "0_key": "синтез речь",
    "1_textForm": "синтеза речи",
    "2_modelName": "С + Срд",
    "3_docNum": 691996,
    "4_sentNum": 164,
    "5_start_ind": 9,
    "6_end_ind": 10,
    "7_lemmas": [
        "0_синтез",
        "1_речь"
    ]
},
{
    "0_key": "платформа для управление",
    "1_textForm": "платформу для управления",
    "2_modelName": "С + Предл(Для) + С",
    "3_docNum": 691996,
    "4_sentNum": 164,
    "5_start_ind": 19,
    "6_end_ind": 21,
    "7_lemmas": [
        "0_платформа",
        "1_для",
        "2_управление"
    ]
},
{
    "0_key": "текстовый диалог",
    "1_textForm": "текстовыми диалогами",
    "2_modelName": "Прил + С",
    "3_docNum": 691996,
    "4_sentNum": 164,
    "5_start_ind": 24,
    "6_end_ind": 25,
    "7_lemmas": [
        "0_диалог",
        "1_текстовый"
    ]
},
{
    "0_key": "пилот с внедрение инструмент распознавание",
    "1_textForm": "пилот с внедрением инструментов распознавания",
    "2_modelName": "С + Предл + (С + Срд)",
    "3_docNum": 691996,
    "4_sentNum": 164,
    "5_start_ind": 3,
    "6_end_ind": 7,
    "7_lemmas": [
        "0_внедрение",
        "1_инструмент",
        "2_распознавание",
        "3_с",
        "4_пилот"
    ]
},
{
    "0_key": "внедрение инструмент распознавание и синтез речь",
    "1_textForm": "внедрением инструментов распознавания и синтеза речи",
    "2_modelName": "(С + Срд) + СоюзИ + (С + Срд)",
    "3_docNum": 691996,
    "4_sentNum": 164,
    "5_start_ind": 5,
    "6_end_ind": 10,
    "7_lemmas": [
        "0_внедрение",
        "1_инструмент",
        "2_распознавание",
        "3_и",
        "4_синтез",
        "5_речь"
    ]
},
{
    "0_key": "инструмент распознавание и синтез речь",
    "1_textForm": "инструментов распознавания и синтеза речи",
    "2_modelName": "(С + Срд) + СоюзИ + (С + Срд)",
    "3_docNum": 691996,
    "4_sentNum": 164,
    "5_start_ind": 6,
    "6_end_ind": 10,
    "7_lemmas": [
        "0_инструмент",
        "1_распознавание",
        "2_и",
        "3_синтез",
        "4_речь"
    ]
},
{
    "0_key": "распознавание и синтез речь",
    "1_textForm": "распознавания и синтеза речи",
    "2_modelName": "С + СоюзИ + (С + Срд)",
    "3_docNum": 691996,
    "4_sentNum": 164,
    "5_start_ind": 7,
    "6_end_ind": 10,
    "7_lemmas": [
        "0_синтез",
        "1_речь",
        "2_и",
        "3_распознавание"
    ]
},
{
    "0_key": "голосовой и текстовый диалог",
    "1_textForm": "голосовыми и текстовыми диалогами",
    "2_modelName": "Прил и (Прил + С)",
    "3_docNum": 691996,
    "4_sentNum": 164,
    "5_start_ind": 22,
    "6_end_ind": 25,
    "7_lemmas": [
        "0_диалог",
        "1_текстовый",
        "2_и",
        "3_голосовой"
    ]
}
]