[
{
    "0_key": "данный пост",
    "1_textForm": "данном посте",
    "2_modelName": "Прил + С",
    "3_docNum": 585378,
    "4_sentNum": 1,
    "5_start_ind": 1,
    "6_end_ind": 2,
    "7_lemmas": [
        "0_пост",
        "1_данный"
    ]
},
{
    "0_key": "автоматический обработка",
    "1_textForm": "автоматической обработки",
    "2_modelName": "Прил + С",
    "3_docNum": 585378,
    "4_sentNum": 1,
    "5_start_ind": 8,
    "6_end_ind": 9,
    "7_lemmas": [
        "0_обработка",
        "1_автоматический"
    ]
},
{
    "0_key": "обработка текст",
    "1_textForm": "обработки текстов",
    "2_modelName": "С + Срд",
    "3_docNum": 585378,
    "4_sentNum": 1,
    "5_start_ind": 9,
    "6_end_ind": 10,
    "7_lemmas": [
        "0_обработка",
        "1_текст"
    ]
},
{
    "0_key": "стиль речь",
    "1_textForm": "стиль речи",
    "2_modelName": "С + Срд",
    "3_docNum": 585378,
    "4_sentNum": 1,
    "5_start_ind": 21,
    "6_end_ind": 22,
    "7_lemmas": [
        "0_стиль",
        "1_речь"
    ]
},
{
    "0_key": "знаменитый сериал",
    "1_textForm": "знаменитого сериала",
    "2_modelName": "Прил + С",
    "3_docNum": 585378,
    "4_sentNum": 1,
    "5_start_ind": 26,
    "6_end_ind": 27,
    "7_lemmas": [
        "0_сериал",
        "1_знаменитый"
    ]
},
{
    "0_key": "мультиязычный анализ",
    "1_textForm": "мультиязычный анализ",
    "2_modelName": "Прил + С",
    "3_docNum": 585378,
    "4_sentNum": 1,
    "5_start_ind": 33,
    "6_end_ind": 34,
    "7_lemmas": [
        "0_анализ",
        "1_мультиязычный"
    ]
},
{
    "0_key": "английский язык",
    "1_textForm": "английского языков",
    "2_modelName": "Прил + С",
    "3_docNum": 585378,
    "4_sentNum": 1,
    "5_start_ind": 38,
    "6_end_ind": 39,
    "7_lemmas": [
        "0_язык",
        "1_английский"
    ]
},
{
    "0_key": "метод автоматический обработка",
    "1_textForm": "методов автоматической обработки",
    "2_modelName": "C + (Прил + С)рд",
    "3_docNum": 585378,
    "4_sentNum": 1,
    "5_start_ind": 7,
    "6_end_ind": 9,
    "7_lemmas": [
        "0_обработка",
        "1_автоматический",
        "2_метод"
    ]
},
{
    "0_key": "автоматический обработка текст",
    "1_textForm": "автоматической обработки текстов",
    "2_modelName": "(Прил + С) + Срд",
    "3_docNum": 585378,
    "4_sentNum": 1,
    "5_start_ind": 8,
    "6_end_ind": 10,
    "7_lemmas": [
        "0_обработка",
        "1_автоматический",
        "2_текст"
    ]
},
{
    "0_key": "герой знаменитый сериал",
    "1_textForm": "героев знаменитого сериала",
    "2_modelName": "C + (Прил + С)рд",
    "3_docNum": 585378,
    "4_sentNum": 1,
    "5_start_ind": 25,
    "6_end_ind": 27,
    "7_lemmas": [
        "0_сериал",
        "1_знаменитый",
        "2_герой"
    ]
},
{
    "0_key": "русский и английский язык",
    "1_textForm": "русского и английского языков",
    "2_modelName": "Прил и (Прил + С)",
    "3_docNum": 585378,
    "4_sentNum": 1,
    "5_start_ind": 36,
    "6_end_ind": 39,
    "7_lemmas": [
        "0_язык",
        "1_английский",
        "2_и",
        "3_русский"
    ]
},
{
    "0_key": "перенос стиль",
    "1_textForm": "Перенос стиля",
    "2_modelName": "С + Срд",
    "3_docNum": 585378,
    "4_sentNum": 3,
    "5_start_ind": 0,
    "6_end_ind": 1,
    "7_lemmas": [
        "0_перенос",
        "1_стиль"
    ]
},
{
    "0_key": "электронный помощник",
    "1_textForm": "электронных помощников",
    "2_modelName": "Прил + С",
    "3_docNum": 585378,
    "4_sentNum": 3,
    "5_start_ind": 25,
    "6_end_ind": 26,
    "7_lemmas": [
        "0_помощник",
        "1_электронный"
    ]
},
{
    "0_key": "персонализация электронный помощник",
    "1_textForm": "персонализации электронных помощников",
    "2_modelName": "C + (Прил + С)рд",
    "3_docNum": 585378,
    "4_sentNum": 3,
    "5_start_ind": 24,
    "6_end_ind": 26,
    "7_lemmas": [
        "0_помощник",
        "1_электронный",
        "2_персонализация"
    ]
},
{
    "0_key": "трансформерный модель",
    "1_textForm": "трансформерных моделей",
    "2_modelName": "Прил + С",
    "3_docNum": 585378,
    "4_sentNum": 4,
    "5_start_ind": 4,
    "6_end_ind": 5,
    "7_lemmas": [
        "0_модель",
        "1_трансформерный"
    ]
},
{
    "0_key": "выдающийся способность",
    "1_textForm": "выдающиеся способности",
    "2_modelName": "Прич + С",
    "3_docNum": 585378,
    "4_sentNum": 4,
    "5_start_ind": 9,
    "6_end_ind": 10,
    "7_lemmas": [
        "0_способность",
        "1_выдающийся"
    ]
},
{
    "0_key": "область понимание",
    "1_textForm": "области понимания",
    "2_modelName": "С + Срд",
    "3_docNum": 585378,
    "4_sentNum": 4,
    "5_start_ind": 12,
    "6_end_ind": 13,
    "7_lemmas": [
        "0_область",
        "1_понимание"
    ]
},
{
    "0_key": "естественный язык",
    "1_textForm": "естественного языка",
    "2_modelName": "Прил + С",
    "3_docNum": 585378,
    "4_sentNum": 4,
    "5_start_ind": 14,
    "6_end_ind": 15,
    "7_lemmas": [
        "0_язык",
        "1_естественный"
    ]
},
{
    "0_key": "выдающийся способность в область понимание",
    "1_textForm": "выдающиеся способности в области понимания",
    "2_modelName": "(Прич + С) + Предл + (С + Срд)",
    "3_docNum": 585378,
    "4_sentNum": 4,
    "5_start_ind": 9,
    "6_end_ind": 13,
    "7_lemmas": [
        "0_способность",
        "1_выдающийся",
        "2_в",
        "3_область",
        "4_понимание"
    ]
},
{
    "0_key": "способность в область понимание",
    "1_textForm": "способности в области понимания",
    "2_modelName": "С + Предл + (С + Срд)",
    "3_docNum": 585378,
    "4_sentNum": 4,
    "5_start_ind": 10,
    "6_end_ind": 13,
    "7_lemmas": [
        "0_область",
        "1_понимание",
        "2_в",
        "3_способность"
    ]
},
{
    "0_key": "естественный язык и имитация",
    "1_textForm": "естественного языка и имитации",
    "2_modelName": "(Прил + С) + СоюзИ + С",
    "3_docNum": 585378,
    "4_sentNum": 4,
    "5_start_ind": 14,
    "6_end_ind": 17,
    "7_lemmas": [
        "0_язык",
        "1_естественный",
        "2_и",
        "3_имитация"
    ]
},
{
    "0_key": "понимание естественный язык",
    "1_textForm": "понимания естественного языка",
    "2_modelName": "C + (Прил + С)рд",
    "3_docNum": 585378,
    "4_sentNum": 4,
    "5_start_ind": 13,
    "6_end_ind": 15,
    "7_lemmas": [
        "0_язык",
        "1_естественный",
        "2_понимание"
    ]
},
{
    "0_key": "языковый модель",
    "1_textForm": "языковые модели",
    "2_modelName": "Прил + С",
    "3_docNum": 585378,
    "4_sentNum": 5,
    "5_start_ind": 2,
    "6_end_ind": 3,
    "7_lemmas": [
        "0_модель",
        "1_языковый"
    ]
},
{
    "0_key": "миллиард параметр",
    "1_textForm": "миллиардам параметров",
    "2_modelName": "С + Срд",
    "3_docNum": 585378,
    "4_sentNum": 5,
    "5_start_ind": 13,
    "6_end_ind": 14,
    "7_lemmas": [
        "0_миллиард",
        "1_параметр"
    ]
},
{
    "0_key": "обучающий выборка",
    "1_textForm": "обучающей выборки",
    "2_modelName": "Прич + С",
    "3_docNum": 585378,
    "4_sentNum": 5,
    "5_start_ind": 21,
    "6_end_ind": 22,
    "7_lemmas": [
        "0_выборка",
        "1_обучающий"
    ]
},
{
    "0_key": "реалистичный текст",
    "1_textForm": "реалистичный текст",
    "2_modelName": "Прил + С",
    "3_docNum": 585378,
    "4_sentNum": 5,
    "5_start_ind": 31,
    "6_end_ind": 32,
    "7_lemmas": [
        "0_текст",
        "1_реалистичный"
    ]
},
{
    "0_key": "объем и миллиард параметр",
    "1_textForm": "объемам и миллиардам параметров",
    "2_modelName": "С + СоюзИ + (С + Срд)",
    "3_docNum": 585378,
    "4_sentNum": 5,
    "5_start_ind": 11,
    "6_end_ind": 14,
    "7_lemmas": [
        "0_миллиард",
        "1_параметр",
        "2_и",
        "3_объем"
    ]
},
{
    "0_key": "особенность обучающий выборка",
    "1_textForm": "особенности обучающей выборки",
    "2_modelName": "C + (Прич + С)рд",
    "3_docNum": 585378,
    "4_sentNum": 5,
    "5_start_ind": 20,
    "6_end_ind": 22,
    "7_lemmas": [
        "0_выборка",
        "1_обучающий",
        "2_особенность"
    ]
},
{
    "0_key": "данный пост",
    "1_textForm": "данном посте",
    "2_modelName": "Прил + С",
    "3_docNum": 585378,
    "4_sentNum": 6,
    "5_start_ind": 1,
    "6_end_ind": 2,
    "7_lemmas": [
        "0_пост",
        "1_данный"
    ]
},
{
    "0_key": "языковый модель",
    "1_textForm": "языковых моделей",
    "2_modelName": "Прил + С",
    "3_docNum": 585378,
    "4_sentNum": 6,
    "5_start_ind": 6,
    "6_end_ind": 7,
    "7_lemmas": [
        "0_модель",
        "1_языковый"
    ]
},
{
    "0_key": "модель для генерация",
    "1_textForm": "моделей для генерации",
    "2_modelName": "С + Предл(Для) + С",
    "3_docNum": 585378,
    "4_sentNum": 6,
    "5_start_ind": 7,
    "6_end_ind": 9,
    "7_lemmas": [
        "0_модель",
        "1_для",
        "2_генерация"
    ]
},
{
    "0_key": "генерация текст",
    "1_textForm": "генерации текста",
    "2_modelName": "С + Срд",
    "3_docNum": 585378,
    "4_sentNum": 6,
    "5_start_ind": 9,
    "6_end_ind": 10,
    "7_lemmas": [
        "0_генерация",
        "1_текст"
    ]
},
{
    "0_key": "стиль герой",
    "1_textForm": "стиле героев",
    "2_modelName": "С + Срд",
    "3_docNum": 585378,
    "4_sentNum": 6,
    "5_start_ind": 12,
    "6_end_ind": 13,
    "7_lemmas": [
        "0_стиль",
        "1_герой"
    ]
},
{
    "0_key": "знаменитый сериал",
    "1_textForm": "знаменитого сериала",
    "2_modelName": "Прил + С",
    "3_docNum": 585378,
    "4_sentNum": 6,
    "5_start_ind": 14,
    "6_end_ind": 15,
    "7_lemmas": [
        "0_сериал",
        "1_знаменитый"
    ]
},
{
    "0_key": "языковый модель для генерация текст",
    "1_textForm": "языковых моделей для генерации текста",
    "2_modelName": "(Прил + С) + Предл + (С + Срд)",
    "3_docNum": 585378,
    "4_sentNum": 6,
    "5_start_ind": 6,
    "6_end_ind": 10,
    "7_lemmas": [
        "0_модель",
        "1_языковый",
        "2_для",
        "3_генерация",
        "4_текст"
    ]
},
{
    "0_key": "возможность языковый модель",
    "1_textForm": "возможности языковых моделей",
    "2_modelName": "C + (Прил + С)рд",
    "3_docNum": 585378,
    "4_sentNum": 6,
    "5_start_ind": 5,
    "6_end_ind": 7,
    "7_lemmas": [
        "0_модель",
        "1_языковый",
        "2_возможность"
    ]
},
{
    "0_key": "модель для генерация текст",
    "1_textForm": "моделей для генерации текста",
    "2_modelName": "С + Предл + (С + Срд)",
    "3_docNum": 585378,
    "4_sentNum": 6,
    "5_start_ind": 7,
    "6_end_ind": 10,
    "7_lemmas": [
        "0_генерация",
        "1_текст",
        "2_для",
        "3_модель"
    ]
},
{
    "0_key": "генерация текст в стиль герой",
    "1_textForm": "генерации текста в стиле героев",
    "2_modelName": "(С + Срд) + Предл + (С + Срд)",
    "3_docNum": 585378,
    "4_sentNum": 6,
    "5_start_ind": 9,
    "6_end_ind": 13,
    "7_lemmas": [
        "0_генерация",
        "1_текст",
        "2_в",
        "3_стиль",
        "4_герой"
    ]
},
{
    "0_key": "текст в стиль герой",
    "1_textForm": "текста в стиле героев",
    "2_modelName": "С + Предл + (С + Срд)",
    "3_docNum": 585378,
    "4_sentNum": 6,
    "5_start_ind": 10,
    "6_end_ind": 13,
    "7_lemmas": [
        "0_стиль",
        "1_герой",
        "2_в",
        "3_текст"
    ]
},
{
    "0_key": "герой знаменитый сериал",
    "1_textForm": "героев знаменитого сериала",
    "2_modelName": "C + (Прил + С)рд",
    "3_docNum": 585378,
    "4_sentNum": 6,
    "5_start_ind": 13,
    "6_end_ind": 15,
    "7_lemmas": [
        "0_сериал",
        "1_знаменитый",
        "2_герой"
    ]
},
{
    "0_key": "английский транскрипет",
    "1_textForm": "английских транскриптов",
    "2_modelName": "Прил + С",
    "3_docNum": 585378,
    "4_sentNum": 7,
    "5_start_ind": 5,
    "6_end_ind": 6,
    "7_lemmas": [
        "0_транскрипет",
        "1_английский"
    ]
},
{
    "0_key": "транскрипет сериал",
    "1_textForm": "транскриптов сериала",
    "2_modelName": "С + Срд",
    "3_docNum": 585378,
    "4_sentNum": 7,
    "5_start_ind": 6,
    "6_end_ind": 7,
    "7_lemmas": [
        "0_транскрипет",
        "1_сериал"
    ]
},
{
    "0_key": "корпус английский транскрипет",
    "1_textForm": "корпус английских транскриптов",
    "2_modelName": "C + (Прил + С)рд",
    "3_docNum": 585378,
    "4_sentNum": 7,
    "5_start_ind": 4,
    "6_end_ind": 6,
    "7_lemmas": [
        "0_транскрипет",
        "1_английский",
        "2_корпус"
    ]
},
{
    "0_key": "английский транскрипет сериал",
    "1_textForm": "английских транскриптов сериала",
    "2_modelName": "(Прил + С) + Срд",
    "3_docNum": 585378,
    "4_sentNum": 7,
    "5_start_ind": 5,
    "6_end_ind": 7,
    "7_lemmas": [
        "0_транскрипет",
        "1_английский",
        "2_сериал"
    ]
},
{
    "0_key": "анализ стиль",
    "1_textForm": "анализ стиля",
    "2_modelName": "С + Срд",
    "3_docNum": 585378,
    "4_sentNum": 8,
    "5_start_ind": 5,
    "6_end_ind": 6,
    "7_lemmas": [
        "0_анализ",
        "1_стиль"
    ]
},
{
    "0_key": "особенность речь",
    "1_textForm": "особенности речи",
    "2_modelName": "С + Срд",
    "3_docNum": 585378,
    "4_sentNum": 8,
    "5_start_ind": 9,
    "6_end_ind": 10,
    "7_lemmas": [
        "0_особенность",
        "1_речь"
    ]
},
{
    "0_key": "сравнительный анализ",
    "1_textForm": "сравнительный анализ",
    "2_modelName": "Прил + С",
    "3_docNum": 585378,
    "4_sentNum": 8,
    "5_start_ind": 19,
    "6_end_ind": 20,
    "7_lemmas": [
        "0_анализ",
        "1_сравнительный"
    ]
},
{
    "0_key": "русский язык",
    "1_textForm": "русским языками",
    "2_modelName": "Прил + С",
    "3_docNum": 585378,
    "4_sentNum": 8,
    "5_start_ind": 24,
    "6_end_ind": 25,
    "7_lemmas": [
        "0_язык",
        "1_русский"
    ]
},
{
    "0_key": "английский и русский язык",
    "1_textForm": "английским и русским языками",
    "2_modelName": "Прил и (Прил + С)",
    "3_docNum": 585378,
    "4_sentNum": 8,
    "5_start_ind": 22,
    "6_end_ind": 25,
    "7_lemmas": [
        "0_язык",
        "1_русский",
        "2_и",
        "3_английский"
    ]
},
{
    "0_key": "выбор персонаж",
    "1_textForm": "Выбор персонажа",
    "2_modelName": "С + Срд",
    "3_docNum": 585378,
    "4_sentNum": 10,
    "5_start_ind": 0,
    "6_end_ind": 1,
    "7_lemmas": [
        "0_выбор",
        "1_персонаж"
    ]
},
{
    "0_key": "сбор данный",
    "1_textForm": "сбор данных",
    "2_modelName": "С + Срд",
    "3_docNum": 585378,
    "4_sentNum": 10,
    "5_start_ind": 3,
    "6_end_ind": 4,
    "7_lemmas": [
        "0_сбор",
        "1_данный"
    ]
},
{
    "0_key": "выбор персонаж и сбор данный",
    "1_textForm": "Выбор персонажа и сбор данных",
    "2_modelName": "(С + Срд) + СоюзИ + (С + Срд)",
    "3_docNum": 585378,
    "4_sentNum": 10,
    "5_start_ind": 0,
    "6_end_ind": 4,
    "7_lemmas": [
        "0_выбор",
        "1_персонаж",
        "2_и",
        "3_сбор",
        "4_данный"
    ]
},
{
    "0_key": "персонаж и сбор данный",
    "1_textForm": "персонажа и сбор данных",
    "2_modelName": "С + СоюзИ + (С + Срд)",
    "3_docNum": 585378,
    "4_sentNum": 10,
    "5_start_ind": 1,
    "6_end_ind": 4,
    "7_lemmas": [
        "0_сбор",
        "1_данный",
        "2_и",
        "3_персонаж"
    ]
},
{
    "0_key": "стилистический анализ",
    "1_textForm": "Стилистический анализ",
    "2_modelName": "Прил + С",
    "3_docNum": 585378,
    "4_sentNum": 11,
    "5_start_ind": 0,
    "6_end_ind": 1,
    "7_lemmas": [
        "0_анализ",
        "1_стилистический"
    ]
},
{
    "0_key": "анализ речь",
    "1_textForm": "анализ речи",
    "2_modelName": "С + Срд",
    "3_docNum": 585378,
    "4_sentNum": 11,
    "5_start_ind": 1,
    "6_end_ind": 2,
    "7_lemmas": [
        "0_анализ",
        "1_речь"
    ]
},
{
    "0_key": "анализ речь персонаж",
    "1_textForm": "анализ речи персонажей",
    "2_modelName": "С + Срд",
    "3_docNum": 585378,
    "4_sentNum": 11,
    "5_start_ind": 1,
    "6_end_ind": 3,
    "7_lemmas": [
        "0_анализ",
        "1_речь",
        "2_персонаж"
    ]
},
{
    "0_key": "речь персонаж",
    "1_textForm": "речи персонажей",
    "2_modelName": "С + Срд",
    "3_docNum": 585378,
    "4_sentNum": 11,
    "5_start_ind": 2,
    "6_end_ind": 3,
    "7_lemmas": [
        "0_речь",
        "1_персонаж"
    ]
},
{
    "0_key": "стилистический анализ речь персонаж",
    "1_textForm": "Стилистический анализ речи персонажей",
    "2_modelName": "(Прил + С) + Срд",
    "3_docNum": 585378,
    "4_sentNum": 11,
    "5_start_ind": 0,
    "6_end_ind": 3,
    "7_lemmas": [
        "0_анализ",
        "1_стилистический",
        "2_речь",
        "3_персонаж"
    ]
},
{
    "0_key": "обучение модель",
    "1_textForm": "обучения моделей",
    "2_modelName": "С + Срд",
    "3_docNum": 585378,
    "4_sentNum": 12,
    "5_start_ind": 2,
    "6_end_ind": 3,
    "7_lemmas": [
        "0_обучение",
        "1_модель"
    ]
},
{
    "0_key": "github репозиторий",
    "1_textForm": "GitHub репозитории",
    "2_modelName": "Прил + С",
    "3_docNum": 585378,
    "4_sentNum": 13,
    "5_start_ind": 9,
    "6_end_ind": 10,
    "7_lemmas": [
        "0_репозиторий",
        "1_github"
    ]
},
{
    "0_key": "выбор персонаж",
    "1_textForm": "Выбор персонажа",
    "2_modelName": "С + Срд",
    "3_docNum": 585378,
    "4_sentNum": 15,
    "5_start_ind": 0,
    "6_end_ind": 1,
    "7_lemmas": [
        "0_выбор",
        "1_персонаж"
    ]
},
{
    "0_key": "персонаж для перенос",
    "1_textForm": "персонажа для переноса",
    "2_modelName": "С + Предл(Для) + С",
    "3_docNum": 585378,
    "4_sentNum": 16,
    "5_start_ind": 18,
    "6_end_ind": 20,
    "7_lemmas": [
        "0_персонаж",
        "1_для",
        "2_перенос"
    ]
},
{
    "0_key": "перенос стиль",
    "1_textForm": "переноса стиля",
    "2_modelName": "С + Срд",
    "3_docNum": 585378,
    "4_sentNum": 16,
    "5_start_ind": 20,
    "6_end_ind": 21,
    "7_lemmas": [
        "0_перенос",
        "1_стиль"
    ]
},
{
    "0_key": "персонаж для перенос стиль",
    "1_textForm": "персонажа для переноса стиля",
    "2_modelName": "С + Предл + (С + Срд)",
    "3_docNum": 585378,
    "4_sentNum": 16,
    "5_start_ind": 18,
    "6_end_ind": 21,
    "7_lemmas": [
        "0_перенос",
        "1_стиль",
        "2_для",
        "3_персонаж"
    ]
},
{
    "0_key": "амбициозный цель",
    "1_textForm": "амбициозную цель",
    "2_modelName": "Прил + С",
    "3_docNum": 585378,
    "4_sentNum": 17,
    "5_start_ind": 6,
    "6_end_ind": 7,
    "7_lemmas": [
        "0_цель",
        "1_амбициозный"
    ]
},
{
    "0_key": "гигантский датасет",
    "1_textForm": "гигантский датасет",
    "2_modelName": "Прил + С",
    "3_docNum": 585378,
    "4_sentNum": 17,
    "5_start_ind": 10,
    "6_end_ind": 11,
    "7_lemmas": [
        "0_датасет",
        "1_гигантский"
    ]
},
{
    "0_key": "выдуманный герой",
    "1_textForm": "выдуманного героя",
    "2_modelName": "Прич + С",
    "3_docNum": 585378,
    "4_sentNum": 17,
    "5_start_ind": 18,
    "6_end_ind": 19,
    "7_lemmas": [
        "0_герой",
        "1_выдуманный"
    ]
},
{
    "0_key": "гигантский датасет с реплика",
    "1_textForm": "гигантский датасет с репликами",
    "2_modelName": "(Прил + С) + Предл + С",
    "3_docNum": 585378,
    "4_sentNum": 17,
    "5_start_ind": 10,
    "6_end_ind": 13,
    "7_lemmas": [
        "0_датасет",
        "1_гигантский",
        "2_с",
        "3_реплика"
    ]
},
{
    "0_key": "политический фигура",
    "1_textForm": "политических фигур",
    "2_modelName": "Прил + С",
    "3_docNum": 585378,
    "4_sentNum": 18,
    "5_start_ind": 12,
    "6_end_ind": 13,
    "7_lemmas": [
        "0_фигура",
        "1_политический"
    ]
},
{
    "0_key": "русский шоу",
    "1_textForm": "русских шоу",
    "2_modelName": "Прил + С",
    "3_docNum": 585378,
    "4_sentNum": 19,
    "5_start_ind": 6,
    "6_end_ind": 7,
    "7_lemmas": [
        "0_шоу",
        "1_русский"
    ]
},
{
    "0_key": "вечерний ургант",
    "1_textForm": "Вечерний Ургант",
    "2_modelName": "Прил + С",
    "3_docNum": 585378,
    "4_sentNum": 19,
    "5_start_ind": 10,
    "6_end_ind": 11,
    "7_lemmas": [
        "0_ургант",
        "1_вечерний"
    ]
},
{
    "0_key": "публичный доступ",
    "1_textForm": "публичном доступе",
    "2_modelName": "Прил + С",
    "3_docNum": 585378,
    "4_sentNum": 19,
    "5_start_ind": 22,
    "6_end_ind": 23,
    "7_lemmas": [
        "0_доступ",
        "1_публичный"
    ]
},
{
    "0_key": "транскрипта русский шоу",
    "1_textForm": "транскрипты русских шоу",
    "2_modelName": "C + (Прил + С)рд",
    "3_docNum": 585378,
    "4_sentNum": 19,
    "5_start_ind": 5,
    "6_end_ind": 7,
    "7_lemmas": [
        "0_шоу",
        "1_русский",
        "2_транскрипта"
    ]
},
{
    "0_key": "анализ субтитр",
    "1_textForm": "Анализ субтитров",
    "2_modelName": "С + Срд",
    "3_docNum": 585378,
    "4_sentNum": 20,
    "5_start_ind": 0,
    "6_end_ind": 1,
    "7_lemmas": [
        "0_анализ",
        "1_субтитр"
    ]
},
{
    "0_key": "автосгенерированный субтитр",
    "1_textForm": "автосгенерированных субтитров",
    "2_modelName": "Прич + С",
    "3_docNum": 585378,
    "4_sentNum": 20,
    "5_start_ind": 31,
    "6_end_ind": 32,
    "7_lemmas": [
        "0_субтитр",
        "1_автосгенерированный"
    ]
},
{
    "0_key": "качество автосгенерированный субтитр",
    "1_textForm": "качество автосгенерированных субтитров",
    "2_modelName": "C + (Прич + С)рд",
    "3_docNum": 585378,
    "4_sentNum": 20,
    "5_start_ind": 30,
    "6_end_ind": 32,
    "7_lemmas": [
        "0_субтитр",
        "1_автосгенерированный",
        "2_качество"
    ]
},
{
    "0_key": "литературный герой",
    "1_textForm": "литературных героев",
    "2_modelName": "Прил + С",
    "3_docNum": 585378,
    "4_sentNum": 21,
    "5_start_ind": 4,
    "6_end_ind": 5,
    "7_lemmas": [
        "0_герой",
        "1_литературный"
    ]
},
{
    "0_key": "надежный источник",
    "1_textForm": "надежный источник",
    "2_modelName": "Прил + С",
    "3_docNum": 585378,
    "4_sentNum": 22,
    "5_start_ind": 5,
    "6_end_ind": 6,
    "7_lemmas": [
        "0_источник",
        "1_надежный"
    ]
},
{
    "0_key": "источник данный",
    "1_textForm": "источник данных",
    "2_modelName": "С + Срд",
    "3_docNum": 585378,
    "4_sentNum": 22,
    "5_start_ind": 6,
    "6_end_ind": 7,
    "7_lemmas": [
        "0_источник",
        "1_данный"
    ]
},
{
    "0_key": "надежный источник данный",
    "1_textForm": "надежный источник данных",
    "2_modelName": "(Прил + С) + Срд",
    "3_docNum": 585378,
    "4_sentNum": 22,
    "5_start_ind": 5,
    "6_end_ind": 7,
    "7_lemmas": [
        "0_источник",
        "1_надежный",
        "2_данный"
    ]
},
{
    "0_key": "реплика персонаж",
    "1_textForm": "реплики персонажа",
    "2_modelName": "С + Срд",
    "3_docNum": 585378,
    "4_sentNum": 23,
    "5_start_ind": 13,
    "6_end_ind": 14,
    "7_lemmas": [
        "0_реплика",
        "1_персонаж"
    ]
},
{
    "0_key": "английский ситком",
    "1_textForm": "английском ситкоме",
    "2_modelName": "Прил + С",
    "3_docNum": 585378,
    "4_sentNum": 25,
    "5_start_ind": 12,
    "6_end_ind": 13,
    "7_lemmas": [
        "0_ситком",
        "1_английский"
    ]
},
{
    "0_key": "знаменитый английский ситком",
    "1_textForm": "знаменитом английском ситкоме",
    "2_modelName": "Прил + С",
    "3_docNum": 585378,
    "4_sentNum": 25,
    "5_start_ind": 11,
    "6_end_ind": 13,
    "7_lemmas": [
        "0_ситком",
        "1_английский",
        "2_знаменитый"
    ]
},
{
    "0_key": "комедийный сериал",
    "1_textForm": "комедийный сериал",
    "2_modelName": "Прил + С",
    "3_docNum": 585378,
    "4_sentNum": 27,
    "5_start_ind": 1,
    "6_end_ind": 2,
    "7_lemmas": [
        "0_сериал",
        "1_комедийный"
    ]
},
{
    "0_key": "публичный доступ",
    "1_textForm": "публичном доступе",
    "2_modelName": "Прил + С",
    "3_docNum": 585378,
    "4_sentNum": 29,
    "5_start_ind": 10,
    "6_end_ind": 11,
    "7_lemmas": [
        "0_доступ",
        "1_публичный"
    ]
},
{
    "0_key": "эпизод в публичный доступ",
    "1_textForm": "эпизодов в публичном доступе",
    "2_modelName": "С + Предл + (Прил + С)",
    "3_docNum": 585378,
    "4_sentNum": 29,
    "5_start_ind": 8,
    "6_end_ind": 11,
    "7_lemmas": [
        "0_доступ",
        "1_публичный",
        "2_в",
        "3_эпизод"
    ]
},
{
    "0_key": "достаточный количество",
    "1_textForm": "Достаточное количество",
    "2_modelName": "Прил + С",
    "3_docNum": 585378,
    "4_sentNum": 31,
    "5_start_ind": 0,
    "6_end_ind": 1,
    "7_lemmas": [
        "0_количество",
        "1_достаточный"
    ]
},
{
    "0_key": "количество данный",
    "1_textForm": "количество данных",
    "2_modelName": "С + Срд",
    "3_docNum": 585378,
    "4_sentNum": 31,
    "5_start_ind": 1,
    "6_end_ind": 2,
    "7_lemmas": [
        "0_количество",
        "1_данный"
    ]
},
{
    "0_key": "достаточный количество данный",
    "1_textForm": "Достаточное количество данных",
    "2_modelName": "(Прил + С) + Срд",
    "3_docNum": 585378,
    "4_sentNum": 31,
    "5_start_ind": 0,
    "6_end_ind": 2,
    "7_lemmas": [
        "0_количество",
        "1_достаточный",
        "2_данный"
    ]
},
{
    "0_key": "языковый модель",
    "1_textForm": "языковую модель",
    "2_modelName": "Прил + С",
    "3_docNum": 585378,
    "4_sentNum": 32,
    "5_start_ind": 6,
    "6_end_ind": 7,
    "7_lemmas": [
        "0_модель",
        "1_языковый"
    ]
},
{
    "0_key": "сравнительный анализ",
    "1_textForm": "сравнительного анализа",
    "2_modelName": "Прил + С",
    "3_docNum": 585378,
    "4_sentNum": 33,
    "5_start_ind": 17,
    "6_end_ind": 18,
    "7_lemmas": [
        "0_анализ",
        "1_сравнительный"
    ]
},
{
    "0_key": "возможность для сравнительный анализ",
    "1_textForm": "возможность для сравнительного анализа",
    "2_modelName": "С + Предл + (Прил + С)",
    "3_docNum": 585378,
    "4_sentNum": 33,
    "5_start_ind": 15,
    "6_end_ind": 18,
    "7_lemmas": [
        "0_анализ",
        "1_сравнительный",
        "2_для",
        "3_возможность"
    ]
},
{
    "0_key": "популярный сериал",
    "1_textForm": "популярный сериал",
    "2_modelName": "Прил + С",
    "3_docNum": 585378,
    "4_sentNum": 34,
    "5_start_ind": 1,
    "6_end_ind": 2,
    "7_lemmas": [
        "0_сериал",
        "1_популярный"
    ]
},
{
    "0_key": "реалистичность стиль",
    "1_textForm": "реалистичность стиля",
    "2_modelName": "С + Срд",
    "3_docNum": 585378,
    "4_sentNum": 37,
    "5_start_ind": 3,
    "6_end_ind": 4,
    "7_lemmas": [
        "0_реалистичность",
        "1_стиль"
    ]
},
{
    "0_key": "сгенерированный текст",
    "1_textForm": "сгенерированного текста",
    "2_modelName": "Прич + С",
    "3_docNum": 585378,
    "4_sentNum": 37,
    "5_start_ind": 5,
    "6_end_ind": 6,
    "7_lemmas": [
        "0_текст",
        "1_сгенерированный"
    ]
},
{
    "0_key": "зрительский опыт",
    "1_textForm": "зрительского опыта",
    "2_modelName": "Прил + С",
    "3_docNum": 585378,
    "4_sentNum": 37,
    "5_start_ind": 10,
    "6_end_ind": 11,
    "7_lemmas": [
        "0_опыт",
        "1_зрительский"
    ]
},
{
    "0_key": "стиль сгенерированный текст",
    "1_textForm": "стиля сгенерированного текста",
    "2_modelName": "C + (Прич + С)рд",
    "3_docNum": 585378,
    "4_sentNum": 37,
    "5_start_ind": 4,
    "6_end_ind": 6,
    "7_lemmas": [
        "0_текст",
        "1_сгенерированный",
        "2_стиль"
    ]
},
{
    "0_key": "сгенерированный текст на основание",
    "1_textForm": "сгенерированного текста на основании",
    "2_modelName": "(Прич + С) + Предл + С",
    "3_docNum": 585378,
    "4_sentNum": 37,
    "5_start_ind": 5,
    "6_end_ind": 8,
    "7_lemmas": [
        "0_текст",
        "1_сгенерированный",
        "2_на",
        "3_основание"
    ]
},
{
    "0_key": "сбор данный",
    "1_textForm": "Сбор данных",
    "2_modelName": "С + Срд",
    "3_docNum": 585378,
    "4_sentNum": 38,
    "5_start_ind": 0,
    "6_end_ind": 1,
    "7_lemmas": [
        "0_сбор",
        "1_данный"
    ]
},
{
    "0_key": "оригинальный транскрипта",
    "1_textForm": "Оригинальные транскрипты",
    "2_modelName": "Прил + С",
    "3_docNum": 585378,
    "4_sentNum": 39,
    "5_start_ind": 0,
    "6_end_ind": 1,
    "7_lemmas": [
        "0_транскрипта",
        "1_оригинальный"
    ]
},
{
    "0_key": "публичный доступ",
    "1_textForm": "публичном доступе",
    "2_modelName": "Прил + С",
    "3_docNum": 585378,
    "4_sentNum": 39,
    "5_start_ind": 19,
    "6_end_ind": 20,
    "7_lemmas": [
        "0_доступ",
        "1_публичный"
    ]
},
{
    "0_key": "предобработка текст",
    "1_textForm": "предобработку текста",
    "2_modelName": "С + Срд",
    "3_docNum": 585378,
    "4_sentNum": 41,
    "5_start_ind": 4,
    "6_end_ind": 5,
    "7_lemmas": [
        "0_предобработка",
        "1_текст"
    ]
},
{
    "0_key": "графемный ошибка",
    "1_textForm": "графемных ошибок",
    "2_modelName": "Прил + С",
    "3_docNum": 585378,
    "4_sentNum": 41,
    "5_start_ind": 18,
    "6_end_ind": 19,
    "7_lemmas": [
        "0_ошибка",
        "1_графемный"
    ]
},
{
    "0_key": "мелкий графемный ошибка",
    "1_textForm": "мелких графемных ошибок",
    "2_modelName": "Прил + С",
    "3_docNum": 585378,
    "4_sentNum": 41,
    "5_start_ind": 17,
    "6_end_ind": 19,
    "7_lemmas": [
        "0_ошибка",
        "1_графемный",
        "2_мелкий"
    ]
},
{
    "0_key": "данный от мелкий графемный ошибка",
    "1_textForm": "данные от мелких графемных ошибок",
    "2_modelName": "С + Предл + (Прил + С)",
    "3_docNum": 585378,
    "4_sentNum": 41,
    "5_start_ind": 15,
    "6_end_ind": 19,
    "7_lemmas": [
        "0_ошибка",
        "1_графемный",
        "2_мелкий",
        "3_от",
        "4_данный"
    ]
},
{
    "0_key": "восклицательный знаковый",
    "1_textForm": "восклицательных знаков",
    "2_modelName": "Прил + С",
    "3_docNum": 585378,
    "4_sentNum": 43,
    "5_start_ind": 6,
    "6_end_ind": 7,
    "7_lemmas": [
        "0_знаковый",
        "1_восклицательный"
    ]
},
{
    "0_key": "знаковый для имитация",
    "1_textForm": "знаков для имитации",
    "2_modelName": "С + Предл(Для) + С",
    "3_docNum": 585378,
    "4_sentNum": 43,
    "5_start_ind": 7,
    "6_end_ind": 9,
    "7_lemmas": [
        "0_знаковый",
        "1_для",
        "2_имитация"
    ]
},
{
    "0_key": "имитация эмоция",
    "1_textForm": "имитации эмоций",
    "2_modelName": "С + Срд",
    "3_docNum": 585378,
    "4_sentNum": 43,
    "5_start_ind": 9,
    "6_end_ind": 10,
    "7_lemmas": [
        "0_имитация",
        "1_эмоция"
    ]
},
{
    "0_key": "вопросительный и восклицательный знаковый",
    "1_textForm": "вопросительных и восклицательных знаков",
    "2_modelName": "Прил и (Прил + С)",
    "3_docNum": 585378,
    "4_sentNum": 43,
    "5_start_ind": 4,
    "6_end_ind": 7,
    "7_lemmas": [
        "0_знаковый",
        "1_восклицательный",
        "2_и",
        "3_вопросительный"
    ]
},
{
    "0_key": "восклицательный знаковый для имитация эмоция",
    "1_textForm": "восклицательных знаков для имитации эмоций",
    "2_modelName": "(Прил + С) + Предл + (С + Срд)",
    "3_docNum": 585378,
    "4_sentNum": 43,
    "5_start_ind": 6,
    "6_end_ind": 10,
    "7_lemmas": [
        "0_знаковый",
        "1_восклицательный",
        "2_для",
        "3_имитация",
        "4_эмоция"
    ]
},
{
    "0_key": "знаковый для имитация эмоция",
    "1_textForm": "знаков для имитации эмоций",
    "2_modelName": "С + Предл + (С + Срд)",
    "3_docNum": 585378,
    "4_sentNum": 43,
    "5_start_ind": 7,
    "6_end_ind": 10,
    "7_lemmas": [
        "0_имитация",
        "1_эмоция",
        "2_для",
        "3_знаковый"
    ]
},
{
    "0_key": "имитация эмоция на письмо",
    "1_textForm": "имитации эмоций на письме",
    "2_modelName": "(С + Срд) + Предл + С",
    "3_docNum": 585378,
    "4_sentNum": 43,
    "5_start_ind": 9,
    "6_end_ind": 12,
    "7_lemmas": [
        "0_имитация",
        "1_эмоция",
        "2_на",
        "3_письмо"
    ]
},
{
    "0_key": "очистка данный",
    "1_textForm": "очистке данных",
    "2_modelName": "С + Срд",
    "3_docNum": 585378,
    "4_sentNum": 49,
    "5_start_ind": 24,
    "6_end_ind": 25,
    "7_lemmas": [
        "0_очистка",
        "1_данный"
    ]
},
{
    "0_key": "слово для комичность",
    "1_textForm": "слова для комичности",
    "2_modelName": "С + Предл(Для) + С",
    "3_docNum": 585378,
    "4_sentNum": 50,
    "5_start_ind": 7,
    "6_end_ind": 9,
    "7_lemmas": [
        "0_слово",
        "1_для",
        "2_комичность"
    ]
},
{
    "0_key": "повторяемый слово",
    "1_textForm": "повторяемого слова",
    "2_modelName": "Прич + С",
    "3_docNum": 585378,
    "4_sentNum": 51,
    "5_start_ind": 10,
    "6_end_ind": 11,
    "7_lemmas": [
        "0_слово",
        "1_повторяемый"
    ]
},
{
    "0_key": "копия повторяемый слово",
    "1_textForm": "копию повторяемого слова",
    "2_modelName": "C + (Прич + С)рд",
    "3_docNum": 585378,
    "4_sentNum": 51,
    "5_start_ind": 9,
    "6_end_ind": 11,
    "7_lemmas": [
        "0_слово",
        "1_повторяемый",
        "2_копия"
    ]
},
{
    "0_key": "общеупотребительный фраза",
    "1_textForm": "общеупотребительные фразы",
    "2_modelName": "Прил + С",
    "3_docNum": 585378,
    "4_sentNum": 52,
    "5_start_ind": 14,
    "6_end_ind": 15,
    "7_lemmas": [
        "0_фраза",
        "1_общеупотребительный"
    ]
},
{
    "0_key": "корпус диалог",
    "1_textForm": "корпус диалогов",
    "2_modelName": "С + Срд",
    "3_docNum": 585378,
    "4_sentNum": 57,
    "5_start_ind": 5,
    "6_end_ind": 6,
    "7_lemmas": [
        "0_корпус",
        "1_диалог"
    ]
},
{
    "0_key": "подробный распределение",
    "1_textForm": "Подробное распределение",
    "2_modelName": "Прил + С",
    "3_docNum": 585378,
    "4_sentNum": 58,
    "5_start_ind": 0,
    "6_end_ind": 1,
    "7_lemmas": [
        "0_распределение",
        "1_подробный"
    ]
},
{
    "0_key": "число предложение",
    "1_textForm": "числу предложений",
    "2_modelName": "С + Срд",
    "3_docNum": 585378,
    "4_sentNum": 58,
    "5_start_ind": 3,
    "6_end_ind": 4,
    "7_lemmas": [
        "0_число",
        "1_предложение"
    ]
},
{
    "0_key": "анализ стиль",
    "1_textForm": "Анализ стилей",
    "2_modelName": "С + Срд",
    "3_docNum": 585378,
    "4_sentNum": 58,
    "5_start_ind": 16,
    "6_end_ind": 17,
    "7_lemmas": [
        "0_анализ",
        "1_стиль"
    ]
},
{
    "0_key": "анализ стиль персонаж",
    "1_textForm": "Анализ стилей персонажей",
    "2_modelName": "С + Срд",
    "3_docNum": 585378,
    "4_sentNum": 58,
    "5_start_ind": 16,
    "6_end_ind": 18,
    "7_lemmas": [
        "0_анализ",
        "1_стиль",
        "2_персонаж"
    ]
},
{
    "0_key": "стиль персонаж",
    "1_textForm": "стилей персонажей",
    "2_modelName": "С + Срд",
    "3_docNum": 585378,
    "4_sentNum": 58,
    "5_start_ind": 17,
    "6_end_ind": 18,
    "7_lemmas": [
        "0_стиль",
        "1_персонаж"
    ]
},
{
    "0_key": "подробный распределение по число предложение",
    "1_textForm": "Подробное распределение по числу предложений",
    "2_modelName": "(Прил + С) + Предл + (С + Срд)",
    "3_docNum": 585378,
    "4_sentNum": 58,
    "5_start_ind": 0,
    "6_end_ind": 4,
    "7_lemmas": [
        "0_распределение",
        "1_подробный",
        "2_по",
        "3_число",
        "4_предложение"
    ]
},
{
    "0_key": "число предложение и слово",
    "1_textForm": "числу предложений и слов",
    "2_modelName": "(С + Срд) + СоюзИ + С",
    "3_docNum": 585378,
    "4_sentNum": 58,
    "5_start_ind": 3,
    "6_end_ind": 6,
    "7_lemmas": [
        "0_число",
        "1_предложение",
        "2_и",
        "3_слово"
    ]
},
{
    "0_key": "распределение по число предложение",
    "1_textForm": "распределение по числу предложений",
    "2_modelName": "С + Предл + (С + Срд)",
    "3_docNum": 585378,
    "4_sentNum": 58,
    "5_start_ind": 1,
    "6_end_ind": 4,
    "7_lemmas": [
        "0_число",
        "1_предложение",
        "2_по",
        "3_распределение"
    ]
},
{
    "0_key": "языковый модель",
    "1_textForm": "языковые модели",
    "2_modelName": "Прил + С",
    "3_docNum": 585378,
    "4_sentNum": 59,
    "5_start_ind": 4,
    "6_end_ind": 5,
    "7_lemmas": [
        "0_модель",
        "1_языковый"
    ]
},
{
    "0_key": "особенность стиль",
    "1_textForm": "особенности стиля",
    "2_modelName": "С + Срд",
    "3_docNum": 585378,
    "4_sentNum": 59,
    "5_start_ind": 9,
    "6_end_ind": 10,
    "7_lemmas": [
        "0_особенность",
        "1_стиль"
    ]
},
{
    "0_key": "особенность речь",
    "1_textForm": "особенности речи",
    "2_modelName": "С + Срд",
    "3_docNum": 585378,
    "4_sentNum": 60,
    "5_start_ind": 5,
    "6_end_ind": 6,
    "7_lemmas": [
        "0_особенность",
        "1_речь"
    ]
},
{
    "0_key": "описательный статистика",
    "1_textForm": "описательные статистики",
    "2_modelName": "Прил + С",
    "3_docNum": 585378,
    "4_sentNum": 60,
    "5_start_ind": 15,
    "6_end_ind": 16,
    "7_lemmas": [
        "0_статистика",
        "1_описательный"
    ]
},
{
    "0_key": "число слово",
    "1_textForm": "число слов",
    "2_modelName": "С + Срд",
    "3_docNum": 585378,
    "4_sentNum": 60,
    "5_start_ind": 21,
    "6_end_ind": 22,
    "7_lemmas": [
        "0_число",
        "1_слово"
    ]
},
{
    "0_key": "средний количество",
    "1_textForm": "среднее количество",
    "2_modelName": "Прил + С",
    "3_docNum": 585378,
    "4_sentNum": 60,
    "5_start_ind": 24,
    "6_end_ind": 25,
    "7_lemmas": [
        "0_количество",
        "1_средний"
    ]
},
{
    "0_key": "количество слово",
    "1_textForm": "количество слов",
    "2_modelName": "С + Срд",
    "3_docNum": 585378,
    "4_sentNum": 60,
    "5_start_ind": 25,
    "6_end_ind": 26,
    "7_lemmas": [
        "0_количество",
        "1_слово"
    ]
},
{
    "0_key": "средний количество слово",
    "1_textForm": "среднее количество слов",
    "2_modelName": "(Прил + С) + Срд",
    "3_docNum": 585378,
    "4_sentNum": 60,
    "5_start_ind": 24,
    "6_end_ind": 26,
    "7_lemmas": [
        "0_количество",
        "1_средний",
        "2_слово"
    ]
},
{
    "0_key": "количество слово в предложение",
    "1_textForm": "количество слов в предложении",
    "2_modelName": "(С + Срд) + Предл + С",
    "3_docNum": 585378,
    "4_sentNum": 60,
    "5_start_ind": 25,
    "6_end_ind": 28,
    "7_lemmas": [
        "0_количество",
        "1_слово",
        "2_в",
        "3_предложение"
    ]
},
{
    "0_key": "персонаж слово",
    "1_textForm": "персонажей слова",
    "2_modelName": "С + Срд",
    "3_docNum": 585378,
    "4_sentNum": 62,
    "5_start_ind": 3,
    "6_end_ind": 4,
    "7_lemmas": [
        "0_персонаж",
        "1_слово"
    ]
},
{
    "0_key": "негативный слово",
    "1_textForm": "негативных слов",
    "2_modelName": "Прил + С",
    "3_docNum": 585378,
    "4_sentNum": 63,
    "5_start_ind": 3,
    "6_end_ind": 4,
    "7_lemmas": [
        "0_слово",
        "1_негативный"
    ]
},
{
    "0_key": "позитивный и негативный слово",
    "1_textForm": "позитивных и негативных слов",
    "2_modelName": "Прил и (Прил + С)",
    "3_docNum": 585378,
    "4_sentNum": 63,
    "5_start_ind": 1,
    "6_end_ind": 4,
    "7_lemmas": [
        "0_слово",
        "1_негативный",
        "2_и",
        "3_позитивный"
    ]
},
{
    "0_key": "предварительный вывод",
    "1_textForm": "предварительные выводы",
    "2_modelName": "Прил + С",
    "3_docNum": 585378,
    "4_sentNum": 64,
    "5_start_ind": 5,
    "6_end_ind": 6,
    "7_lemmas": [
        "0_вывод",
        "1_предварительный"
    ]
},
{
    "0_key": "специфика речь",
    "1_textForm": "специфике речи",
    "2_modelName": "С + Срд",
    "3_docNum": 585378,
    "4_sentNum": 64,
    "5_start_ind": 8,
    "6_end_ind": 9,
    "7_lemmas": [
        "0_специфика",
        "1_речь"
    ]
},
{
    "0_key": "специфика речь герой",
    "1_textForm": "специфике речи героев",
    "2_modelName": "С + Срд",
    "3_docNum": 585378,
    "4_sentNum": 64,
    "5_start_ind": 8,
    "6_end_ind": 10,
    "7_lemmas": [
        "0_специфика",
        "1_речь",
        "2_герой"
    ]
},
{
    "0_key": "речь герой",
    "1_textForm": "речи героев",
    "2_modelName": "С + Срд",
    "3_docNum": 585378,
    "4_sentNum": 64,
    "5_start_ind": 9,
    "6_end_ind": 10,
    "7_lemmas": [
        "0_речь",
        "1_герой"
    ]
},
{
    "0_key": "предварительный вывод о специфика речь",
    "1_textForm": "предварительные выводы о специфике речи",
    "2_modelName": "(Прил + С) + Предл + (С + Срд)",
    "3_docNum": 585378,
    "4_sentNum": 64,
    "5_start_ind": 5,
    "6_end_ind": 9,
    "7_lemmas": [
        "0_вывод",
        "1_предварительный",
        "2_о",
        "3_специфика",
        "4_речь"
    ]
},
{
    "0_key": "вывод о специфика речь герой",
    "1_textForm": "выводы о специфике речи героев",
    "2_modelName": "С + Предл + (С + Срд)",
    "3_docNum": 585378,
    "4_sentNum": 64,
    "5_start_ind": 6,
    "6_end_ind": 10,
    "7_lemmas": [
        "0_специфика",
        "1_речь",
        "2_герой",
        "3_о",
        "4_вывод"
    ]
},
{
    "0_key": "максимальный число",
    "1_textForm": "максимальное число",
    "2_modelName": "Прил + С",
    "3_docNum": 585378,
    "4_sentNum": 65,
    "5_start_ind": 10,
    "6_end_ind": 11,
    "7_lemmas": [
        "0_число",
        "1_максимальный"
    ]
},
{
    "0_key": "число предложение",
    "1_textForm": "число предложений",
    "2_modelName": "С + Срд",
    "3_docNum": 585378,
    "4_sentNum": 65,
    "5_start_ind": 11,
    "6_end_ind": 12,
    "7_lemmas": [
        "0_число",
        "1_предложение"
    ]
},
{
    "0_key": "максимальный число предложение",
    "1_textForm": "максимальное число предложений",
    "2_modelName": "(Прил + С) + Срд",
    "3_docNum": 585378,
    "4_sentNum": 65,
    "5_start_ind": 10,
    "6_end_ind": 12,
    "7_lemmas": [
        "0_число",
        "1_максимальный",
        "2_предложение"
    ]
},
{
    "0_key": "количество предложение",
    "1_textForm": "количество предложений",
    "2_modelName": "С + Срд",
    "3_docNum": 585378,
    "4_sentNum": 66,
    "5_start_ind": 5,
    "6_end_ind": 6,
    "7_lemmas": [
        "0_количество",
        "1_предложение"
    ]
},
{
    "0_key": "особенность структура",
    "1_textForm": "особенностями структуры",
    "2_modelName": "С + Срд",
    "3_docNum": 585378,
    "4_sentNum": 67,
    "5_start_ind": 4,
    "6_end_ind": 5,
    "7_lemmas": [
        "0_особенность",
        "1_структура"
    ]
},
{
    "0_key": "русский язык",
    "1_textForm": "русского языка",
    "2_modelName": "Прил + С",
    "3_docNum": 585378,
    "4_sentNum": 67,
    "5_start_ind": 17,
    "6_end_ind": 18,
    "7_lemmas": [
        "0_язык",
        "1_русский"
    ]
},
{
    "0_key": "автоматический перевод",
    "1_textForm": "автоматическом переводе",
    "2_modelName": "Прил + С",
    "3_docNum": 585378,
    "4_sentNum": 67,
    "5_start_ind": 25,
    "6_end_ind": 26,
    "7_lemmas": [
        "0_перевод",
        "1_автоматический"
    ]
},
{
    "0_key": "пунктуация для русский язык",
    "1_textForm": "пунктуации для русского языка",
    "2_modelName": "С + Предл + (Прил + С)",
    "3_docNum": 585378,
    "4_sentNum": 67,
    "5_start_ind": 15,
    "6_end_ind": 18,
    "7_lemmas": [
        "0_язык",
        "1_русский",
        "2_для",
        "3_пунктуация"
    ]
},
{
    "0_key": "первичный анализ",
    "1_textForm": "первичного анализа",
    "2_modelName": "Прил + С",
    "3_docNum": 585378,
    "4_sentNum": 68,
    "5_start_ind": 2,
    "6_end_ind": 3,
    "7_lemmas": [
        "0_анализ",
        "1_первичный"
    ]
},
{
    "0_key": "анализ речь",
    "1_textForm": "анализа речи",
    "2_modelName": "С + Срд",
    "3_docNum": 585378,
    "4_sentNum": 68,
    "5_start_ind": 3,
    "6_end_ind": 4,
    "7_lemmas": [
        "0_анализ",
        "1_речь"
    ]
},
{
    "0_key": "словарный запас",
    "1_textForm": "словарный запас",
    "2_modelName": "Прил + С",
    "3_docNum": 585378,
    "4_sentNum": 68,
    "5_start_ind": 7,
    "6_end_ind": 8,
    "7_lemmas": [
        "0_запас",
        "1_словарный"
    ]
},
{
    "0_key": "зрение сложность",
    "1_textForm": "зрения сложности",
    "2_modelName": "С + Срд",
    "3_docNum": 585378,
    "4_sentNum": 68,
    "5_start_ind": 18,
    "6_end_ind": 19,
    "7_lemmas": [
        "0_зрение",
        "1_сложность"
    ]
},
{
    "0_key": "используемый герой",
    "1_textForm": "используемых героями",
    "2_modelName": "Прич + С",
    "3_docNum": 585378,
    "4_sentNum": 68,
    "5_start_ind": 21,
    "6_end_ind": 22,
    "7_lemmas": [
        "0_герой",
        "1_используемый"
    ]
},
{
    "0_key": "герой слово",
    "1_textForm": "героями слов",
    "2_modelName": "С + Срд",
    "3_docNum": 585378,
    "4_sentNum": 68,
    "5_start_ind": 22,
    "6_end_ind": 23,
    "7_lemmas": [
        "0_герой",
        "1_слово"
    ]
},
{
    "0_key": "первичный анализ речь",
    "1_textForm": "первичного анализа речи",
    "2_modelName": "(Прил + С) + Срд",
    "3_docNum": 585378,
    "4_sentNum": 68,
    "5_start_ind": 2,
    "6_end_ind": 4,
    "7_lemmas": [
        "0_анализ",
        "1_первичный",
        "2_речь"
    ]
},
{
    "0_key": "используемый герой слово",
    "1_textForm": "используемых героями слов",
    "2_modelName": "(Прич + С) + Срд",
    "3_docNum": 585378,
    "4_sentNum": 68,
    "5_start_ind": 21,
    "6_end_ind": 23,
    "7_lemmas": [
        "0_герой",
        "1_используемый",
        "2_слово"
    ]
},
{
    "0_key": "речь персонаж",
    "1_textForm": "Речь персонажей",
    "2_modelName": "С + Срд",
    "3_docNum": 585378,
    "4_sentNum": 70,
    "5_start_ind": 12,
    "6_end_ind": 13,
    "7_lemmas": [
        "0_речь",
        "1_персонаж"
    ]
},
{
    "0_key": "занудный ученый-палеонтолог",
    "1_textForm": "занудный ученый-палеонтолог",
    "2_modelName": "Прил + С",
    "3_docNum": 585378,
    "4_sentNum": 71,
    "5_start_ind": 7,
    "6_end_ind": 8,
    "7_lemmas": [
        "0_ученый-палеонтолог",
        "1_занудный"
    ]
},
{
    "0_key": "больший процент",
    "1_textForm": "наибольший процент",
    "2_modelName": "Прил + С",
    "3_docNum": 585378,
    "4_sentNum": 71,
    "5_start_ind": 11,
    "6_end_ind": 12,
    "7_lemmas": [
        "0_процент",
        "1_больший"
    ]
},
{
    "0_key": "статистический мера",
    "1_textForm": "статистическая мера",
    "2_modelName": "Прил + С",
    "3_docNum": 585378,
    "4_sentNum": 73,
    "5_start_ind": 7,
    "6_end_ind": 8,
    "7_lemmas": [
        "0_мера",
        "1_статистический"
    ]
},
{
    "0_key": "данный герой",
    "1_textForm": "данного героя",
    "2_modelName": "Прич + С",
    "3_docNum": 585378,
    "4_sentNum": 73,
    "5_start_ind": 18,
    "6_end_ind": 19,
    "7_lemmas": [
        "0_герой",
        "1_данный"
    ]
},
{
    "0_key": "частотный слово",
    "1_textForm": "частотные слова",
    "2_modelName": "Прил + С",
    "3_docNum": 585378,
    "4_sentNum": 73,
    "5_start_ind": 31,
    "6_end_ind": 32,
    "7_lemmas": [
        "0_слово",
        "1_частотный"
    ]
},
{
    "0_key": "частотный слово и стоп-слово",
    "1_textForm": "частотные слова и стоп-слова",
    "2_modelName": "(Прил + С) + СоюзИ + С",
    "3_docNum": 585378,
    "4_sentNum": 73,
    "5_start_ind": 31,
    "6_end_ind": 34,
    "7_lemmas": [
        "0_слово",
        "1_частотный",
        "2_и",
        "3_стоп-слово"
    ]
},
{
    "0_key": "мусорный стоп-слов",
    "1_textForm": "мусорным стоп-словам",
    "2_modelName": "Прил + С",
    "3_docNum": 585378,
    "4_sentNum": 74,
    "5_start_ind": 2,
    "6_end_ind": 3,
    "7_lemmas": [
        "0_стоп-слов",
        "1_мусорный"
    ]
},
{
    "0_key": "результат для росс",
    "1_textForm": "результаты для Росса",
    "2_modelName": "С + Предл(Для) + С",
    "3_docNum": 585378,
    "4_sentNum": 76,
    "5_start_ind": 4,
    "6_end_ind": 6,
    "7_lemmas": [
        "0_результат",
        "1_для",
        "2_росс"
    ]
},
{
    "0_key": "размер слово",
    "1_textForm": "Размер слова",
    "2_modelName": "С + Срд",
    "3_docNum": 585378,
    "4_sentNum": 77,
    "5_start_ind": 0,
    "6_end_ind": 1,
    "7_lemmas": [
        "0_размер",
        "1_слово"
    ]
},
{
    "0_key": "tf-idf вес",
    "1_textForm": "TF-IDF весу",
    "2_modelName": "Прил + С",
    "3_docNum": 585378,
    "4_sentNum": 77,
    "5_start_ind": 4,
    "6_end_ind": 5,
    "7_lemmas": [
        "0_вес",
        "1_tf-idf"
    ]
},
{
    "0_key": "данный герой",
    "1_textForm": "данного героя",
    "2_modelName": "Прич + С",
    "3_docNum": 585378,
    "4_sentNum": 77,
    "5_start_ind": 7,
    "6_end_ind": 8,
    "7_lemmas": [
        "0_герой",
        "1_данный"
    ]
},
{
    "0_key": "tf-idf вес для данный герой",
    "1_textForm": "TF-IDF весу для данного героя",
    "2_modelName": "(Прил + С) + Предл + (Прич + С)",
    "3_docNum": 585378,
    "4_sentNum": 77,
    "5_start_ind": 4,
    "6_end_ind": 8,
    "7_lemmas": [
        "0_вес",
        "1_tf-idf",
        "2_для",
        "3_данный",
        "4_герой"
    ]
},
{
    "0_key": "вес для данный герой",
    "1_textForm": "весу для данного героя",
    "2_modelName": "С + Предл + (Прич + С)",
    "3_docNum": 585378,
    "4_sentNum": 77,
    "5_start_ind": 5,
    "6_end_ind": 8,
    "7_lemmas": [
        "0_герой",
        "1_данный",
        "2_для",
        "3_вес"
    ]
},
{
    "0_key": "характерный аналог",
    "1_textForm": "характерного аналога",
    "2_modelName": "Прил + С",
    "3_docNum": 585378,
    "4_sentNum": 79,
    "5_start_ind": 30,
    "6_end_ind": 31,
    "7_lemmas": [
        "0_аналог",
        "1_характерный"
    ]
},
{
    "0_key": "специфический лексика",
    "1_textForm": "специфической лексике",
    "2_modelName": "Прил + С",
    "3_docNum": 585378,
    "4_sentNum": 81,
    "5_start_ind": 4,
    "6_end_ind": 5,
    "7_lemmas": [
        "0_лексика",
        "1_специфический"
    ]
},
{
    "0_key": "лексика герой",
    "1_textForm": "лексике героев",
    "2_modelName": "С + Срд",
    "3_docNum": 585378,
    "4_sentNum": 81,
    "5_start_ind": 5,
    "6_end_ind": 6,
    "7_lemmas": [
        "0_лексика",
        "1_герой"
    ]
},
{
    "0_key": "полный соответствие",
    "1_textForm": "полного соответствия",
    "2_modelName": "Прил + С",
    "3_docNum": 585378,
    "4_sentNum": 81,
    "5_start_ind": 10,
    "6_end_ind": 11,
    "7_lemmas": [
        "0_соответствие",
        "1_полный"
    ]
},
{
    "0_key": "специфический лексика герой",
    "1_textForm": "специфической лексике героев",
    "2_modelName": "(Прил + С) + Срд",
    "3_docNum": 585378,
    "4_sentNum": 81,
    "5_start_ind": 4,
    "6_end_ind": 6,
    "7_lemmas": [
        "0_лексика",
        "1_специфический",
        "2_герой"
    ]
},
{
    "0_key": "полный соответствие и набор",
    "1_textForm": "полного соответствия и набор",
    "2_modelName": "(Прил + С) + СоюзИ + С",
    "3_docNum": 585378,
    "4_sentNum": 81,
    "5_start_ind": 10,
    "6_end_ind": 13,
    "7_lemmas": [
        "0_соответствие",
        "1_полный",
        "2_и",
        "3_набор"
    ]
},
{
    "0_key": "характерный слово",
    "1_textForm": "характерные слова",
    "2_modelName": "Прил + С",
    "3_docNum": 585378,
    "4_sentNum": 82,
    "5_start_ind": 6,
    "6_end_ind": 7,
    "7_lemmas": [
        "0_слово",
        "1_характерный"
    ]
},
{
    "0_key": "русскоязычный росс",
    "1_textForm": "русскоязычный Росс",
    "2_modelName": "Прил + С",
    "3_docNum": 585378,
    "4_sentNum": 83,
    "5_start_ind": 13,
    "6_end_ind": 14,
    "7_lemmas": [
        "0_росс",
        "1_русскоязычный"
    ]
},
{
    "0_key": "англоязычный версия",
    "1_textForm": "англоязычная версия",
    "2_modelName": "Прил + С",
    "3_docNum": 585378,
    "4_sentNum": 83,
    "5_start_ind": 28,
    "6_end_ind": 29,
    "7_lemmas": [
        "0_версия",
        "1_англоязычный"
    ]
},
{
    "0_key": "анализ стиль",
    "1_textForm": "анализа стиля",
    "2_modelName": "С + Срд",
    "3_docNum": 585378,
    "4_sentNum": 84,
    "5_start_ind": 3,
    "6_end_ind": 4,
    "7_lemmas": [
        "0_анализ",
        "1_стиль"
    ]
},
{
    "0_key": "окрашенный слово",
    "1_textForm": "окрашенных слов",
    "2_modelName": "Прич + С",
    "3_docNum": 585378,
    "4_sentNum": 85,
    "5_start_ind": 6,
    "6_end_ind": 7,
    "7_lemmas": [
        "0_слово",
        "1_окрашенный"
    ]
},
{
    "0_key": "доля слово",
    "1_textForm": "долю слов",
    "2_modelName": "С + Срд",
    "3_docNum": 585378,
    "4_sentNum": 88,
    "5_start_ind": 3,
    "6_end_ind": 4,
    "7_lemmas": [
        "0_доля",
        "1_слово"
    ]
},
{
    "0_key": "речь персонаж",
    "1_textForm": "речи персонажей",
    "2_modelName": "С + Срд",
    "3_docNum": 585378,
    "4_sentNum": 88,
    "5_start_ind": 8,
    "6_end_ind": 9,
    "7_lemmas": [
        "0_речь",
        "1_персонаж"
    ]
},
{
    "0_key": "класс в речь персонаж",
    "1_textForm": "класса в речи персонажей",
    "2_modelName": "С + Предл + (С + Срд)",
    "3_docNum": 585378,
    "4_sentNum": 88,
    "5_start_ind": 6,
    "6_end_ind": 9,
    "7_lemmas": [
        "0_речь",
        "1_персонаж",
        "2_в",
        "3_класс"
    ]
},
{
    "0_key": "негативный слово",
    "1_textForm": "негативные слова",
    "2_modelName": "Прил + С",
    "3_docNum": 585378,
    "4_sentNum": 90,
    "5_start_ind": 8,
    "6_end_ind": 9,
    "7_lemmas": [
        "0_слово",
        "1_негативный"
    ]
},
{
    "0_key": "одинаковый частота",
    "1_textForm": "одинаковой частотой",
    "2_modelName": "Прил + С",
    "3_docNum": 585378,
    "4_sentNum": 90,
    "5_start_ind": 12,
    "6_end_ind": 13,
    "7_lemmas": [
        "0_частота",
        "1_одинаковый"
    ]
},
{
    "0_key": "доля негатив",
    "1_textForm": "доля негатива",
    "2_modelName": "С + Срд",
    "3_docNum": 585378,
    "4_sentNum": 91,
    "5_start_ind": 19,
    "6_end_ind": 20,
    "7_lemmas": [
        "0_доля",
        "1_негатив"
    ]
},
{
    "0_key": "позитивный слово",
    "1_textForm": "позитивных слов",
    "2_modelName": "Прил + С",
    "3_docNum": 585378,
    "4_sentNum": 92,
    "5_start_ind": 26,
    "6_end_ind": 27,
    "7_lemmas": [
        "0_слово",
        "1_позитивный"
    ]
},
{
    "0_key": "доля позитивный слово",
    "1_textForm": "долей позитивных слов",
    "2_modelName": "C + (Прил + С)рд",
    "3_docNum": 585378,
    "4_sentNum": 92,
    "5_start_ind": 25,
    "6_end_ind": 27,
    "7_lemmas": [
        "0_слово",
        "1_позитивный",
        "2_доля"
    ]
},
{
    "0_key": "проявление эмоция",
    "1_textForm": "проявлению эмоций",
    "2_modelName": "С + Срд",
    "3_docNum": 585378,
    "4_sentNum": 93,
    "5_start_ind": 24,
    "6_end_ind": 25,
    "7_lemmas": [
        "0_проявление",
        "1_эмоция"
    ]
},
{
    "0_key": "стилистический анализ",
    "1_textForm": "стилистического анализа",
    "2_modelName": "Прил + С",
    "3_docNum": 585378,
    "4_sentNum": 94,
    "5_start_ind": 7,
    "6_end_ind": 8,
    "7_lemmas": [
        "0_анализ",
        "1_стилистический"
    ]
},
{
    "0_key": "результат стилистический анализ",
    "1_textForm": "результаты стилистического анализа",
    "2_modelName": "C + (Прил + С)рд",
    "3_docNum": 585378,
    "4_sentNum": 94,
    "5_start_ind": 6,
    "6_end_ind": 8,
    "7_lemmas": [
        "0_анализ",
        "1_стилистический",
        "2_результат"
    ]
},
{
    "0_key": "занудный ученый",
    "1_textForm": "занудный ученый",
    "2_modelName": "Прил + С",
    "3_docNum": 585378,
    "4_sentNum": 95,
    "5_start_ind": 3,
    "6_end_ind": 4,
    "7_lemmas": [
        "0_ученый",
        "1_занудный"
    ]
},
{
    "0_key": "беззаботный героиня",
    "1_textForm": "беззаботная героиня",
    "2_modelName": "Прил + С",
    "3_docNum": 585378,
    "4_sentNum": 96,
    "5_start_ind": 4,
    "6_end_ind": 5,
    "7_lemmas": [
        "0_героиня",
        "1_беззаботный"
    ]
},
{
    "0_key": "несложный речь",
    "1_textForm": "несложной речью",
    "2_modelName": "Прил + С",
    "3_docNum": 585378,
    "4_sentNum": 96,
    "5_start_ind": 10,
    "6_end_ind": 11,
    "7_lemmas": [
        "0_речь",
        "1_несложный"
    ]
},
{
    "0_key": "позитивный и беззаботный героиня",
    "1_textForm": "позитивная и беззаботная героиня",
    "2_modelName": "Прил и (Прил + С)",
    "3_docNum": 585378,
    "4_sentNum": 96,
    "5_start_ind": 2,
    "6_end_ind": 5,
    "7_lemmas": [
        "0_героиня",
        "1_беззаботный",
        "2_и",
        "3_позитивный"
    ]
},
{
    "0_key": "финальный датасет",
    "1_textForm": "финального датасета",
    "2_modelName": "Прил + С",
    "3_docNum": 585378,
    "4_sentNum": 98,
    "5_start_ind": 1,
    "6_end_ind": 2,
    "7_lemmas": [
        "0_датасет",
        "1_финальный"
    ]
},
{
    "0_key": "дополнительный набор",
    "1_textForm": "дополнительным набором",
    "2_modelName": "Прил + С",
    "3_docNum": 585378,
    "4_sentNum": 100,
    "5_start_ind": 6,
    "6_end_ind": 7,
    "7_lemmas": [
        "0_набор",
        "1_дополнительный"
    ]
},
{
    "0_key": "специальный токен",
    "1_textForm": "Специальные токены",
    "2_modelName": "Прил + С",
    "3_docNum": 585378,
    "4_sentNum": 100,
    "5_start_ind": 12,
    "6_end_ind": 13,
    "7_lemmas": [
        "0_токен",
        "1_специальный"
    ]
},
{
    "0_key": "реплика дополнительный набор",
    "1_textForm": "реплики дополнительным набором",
    "2_modelName": "C + (Прил + С)рд",
    "3_docNum": 585378,
    "4_sentNum": 100,
    "5_start_ind": 5,
    "6_end_ind": 7,
    "7_lemmas": [
        "0_набор",
        "1_дополнительный",
        "2_реплика"
    ]
},
{
    "0_key": "автор реплика",
    "1_textForm": "автора реплики",
    "2_modelName": "С + Срд",
    "3_docNum": 585378,
    "4_sentNum": 101,
    "5_start_ind": 6,
    "6_end_ind": 7,
    "7_lemmas": [
        "0_автор",
        "1_реплика"
    ]
},
{
    "0_key": "заглавный буква",
    "1_textForm": "заглавными буквами",
    "2_modelName": "Прил + С",
    "3_docNum": 585378,
    "4_sentNum": 101,
    "5_start_ind": 11,
    "6_end_ind": 12,
    "7_lemmas": [
        "0_буква",
        "1_заглавный"
    ]
},
{
    "0_key": "специальный псевдоним",
    "1_textForm": "Специальный псевдоним",
    "2_modelName": "Прил + С",
    "3_docNum": 585378,
    "4_sentNum": 102,
    "5_start_ind": 0,
    "6_end_ind": 1,
    "7_lemmas": [
        "0_псевдоним",
        "1_специальный"
    ]
},
{
    "0_key": "маркер реплика",
    "1_textForm": "маркером реплики",
    "2_modelName": "С + Срд",
    "3_docNum": 585378,
    "4_sentNum": 102,
    "5_start_ind": 9,
    "6_end_ind": 10,
    "7_lemmas": [
        "0_маркер",
        "1_реплика"
    ]
},
{
    "0_key": "диалоговый пара",
    "1_textForm": "диалоговых парах",
    "2_modelName": "Прил + С",
    "3_docNum": 585378,
    "4_sentNum": 102,
    "5_start_ind": 14,
    "6_end_ind": 15,
    "7_lemmas": [
        "0_пара",
        "1_диалоговый"
    ]
},
{
    "0_key": "дополнительный токено",
    "1_textForm": "дополнительными токенами",
    "2_modelName": "Прил + С",
    "3_docNum": 585378,
    "4_sentNum": 104,
    "5_start_ind": 3,
    "6_end_ind": 4,
    "7_lemmas": [
        "0_токено",
        "1_дополнительный"
    ]
},
{
    "0_key": "вид датасет",
    "1_textForm": "вида датасетов",
    "2_modelName": "С + Срд",
    "3_docNum": 585378,
    "4_sentNum": 104,
    "5_start_ind": 10,
    "6_end_ind": 11,
    "7_lemmas": [
        "0_вид",
        "1_датасет"
    ]
},
{
    "0_key": "английский язык",
    "1_textForm": "английского языков",
    "2_modelName": "Прил + С",
    "3_docNum": 585378,
    "4_sentNum": 104,
    "5_start_ind": 18,
    "6_end_ind": 19,
    "7_lemmas": [
        "0_язык",
        "1_английский"
    ]
},
{
    "0_key": "данный с дополнительный токено",
    "1_textForm": "данные с дополнительными токенами",
    "2_modelName": "С + Предл + (Прил + С)",
    "3_docNum": 585378,
    "4_sentNum": 104,
    "5_start_ind": 1,
    "6_end_ind": 4,
    "7_lemmas": [
        "0_токено",
        "1_дополнительный",
        "2_с",
        "3_данный"
    ]
},
{
    "0_key": "русский и английский язык",
    "1_textForm": "русского и английского языков",
    "2_modelName": "Прил и (Прил + С)",
    "3_docNum": 585378,
    "4_sentNum": 104,
    "5_start_ind": 16,
    "6_end_ind": 19,
    "7_lemmas": [
        "0_язык",
        "1_английский",
        "2_и",
        "3_русский"
    ]
},
{
    "0_key": "отдельный реплика",
    "1_textForm": "отдельные реплики",
    "2_modelName": "Прил + С",
    "3_docNum": 585378,
    "4_sentNum": 106,
    "5_start_ind": 9,
    "6_end_ind": 10,
    "7_lemmas": [
        "0_реплика",
        "1_отдельный"
    ]
},
{
    "0_key": "больший информация",
    "1_textForm": "наибольшую информации",
    "2_modelName": "Прил + С",
    "3_docNum": 585378,
    "4_sentNum": 107,
    "5_start_ind": 5,
    "6_end_ind": 6,
    "7_lemmas": [
        "0_информация",
        "1_больший"
    ]
},
{
    "0_key": "конкретный персонаж",
    "1_textForm": "конкретного персонажа",
    "2_modelName": "Прил + С",
    "3_docNum": 585378,
    "4_sentNum": 107,
    "5_start_ind": 9,
    "6_end_ind": 10,
    "7_lemmas": [
        "0_персонаж",
        "1_конкретный"
    ]
},
{
    "0_key": "больший информация о стиль",
    "1_textForm": "наибольшую информации о стиле",
    "2_modelName": "(Прил + С) + Предл + С",
    "3_docNum": 585378,
    "4_sentNum": 107,
    "5_start_ind": 5,
    "6_end_ind": 8,
    "7_lemmas": [
        "0_информация",
        "1_больший",
        "2_о",
        "3_стиль"
    ]
},
{
    "0_key": "стиль конкретный персонаж",
    "1_textForm": "стиле конкретного персонажа",
    "2_modelName": "C + (Прил + С)рд",
    "3_docNum": 585378,
    "4_sentNum": 107,
    "5_start_ind": 8,
    "6_end_ind": 10,
    "7_lemmas": [
        "0_персонаж",
        "1_конкретный",
        "2_стиль"
    ]
},
{
    "0_key": "содержащий пара",
    "1_textForm": "содержащий пары",
    "2_modelName": "Прич + С",
    "3_docNum": 585378,
    "4_sentNum": 109,
    "5_start_ind": 8,
    "6_end_ind": 9,
    "7_lemmas": [
        "0_пара",
        "1_содержащий"
    ]
},
{
    "0_key": "реплика недруг",
    "1_textForm": "реплика НЕДРУГА",
    "2_modelName": "С + Срд",
    "3_docNum": 585378,
    "4_sentNum": 109,
    "5_start_ind": 11,
    "6_end_ind": 12,
    "7_lemmas": [
        "0_реплика",
        "1_недруг"
    ]
},
{
    "0_key": "ответ герой",
    "1_textForm": "ответ ГЕРОЯ",
    "2_modelName": "С + Срд",
    "3_docNum": 585378,
    "4_sentNum": 109,
    "5_start_ind": 14,
    "6_end_ind": 15,
    "7_lemmas": [
        "0_ответ",
        "1_герой"
    ]
},
{
    "0_key": "разделенный символ",
    "1_textForm": "разделенные символом",
    "2_modelName": "Прич + С",
    "3_docNum": 585378,
    "4_sentNum": 109,
    "5_start_ind": 18,
    "6_end_ind": 19,
    "7_lemmas": [
        "0_символ",
        "1_разделенный"
    ]
},
{
    "0_key": "символ перенос",
    "1_textForm": "символом переноса",
    "2_modelName": "С + Срд",
    "3_docNum": 585378,
    "4_sentNum": 109,
    "5_start_ind": 19,
    "6_end_ind": 20,
    "7_lemmas": [
        "0_символ",
        "1_перенос"
    ]
},
{
    "0_key": "символ перенос строка",
    "1_textForm": "символом переноса строки",
    "2_modelName": "С + Срд",
    "3_docNum": 585378,
    "4_sentNum": 109,
    "5_start_ind": 19,
    "6_end_ind": 21,
    "7_lemmas": [
        "0_символ",
        "1_перенос",
        "2_строка"
    ]
},
{
    "0_key": "перенос строка",
    "1_textForm": "переноса строки",
    "2_modelName": "С + Срд",
    "3_docNum": 585378,
    "4_sentNum": 109,
    "5_start_ind": 20,
    "6_end_ind": 21,
    "7_lemmas": [
        "0_перенос",
        "1_строка"
    ]
},
{
    "0_key": "разделенный символ перенос строка",
    "1_textForm": "разделенные символом переноса строки",
    "2_modelName": "(Прич + С) + Срд",
    "3_docNum": 585378,
    "4_sentNum": 109,
    "5_start_ind": 18,
    "6_end_ind": 21,
    "7_lemmas": [
        "0_символ",
        "1_разделенный",
        "2_перенос",
        "3_строка"
    ]
},
{
    "0_key": "диалоговый датасет",
    "1_textForm": "Диалоговый датасет",
    "2_modelName": "Прил + С",
    "3_docNum": 585378,
    "4_sentNum": 110,
    "5_start_ind": 0,
    "6_end_ind": 1,
    "7_lemmas": [
        "0_датасет",
        "1_диалоговый"
    ]
},
{
    "0_key": "очищенный диалог",
    "1_textForm": "очищенные диалоги",
    "2_modelName": "Прич + С",
    "3_docNum": 585378,
    "4_sentNum": 112,
    "5_start_ind": 3,
    "6_end_ind": 4,
    "7_lemmas": [
        "0_диалог",
        "1_очищенный"
    ]
},
{
    "0_key": "диалоговый датасет",
    "1_textForm": "диалогового датасета",
    "2_modelName": "Прил + С",
    "3_docNum": 585378,
    "4_sentNum": 112,
    "5_start_ind": 9,
    "6_end_ind": 10,
    "7_lemmas": [
        "0_датасет",
        "1_диалоговый"
    ]
},
{
    "0_key": "предыдущий диалоговый датасет",
    "1_textForm": "предыдущего диалогового датасета",
    "2_modelName": "Прил + С",
    "3_docNum": 585378,
    "4_sentNum": 112,
    "5_start_ind": 8,
    "6_end_ind": 10,
    "7_lemmas": [
        "0_датасет",
        "1_диалоговый",
        "2_предыдущий"
    ]
},
{
    "0_key": "частотный реплика",
    "1_textForm": "частотные реплики",
    "2_modelName": "Прил + С",
    "3_docNum": 585378,
    "4_sentNum": 112,
    "5_start_ind": 16,
    "6_end_ind": 17,
    "7_lemmas": [
        "0_реплика",
        "1_частотный"
    ]
},
{
    "0_key": "конкретный персонаж",
    "1_textForm": "конкретного персонажа",
    "2_modelName": "Прил + С",
    "3_docNum": 585378,
    "4_sentNum": 112,
    "5_start_ind": 29,
    "6_end_ind": 30,
    "7_lemmas": [
        "0_персонаж",
        "1_конкретный"
    ]
},
{
    "0_key": "модификация предыдущий диалоговый датасет",
    "1_textForm": "модификация предыдущего диалогового датасета",
    "2_modelName": "C + (Прил + С)рд",
    "3_docNum": 585378,
    "4_sentNum": 112,
    "5_start_ind": 7,
    "6_end_ind": 10,
    "7_lemmas": [
        "0_датасет",
        "1_диалоговый",
        "2_предыдущий",
        "3_модификация"
    ]
},
{
    "0_key": "стиль конкретный персонаж",
    "1_textForm": "стиле конкретного персонажа",
    "2_modelName": "C + (Прил + С)рд",
    "3_docNum": 585378,
    "4_sentNum": 112,
    "5_start_ind": 28,
    "6_end_ind": 30,
    "7_lemmas": [
        "0_персонаж",
        "1_конкретный",
        "2_стиль"
    ]
},
{
    "0_key": "языковый модель",
    "1_textForm": "языковые модели",
    "2_modelName": "Прил + С",
    "3_docNum": 585378,
    "4_sentNum": 115,
    "5_start_ind": 28,
    "6_end_ind": 29,
    "7_lemmas": [
        "0_модель",
        "1_языковый"
    ]
},
{
    "0_key": "подход файна-тьюнинг",
    "1_textForm": "подход файн-тьюнинга",
    "2_modelName": "С + Срд",
    "3_docNum": 585378,
    "4_sentNum": 117,
    "5_start_ind": 18,
    "6_end_ind": 19,
    "7_lemmas": [
        "0_подход",
        "1_файна-тьюнинг"
    ]
},
{
    "0_key": "языковый модель",
    "1_textForm": "языковых моделей",
    "2_modelName": "Прил + С",
    "3_docNum": 585378,
    "4_sentNum": 117,
    "5_start_ind": 21,
    "6_end_ind": 22,
    "7_lemmas": [
        "0_модель",
        "1_языковый"
    ]
},
{
    "0_key": "трансформерный языковый модель",
    "1_textForm": "трансформерных языковых моделей",
    "2_modelName": "Прил + С",
    "3_docNum": 585378,
    "4_sentNum": 117,
    "5_start_ind": 20,
    "6_end_ind": 22,
    "7_lemmas": [
        "0_модель",
        "1_языковый",
        "2_трансформерный"
    ]
},
{
    "0_key": "gpt модель",
    "1_textForm": "GPT моделей",
    "2_modelName": "С + Срд",
    "3_docNum": 585378,
    "4_sentNum": 117,
    "5_start_ind": 26,
    "6_end_ind": 27,
    "7_lemmas": [
        "0_gpt",
        "1_модель"
    ]
},
{
    "0_key": "файна-тьюнинг трансформерный языковый модель",
    "1_textForm": "файн-тьюнинга трансформерных языковых моделей",
    "2_modelName": "C + (Прил + С)рд",
    "3_docNum": 585378,
    "4_sentNum": 117,
    "5_start_ind": 19,
    "6_end_ind": 22,
    "7_lemmas": [
        "0_модель",
        "1_языковый",
        "2_трансформерный",
        "3_файна-тьюнинг"
    ]
},
{
    "0_key": "русский язык",
    "1_textForm": "русского языка",
    "2_modelName": "Прил + С",
    "3_docNum": 585378,
    "4_sentNum": 118,
    "5_start_ind": 1,
    "6_end_ind": 2,
    "7_lemmas": [
        "0_язык",
        "1_русский"
    ]
},
{
    "0_key": "английский язык",
    "1_textForm": "английского языка",
    "2_modelName": "Прил + С",
    "3_docNum": 585378,
    "4_sentNum": 119,
    "5_start_ind": 10,
    "6_end_ind": 11,
    "7_lemmas": [
        "0_язык",
        "1_английский"
    ]
},
{
    "0_key": "открытый доступ",
    "1_textForm": "открытом доступе",
    "2_modelName": "Прил + С",
    "3_docNum": 585378,
    "4_sentNum": 119,
    "5_start_ind": 18,
    "6_end_ind": 19,
    "7_lemmas": [
        "0_доступ",
        "1_открытый"
    ]
},
{
    "0_key": "серия эксперимент",
    "1_textForm": "серию экспериментов",
    "2_modelName": "С + Срд",
    "3_docNum": 585378,
    "4_sentNum": 121,
    "5_start_ind": 11,
    "6_end_ind": 12,
    "7_lemmas": [
        "0_серия",
        "1_эксперимент"
    ]
},
{
    "0_key": "цель эксперимент",
    "1_textForm": "целью экспериментов",
    "2_modelName": "С + Срд",
    "3_docNum": 585378,
    "4_sentNum": 122,
    "5_start_ind": 1,
    "6_end_ind": 2,
    "7_lemmas": [
        "0_цель",
        "1_эксперимент"
    ]
},
{
    "0_key": "сформированный датасет",
    "1_textForm": "сформированных датасетов",
    "2_modelName": "Прич + С",
    "3_docNum": 585378,
    "4_sentNum": 122,
    "5_start_ind": 13,
    "6_end_ind": 14,
    "7_lemmas": [
        "0_датасет",
        "1_сформированный"
    ]
},
{
    "0_key": "число сформированный датасет",
    "1_textForm": "числа сформированных датасетов",
    "2_modelName": "C + (Прич + С)рд",
    "3_docNum": 585378,
    "4_sentNum": 122,
    "5_start_ind": 12,
    "6_end_ind": 14,
    "7_lemmas": [
        "0_датасет",
        "1_сформированный",
        "2_число"
    ]
},
{
    "0_key": "диалоговый датасете",
    "1_textForm": "диалоговом датасете",
    "2_modelName": "Прил + С",
    "3_docNum": 585378,
    "4_sentNum": 123,
    "5_start_ind": 18,
    "6_end_ind": 19,
    "7_lemmas": [
        "0_датасете",
        "1_диалоговый"
    ]
},
{
    "0_key": "особенность стиль",
    "1_textForm": "особенности стиля",
    "2_modelName": "С + Срд",
    "3_docNum": 585378,
    "4_sentNum": 124,
    "5_start_ind": 6,
    "6_end_ind": 7,
    "7_lemmas": [
        "0_особенность",
        "1_стиль"
    ]
},
{
    "0_key": "одноэтапный стратегия",
    "1_textForm": "одноэтапных стратегий",
    "2_modelName": "Прил + С",
    "3_docNum": 585378,
    "4_sentNum": 125,
    "5_start_ind": 5,
    "6_end_ind": 6,
    "7_lemmas": [
        "0_стратегия",
        "1_одноэтапный"
    ]
},
{
    "0_key": "очищенный диалог",
    "1_textForm": "очищенных диалогах",
    "2_modelName": "Прич + С",
    "3_docNum": 585378,
    "4_sentNum": 125,
    "5_start_ind": 14,
    "6_end_ind": 15,
    "7_lemmas": [
        "0_диалог",
        "1_очищенный"
    ]
},
{
    "0_key": "диалог и очищенный диалог",
    "1_textForm": "диалогах и очищенных диалогах",
    "2_modelName": "С + СоюзИ + (Прич + С)",
    "3_docNum": 585378,
    "4_sentNum": 125,
    "5_start_ind": 12,
    "6_end_ind": 15,
    "7_lemmas": [
        "0_диалог",
        "1_очищенный",
        "2_и",
        "3_диалог"
    ]
},
{
    "0_key": "двухступенчатый обучение",
    "1_textForm": "двухступенчатом обучении",
    "2_modelName": "Прил + С",
    "3_docNum": 585378,
    "4_sentNum": 126,
    "5_start_ind": 9,
    "6_end_ind": 10,
    "7_lemmas": [
        "0_обучение",
        "1_двухступенчатый"
    ]
},
{
    "0_key": "дополнительный шум",
    "1_textForm": "дополнительный шум",
    "2_modelName": "Прил + С",
    "3_docNum": 585378,
    "4_sentNum": 126,
    "5_start_ind": 14,
    "6_end_ind": 15,
    "7_lemmas": [
        "0_шум",
        "1_дополнительный"
    ]
},
{
    "0_key": "очищенный диалог",
    "1_textForm": "очищенные диалоги",
    "2_modelName": "Прич + С",
    "3_docNum": 585378,
    "4_sentNum": 130,
    "5_start_ind": 1,
    "6_end_ind": 2,
    "7_lemmas": [
        "0_диалог",
        "1_очищенный"
    ]
},
{
    "0_key": "очищенный диалог",
    "1_textForm": "очищенные диалоги",
    "2_modelName": "Прич + С",
    "3_docNum": 585378,
    "4_sentNum": 132,
    "5_start_ind": 2,
    "6_end_ind": 3,
    "7_lemmas": [
        "0_диалог",
        "1_очищенный"
    ]
},
{
    "0_key": "диалоговый пара",
    "1_textForm": "диалоговых пар",
    "2_modelName": "Прил + С",
    "3_docNum": 585378,
    "4_sentNum": 133,
    "5_start_ind": 8,
    "6_end_ind": 9,
    "7_lemmas": [
        "0_пара",
        "1_диалоговый"
    ]
},
{
    "0_key": "набор диалоговый пара",
    "1_textForm": "наборе диалоговых пар",
    "2_modelName": "C + (Прил + С)рд",
    "3_docNum": 585378,
    "4_sentNum": 133,
    "5_start_ind": 7,
    "6_end_ind": 9,
    "7_lemmas": [
        "0_пара",
        "1_диалоговый",
        "2_набор"
    ]
},
{
    "0_key": "эмпирический оценка",
    "1_textForm": "эмпирическим оценкам",
    "2_modelName": "Прил + С",
    "3_docNum": 585378,
    "4_sentNum": 134,
    "5_start_ind": 8,
    "6_end_ind": 9,
    "7_lemmas": [
        "0_оценка",
        "1_эмпирический"
    ]
},
{
    "0_key": "очищенный диалог",
    "1_textForm": "очищенные диалоги",
    "2_modelName": "Прич + С",
    "3_docNum": 585378,
    "4_sentNum": 134,
    "5_start_ind": 17,
    "6_end_ind": 18,
    "7_lemmas": [
        "0_диалог",
        "1_очищенный"
    ]
},
{
    "0_key": "осмысленный фраза",
    "1_textForm": "осмысленные фразы",
    "2_modelName": "Прил + С",
    "3_docNum": 585378,
    "4_sentNum": 135,
    "5_start_ind": 6,
    "6_end_ind": 7,
    "7_lemmas": [
        "0_фраза",
        "1_осмысленный"
    ]
},
{
    "0_key": "двухступенчатый вариант",
    "1_textForm": "двухступенчатый вариант",
    "2_modelName": "Прил + С",
    "3_docNum": 585378,
    "4_sentNum": 136,
    "5_start_ind": 2,
    "6_end_ind": 3,
    "7_lemmas": [
        "0_вариант",
        "1_двухступенчатый"
    ]
},
{
    "0_key": "large версия",
    "1_textForm": "Large версии",
    "2_modelName": "Прил + С",
    "3_docNum": 585378,
    "4_sentNum": 136,
    "5_start_ind": 7,
    "6_end_ind": 8,
    "7_lemmas": [
        "0_версия",
        "1_large"
    ]
},
{
    "0_key": "версия модель",
    "1_textForm": "версии моделей",
    "2_modelName": "С + Срд",
    "3_docNum": 585378,
    "4_sentNum": 136,
    "5_start_ind": 8,
    "6_end_ind": 9,
    "7_lemmas": [
        "0_версия",
        "1_модель"
    ]
},
{
    "0_key": "английский язык",
    "1_textForm": "английского языков",
    "2_modelName": "Прил + С",
    "3_docNum": 585378,
    "4_sentNum": 136,
    "5_start_ind": 17,
    "6_end_ind": 18,
    "7_lemmas": [
        "0_язык",
        "1_английский"
    ]
},
{
    "0_key": "large версия модель",
    "1_textForm": "Large версии моделей",
    "2_modelName": "(Прил + С) + Срд",
    "3_docNum": 585378,
    "4_sentNum": 136,
    "5_start_ind": 7,
    "6_end_ind": 9,
    "7_lemmas": [
        "0_версия",
        "1_large",
        "2_модель"
    ]
},
{
    "0_key": "русский и английский язык",
    "1_textForm": "русского и английского языков",
    "2_modelName": "Прил и (Прил + С)",
    "3_docNum": 585378,
    "4_sentNum": 136,
    "5_start_ind": 15,
    "6_end_ind": 18,
    "7_lemmas": [
        "0_язык",
        "1_английский",
        "2_и",
        "3_русский"
    ]
},
{
    "0_key": "обученный модель",
    "1_textForm": "обученных моделей",
    "2_modelName": "Прич + С",
    "3_docNum": 585378,
    "4_sentNum": 137,
    "5_start_ind": 5,
    "6_end_ind": 6,
    "7_lemmas": [
        "0_модель",
        "1_обученный"
    ]
},
{
    "0_key": "ручной разметка",
    "1_textForm": "ручной разметке",
    "2_modelName": "Прил + С",
    "3_docNum": 585378,
    "4_sentNum": 137,
    "5_start_ind": 19,
    "6_end_ind": 20,
    "7_lemmas": [
        "0_разметка",
        "1_ручной"
    ]
},
{
    "0_key": "качество обученный модель",
    "1_textForm": "качество обученных моделей",
    "2_modelName": "C + (Прич + С)рд",
    "3_docNum": 585378,
    "4_sentNum": 137,
    "5_start_ind": 4,
    "6_end_ind": 6,
    "7_lemmas": [
        "0_модель",
        "1_обученный",
        "2_качество"
    ]
},
{
    "0_key": "реплика недруг",
    "1_textForm": "реплик НЕДРУГА",
    "2_modelName": "С + Срд",
    "3_docNum": 585378,
    "4_sentNum": 138,
    "5_start_ind": 5,
    "6_end_ind": 6,
    "7_lemmas": [
        "0_реплика",
        "1_недруг"
    ]
},
{
    "0_key": "стилистический анализ",
    "1_textForm": "стилистическому анализу",
    "2_modelName": "Прил + С",
    "3_docNum": 585378,
    "4_sentNum": 140,
    "5_start_ind": 21,
    "6_end_ind": 22,
    "7_lemmas": [
        "0_анализ",
        "1_стилистический"
    ]
},
{
    "0_key": "основный эксперимент",
    "1_textForm": "основные эксперименты",
    "2_modelName": "Прил + С",
    "3_docNum": 585378,
    "4_sentNum": 140,
    "5_start_ind": 26,
    "6_end_ind": 27,
    "7_lemmas": [
        "0_эксперимент",
        "1_основный"
    ]
},
{
    "0_key": "раздел по стилистический анализ",
    "1_textForm": "разделе по стилистическому анализу",
    "2_modelName": "С + Предл + (Прил + С)",
    "3_docNum": 585378,
    "4_sentNum": 140,
    "5_start_ind": 19,
    "6_end_ind": 22,
    "7_lemmas": [
        "0_анализ",
        "1_стилистический",
        "2_по",
        "3_раздел"
    ]
},
{
    "0_key": "сгенерированный реплика",
    "1_textForm": "сгенерированные реплики",
    "2_modelName": "Прич + С",
    "3_docNum": 585378,
    "4_sentNum": 141,
    "5_start_ind": 3,
    "6_end_ind": 4,
    "7_lemmas": [
        "0_реплика",
        "1_сгенерированный"
    ]
},
{
    "0_key": "стиль персонаж",
    "1_textForm": "стиль персонажа",
    "2_modelName": "С + Срд",
    "3_docNum": 585378,
    "4_sentNum": 142,
    "5_start_ind": 8,
    "6_end_ind": 9,
    "7_lemmas": [
        "0_стиль",
        "1_персонаж"
    ]
},
{
    "0_key": "английский версия",
    "1_textForm": "английской версии",
    "2_modelName": "Прил + С",
    "3_docNum": 585378,
    "4_sentNum": 145,
    "5_start_ind": 8,
    "6_end_ind": 9,
    "7_lemmas": [
        "0_версия",
        "1_английский"
    ]
},
{
    "0_key": "критерий для английский версия",
    "1_textForm": "критерию для английской версии",
    "2_modelName": "С + Предл + (Прил + С)",
    "3_docNum": 585378,
    "4_sentNum": 145,
    "5_start_ind": 6,
    "6_end_ind": 9,
    "7_lemmas": [
        "0_версия",
        "1_английский",
        "2_для",
        "3_критерий"
    ]
},
{
    "0_key": "ответ герой",
    "1_textForm": "ответ героя",
    "2_modelName": "С + Срд",
    "3_docNum": 585378,
    "4_sentNum": 146,
    "5_start_ind": 5,
    "6_end_ind": 6,
    "7_lemmas": [
        "0_ответ",
        "1_герой"
    ]
},
{
    "0_key": "реплика недруг",
    "1_textForm": "реплике НЕДРУГА",
    "2_modelName": "С + Срд",
    "3_docNum": 585378,
    "4_sentNum": 146,
    "5_start_ind": 10,
    "6_end_ind": 11,
    "7_lemmas": [
        "0_реплика",
        "1_недруг"
    ]
},
{
    "0_key": "отличный день",
    "1_textForm": "Отличный день",
    "2_modelName": "Прил + С",
    "3_docNum": 585378,
    "4_sentNum": 147,
    "5_start_ind": 5,
    "6_end_ind": 6,
    "7_lemmas": [
        "0_день",
        "1_отличный"
    ]
},
{
    "0_key": "сгенерированный модель",
    "1_textForm": "сгенерированный моделью",
    "2_modelName": "Прич + С",
    "3_docNum": 585378,
    "4_sentNum": 150,
    "5_start_ind": 10,
    "6_end_ind": 11,
    "7_lemmas": [
        "0_модель",
        "1_сгенерированный"
    ]
},
{
    "0_key": "заключительный критерий",
    "1_textForm": "Заключительный критерий",
    "2_modelName": "Прил + С",
    "3_docNum": 585378,
    "4_sentNum": 152,
    "5_start_ind": 0,
    "6_end_ind": 1,
    "7_lemmas": [
        "0_критерий",
        "1_заключительный"
    ]
},
{
    "0_key": "сгенерированный предложение",
    "1_textForm": "сгенерированных предложений",
    "2_modelName": "Прич + С",
    "3_docNum": 585378,
    "4_sentNum": 152,
    "5_start_ind": 10,
    "6_end_ind": 11,
    "7_lemmas": [
        "0_предложение",
        "1_сгенерированный"
    ]
},
{
    "0_key": "примитивный фраза",
    "1_textForm": "примитивные фразы",
    "2_modelName": "Прил + С",
    "3_docNum": 585378,
    "4_sentNum": 152,
    "5_start_ind": 16,
    "6_end_ind": 17,
    "7_lemmas": [
        "0_фраза",
        "1_примитивный"
    ]
},
{
    "0_key": "нетривиальность сгенерированный предложение",
    "1_textForm": "нетривиальность сгенерированных предложений",
    "2_modelName": "C + (Прич + С)рд",
    "3_docNum": 585378,
    "4_sentNum": 152,
    "5_start_ind": 9,
    "6_end_ind": 11,
    "7_lemmas": [
        "0_предложение",
        "1_сгенерированный",
        "2_нетривиальность"
    ]
},
{
    "0_key": "сгенерированный модель",
    "1_textForm": "сгенерированные моделями",
    "2_modelName": "Прич + С",
    "3_docNum": 585378,
    "4_sentNum": 154,
    "5_start_ind": 2,
    "6_end_ind": 3,
    "7_lemmas": [
        "0_модель",
        "1_сгенерированный"
    ]
},
{
    "0_key": "модель фраза",
    "1_textForm": "моделями фразы",
    "2_modelName": "С + Срд",
    "3_docNum": 585378,
    "4_sentNum": 154,
    "5_start_ind": 3,
    "6_end_ind": 4,
    "7_lemmas": [
        "0_модель",
        "1_фраза"
    ]
},
{
    "0_key": "трехступенчатый шкала",
    "1_textForm": "трехступенчатой шкале",
    "2_modelName": "Прил + С",
    "3_docNum": 585378,
    "4_sentNum": 154,
    "5_start_ind": 6,
    "6_end_ind": 7,
    "7_lemmas": [
        "0_шкала",
        "1_трехступенчатый"
    ]
},
{
    "0_key": "сгенерированный модель фраза",
    "1_textForm": "сгенерированные моделями фразы",
    "2_modelName": "(Прич + С) + Срд",
    "3_docNum": 585378,
    "4_sentNum": 154,
    "5_start_ind": 2,
    "6_end_ind": 4,
    "7_lemmas": [
        "0_модель",
        "1_сгенерированный",
        "2_фраза"
    ]
},
{
    "0_key": "модель фраза по трехступенчатый шкала",
    "1_textForm": "моделями фразы по трехступенчатой шкале",
    "2_modelName": "(С + Срд) + Предл + (Прил + С)",
    "3_docNum": 585378,
    "4_sentNum": 154,
    "5_start_ind": 3,
    "6_end_ind": 7,
    "7_lemmas": [
        "0_модель",
        "1_фраза",
        "2_по",
        "3_трехступенчатый",
        "4_шкала"
    ]
},
{
    "0_key": "фраза по трехступенчатый шкала",
    "1_textForm": "фразы по трехступенчатой шкале",
    "2_modelName": "С + Предл + (Прил + С)",
    "3_docNum": 585378,
    "4_sentNum": 154,
    "5_start_ind": 4,
    "6_end_ind": 7,
    "7_lemmas": [
        "0_шкала",
        "1_трехступенчатый",
        "2_по",
        "3_фраза"
    ]
},
{
    "0_key": "представлен результат",
    "1_textForm": "представлены результаты",
    "2_modelName": "Прич + С",
    "3_docNum": 585378,
    "4_sentNum": 156,
    "5_start_ind": 1,
    "6_end_ind": 2,
    "7_lemmas": [
        "0_результат",
        "1_представлен"
    ]
},
{
    "0_key": "русский реплика",
    "1_textForm": "русских реплик",
    "2_modelName": "Прил + С",
    "3_docNum": 585378,
    "4_sentNum": 157,
    "5_start_ind": 9,
    "6_end_ind": 10,
    "7_lemmas": [
        "0_реплика",
        "1_русский"
    ]
},
{
    "0_key": "английский транскрипет",
    "1_textForm": "английских транскриптов",
    "2_modelName": "Прил + С",
    "3_docNum": 585378,
    "4_sentNum": 157,
    "5_start_ind": 24,
    "6_end_ind": 25,
    "7_lemmas": [
        "0_транскрипет",
        "1_английский"
    ]
},
{
    "0_key": "оригинальный английский транскрипет",
    "1_textForm": "оригинальных английских транскриптов",
    "2_modelName": "Прил + С",
    "3_docNum": 585378,
    "4_sentNum": 157,
    "5_start_ind": 23,
    "6_end_ind": 25,
    "7_lemmas": [
        "0_транскрипет",
        "1_английский",
        "2_оригинальный"
    ]
},
{
    "0_key": "качество оригинальный английский транскрипет",
    "1_textForm": "качеством оригинальных английских транскриптов",
    "2_modelName": "C + (Прил + С)рд",
    "3_docNum": 585378,
    "4_sentNum": 157,
    "5_start_ind": 22,
    "6_end_ind": 25,
    "7_lemmas": [
        "0_транскрипет",
        "1_английский",
        "2_оригинальный",
        "3_качество"
    ]
},
{
    "0_key": "научный стиль",
    "1_textForm": "научным стилем",
    "2_modelName": "Прил + С",
    "3_docNum": 585378,
    "4_sentNum": 158,
    "5_start_ind": 7,
    "6_end_ind": 8,
    "7_lemmas": [
        "0_стиль",
        "1_научный"
    ]
},
{
    "0_key": "стиль речь",
    "1_textForm": "стилем речи",
    "2_modelName": "С + Срд",
    "3_docNum": 585378,
    "4_sentNum": 158,
    "5_start_ind": 8,
    "6_end_ind": 9,
    "7_lemmas": [
        "0_стиль",
        "1_речь"
    ]
},
{
    "0_key": "научный стиль речь",
    "1_textForm": "научным стилем речи",
    "2_modelName": "(Прил + С) + Срд",
    "3_docNum": 585378,
    "4_sentNum": 158,
    "5_start_ind": 7,
    "6_end_ind": 9,
    "7_lemmas": [
        "0_стиль",
        "1_научный",
        "2_речь"
    ]
},
{
    "0_key": "примитивный стиль",
    "1_textForm": "примитивным стилем",
    "2_modelName": "Прил + С",
    "3_docNum": 585378,
    "4_sentNum": 164,
    "5_start_ind": 9,
    "6_end_ind": 10,
    "7_lemmas": [
        "0_стиль",
        "1_примитивный"
    ]
},
{
    "0_key": "стиль речь",
    "1_textForm": "стилем речи",
    "2_modelName": "С + Срд",
    "3_docNum": 585378,
    "4_sentNum": 164,
    "5_start_ind": 10,
    "6_end_ind": 11,
    "7_lemmas": [
        "0_стиль",
        "1_речь"
    ]
},
{
    "0_key": "примитивный стиль речь",
    "1_textForm": "примитивным стилем речи",
    "2_modelName": "(Прил + С) + Срд",
    "3_docNum": 585378,
    "4_sentNum": 164,
    "5_start_ind": 9,
    "6_end_ind": 11,
    "7_lemmas": [
        "0_стиль",
        "1_примитивный",
        "2_речь"
    ]
},
{
    "0_key": "стиль речь",
    "1_textForm": "стиль речи",
    "2_modelName": "С + Срд",
    "3_docNum": 585378,
    "4_sentNum": 169,
    "5_start_ind": 10,
    "6_end_ind": 11,
    "7_lemmas": [
        "0_стиль",
        "1_речь"
    ]
},
{
    "0_key": "знаменитый сериал",
    "1_textForm": "знаменитого сериала",
    "2_modelName": "Прил + С",
    "3_docNum": 585378,
    "4_sentNum": 169,
    "5_start_ind": 14,
    "6_end_ind": 15,
    "7_lemmas": [
        "0_сериал",
        "1_знаменитый"
    ]
},
{
    "0_key": "мультиязычный анализ",
    "1_textForm": "мультиязычный анализ",
    "2_modelName": "Прил + С",
    "3_docNum": 585378,
    "4_sentNum": 169,
    "5_start_ind": 21,
    "6_end_ind": 22,
    "7_lemmas": [
        "0_анализ",
        "1_мультиязычный"
    ]
},
{
    "0_key": "языковый модель",
    "1_textForm": "языковые модели",
    "2_modelName": "Прил + С",
    "3_docNum": 585378,
    "4_sentNum": 169,
    "5_start_ind": 32,
    "6_end_ind": 33,
    "7_lemmas": [
        "0_модель",
        "1_языковый"
    ]
},
{
    "0_key": "персонаж знаменитый сериал",
    "1_textForm": "персонажей знаменитого сериала",
    "2_modelName": "C + (Прил + С)рд",
    "3_docNum": 585378,
    "4_sentNum": 169,
    "5_start_ind": 13,
    "6_end_ind": 15,
    "7_lemmas": [
        "0_сериал",
        "1_знаменитый",
        "2_персонаж"
    ]
},
{
    "0_key": "больший размер",
    "1_textForm": "бОльшего размера",
    "2_modelName": "Прил + С",
    "3_docNum": 585378,
    "4_sentNum": 170,
    "5_start_ind": 8,
    "6_end_ind": 9,
    "7_lemmas": [
        "0_размер",
        "1_больший"
    ]
},
{
    "0_key": "управляемый генерация",
    "1_textForm": "управляемой генерации",
    "2_modelName": "Прил + С",
    "3_docNum": 585378,
    "4_sentNum": 171,
    "5_start_ind": 11,
    "6_end_ind": 12,
    "7_lemmas": [
        "0_генерация",
        "1_управляемый"
    ]
},
{
    "0_key": "генерация текст",
    "1_textForm": "генерации текстов",
    "2_modelName": "С + Срд",
    "3_docNum": 585378,
    "4_sentNum": 171,
    "5_start_ind": 12,
    "6_end_ind": 13,
    "7_lemmas": [
        "0_генерация",
        "1_текст"
    ]
},
{
    "0_key": "метод управляемый генерация",
    "1_textForm": "методы управляемой генерации",
    "2_modelName": "C + (Прил + С)рд",
    "3_docNum": 585378,
    "4_sentNum": 171,
    "5_start_ind": 10,
    "6_end_ind": 12,
    "7_lemmas": [
        "0_генерация",
        "1_управляемый",
        "2_метод"
    ]
},
{
    "0_key": "управляемый генерация текст",
    "1_textForm": "управляемой генерации текстов",
    "2_modelName": "(Прил + С) + Срд",
    "3_docNum": 585378,
    "4_sentNum": 171,
    "5_start_ind": 11,
    "6_end_ind": 13,
    "7_lemmas": [
        "0_генерация",
        "1_управляемый",
        "2_текст"
    ]
},
{
    "0_key": "совместный труд",
    "1_textForm": "совместных трудов",
    "2_modelName": "Прил + С",
    "3_docNum": 585378,
    "4_sentNum": 173,
    "5_start_ind": 3,
    "6_end_ind": 4,
    "7_lemmas": [
        "0_труд",
        "1_совместный"
    ]
},
{
    "0_key": "покорный слуга",
    "1_textForm": "покорная слуга",
    "2_modelName": "Прил + С",
    "3_docNum": 585378,
    "4_sentNum": 173,
    "5_start_ind": 37,
    "6_end_ind": 38,
    "7_lemmas": [
        "0_слуга",
        "1_покорный"
    ]
},
{
    "0_key": "результат совместный труд",
    "1_textForm": "результат совместных трудов",
    "2_modelName": "C + (Прил + С)рд",
    "3_docNum": 585378,
    "4_sentNum": 173,
    "5_start_ind": 2,
    "6_end_ind": 4,
    "7_lemmas": [
        "0_труд",
        "1_совместный",
        "2_результат"
    ]
},
{
    "0_key": "покорный слуга и рассказчица",
    "1_textForm": "покорная слуга и рассказчица",
    "2_modelName": "(Прил + С) + СоюзИ + С",
    "3_docNum": 585378,
    "4_sentNum": 173,
    "5_start_ind": 37,
    "6_end_ind": 40,
    "7_lemmas": [
        "0_слуга",
        "1_покорный",
        "2_и",
        "3_рассказчица"
    ]
},
{
    "0_key": "совместный работа",
    "1_textForm": "совместную работу",
    "2_modelName": "Прил + С",
    "3_docNum": 585378,
    "4_sentNum": 174,
    "5_start_ind": 4,
    "6_end_ind": 5,
    "7_lemmas": [
        "0_работа",
        "1_совместный"
    ]
},
{
    "0_key": "креативный идея",
    "1_textForm": "креативные идеи",
    "2_modelName": "Прил + С",
    "3_docNum": 585378,
    "4_sentNum": 174,
    "5_start_ind": 12,
    "6_end_ind": 13,
    "7_lemmas": [
        "0_идея",
        "1_креативный"
    ]
},
{
    "0_key": "развитие проект",
    "1_textForm": "развитие проекта",
    "2_modelName": "С + Срд",
    "3_docNum": 585378,
    "4_sentNum": 174,
    "5_start_ind": 18,
    "6_end_ind": 19,
    "7_lemmas": [
        "0_развитие",
        "1_проект"
    ]
},
{
    "0_key": "вклад в развитие проект",
    "1_textForm": "вклад в развитие проекта",
    "2_modelName": "С + Предл + (С + Срд)",
    "3_docNum": 585378,
    "4_sentNum": 174,
    "5_start_ind": 16,
    "6_end_ind": 19,
    "7_lemmas": [
        "0_развитие",
        "1_проект",
        "2_в",
        "3_вклад"
    ]
},
{
    "0_key": "руководитель курс",
    "1_textForm": "руководителем курсов",
    "2_modelName": "С + Срд",
    "3_docNum": 585378,
    "4_sentNum": 176,
    "5_start_ind": 9,
    "6_end_ind": 10,
    "7_lemmas": [
        "0_руководитель",
        "1_курс"
    ]
},
{
    "0_key": "бесплатный мероприятие",
    "1_textForm": "бесплатные мероприятия",
    "2_modelName": "Прил + С",
    "3_docNum": 585378,
    "4_sentNum": 176,
    "5_start_ind": 27,
    "6_end_ind": 28,
    "7_lemmas": [
        "0_мероприятие",
        "1_бесплатный"
    ]
},
{
    "0_key": "рамка вебинар",
    "1_textForm": "рамках вебинаров",
    "2_modelName": "С + Срд",
    "3_docNum": 585378,
    "4_sentNum": 177,
    "5_start_ind": 1,
    "6_end_ind": 2,
    "7_lemmas": [
        "0_рамка",
        "1_вебинар"
    ]
},
{
    "0_key": "рамка вебинар формат",
    "1_textForm": "рамках вебинаров формата",
    "2_modelName": "С + Срд",
    "3_docNum": 585378,
    "4_sentNum": 177,
    "5_start_ind": 1,
    "6_end_ind": 3,
    "7_lemmas": [
        "0_рамка",
        "1_вебинар",
        "2_формат"
    ]
},
{
    "0_key": "вебинар формат",
    "1_textForm": "вебинаров формата",
    "2_modelName": "С + Срд",
    "3_docNum": 585378,
    "4_sentNum": 177,
    "5_start_ind": 2,
    "6_end_ind": 3,
    "7_lemmas": [
        "0_вебинар",
        "1_формат"
    ]
},
{
    "0_key": "процесс обучение",
    "1_textForm": "процессом обучения",
    "2_modelName": "С + Срд",
    "3_docNum": 585378,
    "4_sentNum": 177,
    "5_start_ind": 19,
    "6_end_ind": 20,
    "7_lemmas": [
        "0_процесс",
        "1_обучение"
    ]
},
{
    "0_key": "программа и процесс обучение",
    "1_textForm": "программой и процессом обучения",
    "2_modelName": "С + СоюзИ + (С + Срд)",
    "3_docNum": 585378,
    "4_sentNum": 177,
    "5_start_ind": 17,
    "6_end_ind": 20,
    "7_lemmas": [
        "0_процесс",
        "1_обучение",
        "2_и",
        "3_программа"
    ]
}
]